Workbook

Sheet Extended Profile (EP)
A1: Criteria | B1: Metric Num | C1: Metric Description
A2: 1 Student: | B2: 1.1 | C2: Number of students year wise during the last five years
B3: Year
B4: Number
A5: 2 Teachers: | B5: 2.1 | C5: Number of full time teachers during the last five years (Without repeat count):
B6: 2.2 | C6: Number of full time teachers year wise during the last five years
B7: Year
B8: Number
A9: 3. Expenditure: | B9: 3.1 | C9: Expenditure excluding salary component year wise during the last five years (INR in lakhs)
B10: Year
B11: INR in Lakhs

Sheet Response Score Calc.
A2: S. No | B2: Criteria © | C2: Key Indicator (KI) | D2: Metric (M) Type | E2: Metric (M) Num | F2: Metric (M) Description | G2: M Wt | H2: HEI I/P (Response) | I2: P Response Score
A3: =SUBTOTAL(3,$B$3:B3) -> 1 | B3: 1. Curricular Aspects | C3: 1.2 Academic Flexibility | D3: QlM | E3: 1.1.1 | F3: Curricula developed and implemented have relevance to the local, national, regional and global developmental needs which is reflected in Programme outcomes (POs), Programme Specific outcomes (PSOs) and Course Outcomes (COs) of the Programmes offered by the Institution Write description in maximum of 500 words | G3: 20
A4: =SUBTOTAL(3,$B$3:B4) -> 2 | B4: 1. Curricular Aspects | C4: 1.2 Academic Flexibility | D4: QnM | E4: 1.1.2 | F4: Percentage of Programmes where syllabus revision was carried out during the last five years 1.1.2.1: How many Programmes were revised out of total number of Programmes offered during the same period within last five years? 1.1.2.2 : Number of all Programmes offered by the institution during the last five years | G4: 20 | H4: 4 (= 100%)
A5: =SUBTOTAL(3,$B$3:B5) -> 3 | B5: 1. Curricular Aspects | C5: 1.3 Curriculum Enrichment | D5: QnM | E5: 1.1.3 | F5: Average percentage of courses having focus on employability/ entrepreneurship/ skill development offered by the institution during the last five years 1.1.3.1: Number of courses having focus on employability/ entrepreneurship/ skill development year wise during last five years | G5: 10 | H5: 4 (= 100%)
A6: =SUBTOTAL(3,$B$3:B6) -> 4 | B6: 1. Curricular Aspects | C6: 1.4 Feedback System | D6: QnM | E6: 1.2.1 | F6: Percentage of new courses introduced of the total number of courses across all programs offered during the last five years 1.2.1.1: How many new courses are introduced within the last five years 1.2.1.2 : Number of courses offered by the institution across all Programmes during the last five years | G6: 20 | H6: 4 (> 50%)
A7: =SUBTOTAL(3,$B$3:B7) -> 5 | B7: 2. Teaching-Learning and Evaluation | C7: 2.1 Student Enrolment and Profile | D7: QnM | E7: 1.2.2 | F7: Percentage of Programmes in which Choice Based Credit System (CBCS)/elective course system has been implemented (Data for the latest completed academic year ) 1.2.2.1: Number of Programmes in which CBCS/Elective course system implemented. | G7: 20 | H7: 4 (= 100%)
A8: =SUBTOTAL(3,$B$3:B8) -> 6 | B8: 2. Teaching-Learning and Evaluation | C8: 2.1 Student Enrolment and Profile | D8: QlM | E8: 1.3.1 | F8: Institution integrates crosscutting issues relevant to Professional Ethics, Gender, Human Values, Environment and Sustainability, Human Values into the Curriculum Write description in maximum of 500 words | G8: 10
A9: =SUBTOTAL(3,$B$3:B9) -> 7 | B9: 2. Teaching-Learning and Evaluation | C9: 2.2 Student Teacher Ratio | D9: QnM | E9: 1.3.2 | F9: Number of value-added courses for imparting transferable and life skills offered during last five years 1.3.2.1: How many new value-added courses are added within the last 5 years | G9: 10 | H9: 4 (> 100)
A10: =SUBTOTAL(3,$B$3:B10) -> 8 | B10: 2. Teaching-Learning and Evaluation | C10: 2.4 Teacher Profile and Quality | D10: QnM | E10: 1.3.3 | F10: Average Percentage of students enrolled in the courses under 1.3.2 above 1.3.3.1: Number of students enrolled in value added courses (beyond the curriculum) offered year wise during last five year | G10: 10 | H10: 4 (> 75%)
A11: =SUBTOTAL(3,$B$3:B11) -> 9 | B11: 2. Teaching-Learning and Evaluation | C11: 2.4 Teacher Profile and Quality | D11: QnM | E11: 1.3.4 | F11: Percentage of students undertaking field projects/ internships / student projects (Data for the latest completed academic year) 1.3.4.1: Number of students undertaking field projects / internships / student projects | G11: 10 | H11: 4 (> 90%)
A12: =SUBTOTAL(3,$B$3:B12) -> 10 | B12: 2. Teaching-Learning and Evaluation | C12: 2.6 Student Performance and Learning Outcomes | D12: QnM | E12: 1.4.1 | F12: Structured feedback for design and review of syllabus ( semester wise / year wise) is obtained from 1) Students, 2) Teachers, 3) Employers, 4) Alumni | G12: 10 | H12: 4 (all of the Above)
A13: =SUBTOTAL(3,$B$3:B13) -> 11 | B13: 2. Teaching-Learning and Evaluation | C13: 2.7 Student Satisfaction Survey | D13: QnM | E13: 1.4.2 | F13: The feedback system of the Institution comprises of the following : A. Feedback collected, analysed and action taken and report made available on website B. Feedback collected, analysed and action taken C. Feedback collected and analysed D. Feedback collected E. Feedback not obtained | G13: 10 | H13: 4 (all of the Above)
A14: =SUBTOTAL(3,$B$3:B14) -> 12 | B14: 3. Research, Innovations and Extension | C14: 3.1 Resource Mobilization for Research | D14: QnM | E14: 2.1.1 | F14: Average Enrolment percentage (Average of last five years) 2.1.1.1: Number of students admitted year wise during last five years 2.1.1.2: Number of sanctioned seats year wise during last five years | G14: 10 | H14: 4 (> 90)
A15: =SUBTOTAL(3,$B$3:B15) -> 13 | B15: 3. Research, Innovations and Extension | C15: 3.2 Innovation Ecosystem | D15: QnM | E15: 2.1.2 | F15: Average percentage of seats filled against reserved categories (SC, ST, OBC, Divyangjan, etc. as per applicable reservation policy ) during the last five years ( exclusive of supernumerary seats) 2.1.2.1: Number of actual students admitted from the reserved categories year wise during last five years | G15: 10 | H15: 4 (> 90)
A16: =SUBTOTAL(3,$B$3:B16) -> 14 | B16: 3. Research, Innovations and Extension | C16: 3.3 Research Publications and Awards | D16: QlM | E16: 2.2.1 | F16: The institution assesses the learning levels of the students and organises special Programmes for advanced learners and slow learners. Write description in of 500 words | G16: 15
A17: =SUBTOTAL(3,$B$3:B17) -> 15 | B17: 3. Research, Innovations and Extension | C17: 3.3 Research Publications and Awards | D17: QnM | E17: 2.2.2 | F17: Student - Full time teacher ratio (Data for the latest completed academic year) | G17: 15 | H17: 4 (15 : 01)
A18: =SUBTOTAL(3,$B$3:B18) -> 16 | B18: 3. Research, Innovations and Extension | C18: 3.4 Extension Activities | D18: QlM | E18: 2.3.1 | F18: Student centric methods, such as experiential learning, participative learning and problem solving methodologies are used for enhancing learning experiences Write description in maximum of 500 words | G18: 15
A19: =SUBTOTAL(3,$B$3:B19) -> 17 | B19: 3. Research, Innovations and Extension | C19: 3.5 Collaboration | D19: QlM | E19: 2.3.2 | F19: Teachers use ICT enabled tools including online resources for effective teaching and learning process Write description in maximum of 500 words | G19: 15
A20: =SUBTOTAL(3,$B$3:B20) -> 18 | B20: 4. Infrastructure and Learning Resources | C20: 4.1 Physical Facilities | D20: QnM | E20: 2.3.3 | F20: Ratio of students to mentor for academic and other related issues (Data for the latest completed academic year ) 2.3.3.1: Number of mentors Number of students assigned to each Mentor | G20: 10 | H20: 4 (15-20)
A21: =SUBTOTAL(3,$B$3:B21) -> 19 | B21: 4. Infrastructure and Learning Resources | C21: 4.3 IT Infrastructure | D21: QlM | E21: 2.3.4 | F21: Preparation and adherence of Academic Calendar and Teaching plans by the institution Describe the Preparation and adherence to Academic Calendar and Teaching plans by the institution within the minimum of 500 Characters and maximum of 500 words. | G21: 10
A22: =SUBTOTAL(3,$B$3:B22) -> 20 | B22: 4. Infrastructure and Learning Resources | C22: 4.4 Maintenance of Campus Infrastructure | D22: QnM | E22: 2.4.1 | F22: Average percentage of full time teachers against sanctioned posts during the last five years | G22: 15 | H22: 4 (100)
A23: =SUBTOTAL(3,$B$3:B23) -> 21 | B23: 5. Student Support and Progression | C23: 5.1 Student Support | D23: QnM | E23: 2.4.2 | F23: Average percentage of full time teachers with Ph.D. / D.M. / M.Ch. / D.N.B Super speciality / D.Sc. / D.Litt. during the last five years 2.4.2.1: Number of full time teachers with Ph.D./ D.M. / M.Ch. / D.N.B Super speciality / D.Sc. / D.Litt. year wise during last five years | G23: 20 | H23: 4 (> 80)
A24: =SUBTOTAL(3,$B$3:B24) -> 22 | B24: 5. Student Support and Progression | C24: 5.1 Student Support | D24: QnM | E24: 2.4.3 | F24: Average teaching experience of full time teachers in the same institution (Data for the latest completed academic year in number of years 2.4.3.1: Total experience of full-time teachers | G24: 15 | H24: 4 (> 15)
A25: =SUBTOTAL(3,$B$3:B25) -> 23 | B25: 5. Student Support and Progression | C25: 5.1 Student Support | D25: QnM | E25: 2.5.1 | F25: Average number of days from the date of last semester-end/ year- end examination till the declaration of results during the last five years 2.5.1.1: Number of days from the date of last semester-end/ year- end examination till the declaration of results year wise during the last five years | G25: 20 | H25: 4 (< 10-15)
A26: =SUBTOTAL(3,$B$3:B26) -> 24 | B26: 5. Student Support and Progression | C26: 5.1 Student Support | D26: QnM | E26: 2.5.2 | F26: Average percentage of student complaints/grievances about evaluation against total number appeared in the examinations during the last five years 2.5.2.1: Number of complaints/grievances about evaluation year wise during last five years | G26: 15 | H26: 4 (< 1)
A27: =SUBTOTAL(3,$B$3:B27) -> 25 | B27: 5. Student Support and Progression | C27: 5.2 Student Progression | D27: QlM | E27: 2.5.3 | F27: IT integration and reforms in the examination procedures and processes including Continuous Internal Assessment (CIA) have brought in considerable improvement in Examination Management System (EMS) of the Institution Describe the examination reforms with reference to the following within a minimum of 500 words and maximum 1000 words: | G27: 15
A28: =SUBTOTAL(3,$B$3:B28) -> 26 | B28: 5. Student Support and Progression | C28: 5.2 Student Progression | D28: QlM | E28: 2.6.1 | F28: Programme outcomes and course outcomes for all Programmes offered by the institution are stated and displayed on website and communicated to teachers and students Describe Course Outcomes (COs) for all courses and mechanism of communication within a maximum of 500 words | G28: 20
A29: =SUBTOTAL(3,$B$3:B29) -> 27 | B29: 5. Student Support and Progression | C29: 5.3 Student Participation and Activities | D29: QlM | E29: 2.6.2 | F29: Attainment of program outcomes and course outcomes are evaluated by the institution Describe the method of measuring attainment of POs , PSOs and COs in not more than 500 words and the level of attainment of POs , PSOs and COs. | G29: 10
A30: =SUBTOTAL(3,$B$3:B30) -> 28 | B30: 5. Student Support and Progression | C30: 5.3 Student Participation and Activities | D30: QnM | E30: 2.6.3 | F30: Pass percentage of students (Data for the latest completed academic year) 2.6.3.1: Total number of final year students who passed the examination conducted by Institution. 2.6.3.2: Total number of final year students who appeared for the examination | G30: 20 | H30: 4 (> 90%)
A31: =SUBTOTAL(3,$B$3:B31) -> 29 | B31: 6. Governance, Leadership and Management | C31: 6.2 Strategy Development and Deployment | D31: QnM | E31: 2.7.1 | F31: Online student satisfaction survey regarding to teaching learning process. (Online survey to be conducted) | G31: 50 | H31: 3.5 (>3.5)
A32: =SUBTOTAL(3,$B$3:B32) -> 30 | B32: 6. Governance, Leadership and Management | C32: 6.3 Faculty Empowerment Strategies | D32: QlM | E32: 3.1.1 | F32: The institution Research facilities are frequently updated and there is well defined policy for promotion of research which is uploaded on the institutional website and implemented Write description in maximum of 500 words | G32: 6
A33: =SUBTOTAL(3,$B$3:B33) -> 31 | B33: 6. Governance, Leadership and Management | C33: 6.3 Faculty Empowerment Strategies | D33: QnM | E33: 3.1.2 | F33: The institution provides seed money to its teachers for research (Average per year) 3.1.2.1: The amount of seed money provided by institution to its teachers for research year wise during last five years (INR in lakhs) | G33: 8 | H33: 4 (> 10L)
A34: =SUBTOTAL(3,$B$3:B34) -> 32 | B34: 6. Governance, Leadership and Management | C34: 6.5 Internal Quality Assurance System (IQAS) | D34: QnM | E34: 3.1.3 | F34: Percentage of teachers awarded national / international fellowship for advanced studies/research during the last five years 3.1.3.1: The number of teachers awarded national / international fellowship for advanced studies / research year wise during last five years | G34: 6 | H34: 4 (>10%)
A35: =SUBTOTAL(3,$B$3:B35) -> 33 | B35: 7. Institutional Values and Best Practices | C35: 7.1 Institutional Values and Social Responsibilities | D35: QnM | E35: 3.2.1 | F35: Grants received from Government and non-governmental agencies for research projects, endowments, Chairs in the institution during the last five years (INR in Lakhs) 3.2.1.1: Total Grants from Government and non-governmental agencies for research projects , endowments, Chairs in the institution during the last five years (INR in Lakhs) | G35: 2 | H35: 4 (> 300L)
A36: =SUBTOTAL(3,$B$3:B36) -> 34 | B36: 7. Institutional Values and Best Practices | C36: 7.1 Institutional Values and Social Responsibilities | D36: QnM | E36: 3.2.2 | F36: Percentage of teachers having research projects during the last five years 3.2.2.1: Number of teachers having research projects during the last five years | G36: 2 | H36: 4 (> 3)
D37: QnM | E37: 3.2.3 | F37: Percentage of teachers recognised as research guides 3.2.3.1: Number of teachers recognised as research guides | G37: 3 | H37: 4 (> 20)
D38: QnM | E38: 3.2.4 | F38: Average percentage of departments having Research projects funded by government and non-government agencies during the last five years 3.2.4.1: Number of departments having Research projects funded by government and non-government agencies during the last five years | G38: 3 | H38: 4 (> 40)
D39: QlM | E39: 3.3.1 | F39: Institution has created an eco system for innovations, creation and transfer of knowledge supported by dedicated centers for research, entrepreneurship, community orientation, Incubation etc. Write description in maximum of 500 words | G39: 5
D40: QnM | E40: 3.3.2 | F40: Number of workshops/seminars conducted on Research Methodology, Intellectual Property Rights (IPR), entrepreneurship and skills development during the last five years 3.3.2.1: Total number of workshops/seminars conducted on Research Methodology, Intellectual Property Rights (IPR) and entrepreneurship and skills development year wise during last five years | G40: 5 | H40: 4 (> 80)
D41: QnM | E41: 3.4.1 | F41: The Institution ensures implementation of its stated Code of Ethics for research through the following: 1. Inclusion of research ethics in the research methodology course work 2. Presence of Ethics committee 3. Plagiarism check through software 4. Research Advisory Committee | G41: 5 | H41: 4 (all of the Above)
D42: QnM | E42: 3.4.2 | F42: Number of Ph.D’s registered per teacher (as per the data given w.r.t recognized Ph.D guides/ supervisors provided at 3.2.3 metric) during the last five years 3.4.2.1: How many Ph.Ds are registered within last 5 years 3.4.2.2 : Number of teachers recognized as guides during the last five years | G42: 5 | H42: 4 (> 5)
D43: QnM | E43: 3.4.3 | F43: Number of research papers per teacher in the Journals notified on UGC website during the last five years 3.4.3.1: Number of research papers in the Journals notified on UGC website during the last five | G43: 5 | H43: 4 (> 5)
D44: QnM | E44: 3.4.4 | F44: Number of books and chapters in edited volumes / books published per teacher during the last five years 3.4.4.1: Total number of books and chapters in edited volumes / books published, and papers in national/international conference-proceedings year wise during last five years | G44: 5 | H44: 4 (> 5)
D45: QnM | E45: 3.4.5 | F45: Bibliometrics of the publications during the last five years based on average Citation index in Scopus/ Web of Science/ PubMed 3.4.5.1: Total number of Citations in Scopus in 5 years Total number of Citations in Web of Science in 5 years 3.4.5.2 : Total number of Publications in Scopus in 5 years Total number of Publications in Web of Science in 5 years | G45: 5 | H45: 4 (> 10)
D46: QnM | E46: 3.4.6 | F46: Bibliometrics of the publications during the last five years based on Scopus/ Web of Science – h-index of the Institution 3.4.6.1: h-index of Scopus during the last five years h-index of Web of Science during the last five years | G46: 5 | H46: 4 (> 50)
D47: QnM | E47: 3.5.1 | F47: Revenue generated from consultancy and corporate training during the last five years (INR in Lakhs) 3.5.1.1: Total amount generated from consultancy and corporate training year wise during last five years (INR in lakhs) | G47: 5 | H47: 4 (> 100L)
D48: QnM | E48: 3.5.2 | F48: Total amount spent on developing facilities, training teachers and staff for undertaking consultancy during the last five years 3.5.2.1: Total amount spent on developing facilities, training teachers and staff for undertaking consultancy during the last five years | G48: 5 | H48: 4 (> 300L)
D49: QlM | E49: 3.6.1 | F49: Extension activities are carried out in the neighbourhood community, sensitising students to social issues, for their holistic development, and impact thereof during the last five years Describe the impact of extension activities in sensitising students to social issues and holistic development within a maximum of 500 words | G49: 10
D50: QnM | E50: 3.6.2 | F50: Number of awards and recognition received by the Institution, its teachers and students for extension activities from Government / Government recognised bodies during last five years 3.6.2.1: Total number of awards and recognition received for extension activities from Government /recognised bodies year wise during last five years | G50: 15 | H50: 4 (> 30)
D51: QnM | E51: 3.6.3 | F51: Number of extension and outreach programs conducted by the institution through NSS/NCC/Red cross/YRC etc., during the last five years ( including Government initiated programs such as Swachh Bharat, Aids Awareness, Gender Issue, etc. and those organised in collaboration with industry, community and NGOs) 3.6.3.1: Number of extension and outreach programs conducted in collaboration with industry, community and Non-Government Organisations through NSS/NCC/Red cross/YRC etc., year wise during last five years | G51: 10 | H51: 4 (> 150)
D52: QnM | E52: 3.6.4 | F52: Average percentage of students participating in extension activities listed at 3.6.3 above during the last five years 3.6.4.1: Total number of students participating in extension activities with Government Organisations, Non-Government Organisations and Programmes such as Swachh Bharat, Aids Awareness, Gender Issue, etc. year wise during last five years | G52: 15 | H52: 4 (> 90)
D53: QnM | E53: 3.7.1 | F53: Number of Collaborative activities per year for research/ faculty exchange/ student exchange/ internship/ on –the-job training/ project work 3.7.1.1: Total number of Collaborative activities per year for research/ faculty exchange/ student exchange/ internship/ on –the-job training/ project work | G53: 10 | H53: 4 (> 100)
D54: QnM | E54: 3.7.2 | F54: Number of functional MoUs with institutions of national, international importance, other universities, industries, corporate houses etc. during the last five years (only functional MoUs with ongoing activities to be considered) 3.7.2.1: Number of functional MoUs with institutions of national, international importance, other Institutions, industries, corporate houses etc. year wise during last five years Data Template | G54: 10 | H54: 4 (> 80)
D55: QlM | E55: 4.1.1 | F55: The Institution has adequate infrastructure and physical facilities for teaching – learning, viz., classrooms, laboratories, computing equipment, etc. Describe the adequacy of facilities for teaching –learning as per the minimum specified requirement by statutory bodies within a maximum of 500 words | G55: 6
D56: QlM | E56: 4.1.2 | F56: The institution has adequate facilities for cultural activities, yoga, games (indoor, outdoor) and sports. (gymnasium, yoga centre, auditorium, etc.) Describe the adequacy facilities for cultural activities, yoga, games (indoor, outdoor) and sports which include specification about area/size, year of establishment and user rate within minimum of 500 characters and maximum of 500 words | G56: 4
D57: QnM | E57: 4.1.3 | F57: Percentage of classrooms and seminar halls with ICT – enabled facilities such as smart class, LMS, etc. (Data for the latest completed academic year) 4.1.3.1: Number of classrooms and seminar halls with ICT facilities | G57: 10 | H57: 4 (> 90)
D58: QnM | E58: 4.1.4 | F58: Average percentage of expenditure for infrastructure augmentation excluding salary during the last five years (INR in Lakhs) 4.1.4.1: Expenditure for infrastructure augmentation, excluding salary year wise during last five years (INR in lakhs) | G58: 10 | H58: 4 (> 50)
D59: QlM | E59: 4.2.1 | F59: Library is automated using Integrated Library Management System (ILMS) | G59: 5
D60: QnM | E60: 4.2.2 | F60: Institution has access to the following: 1. e-journals 2. e-ShodhSindhu 3. Shodhganga Membership 4. e-books 5. Databases 6. Remote access to e-resources | G60: 5 | H60: 4 (all of the Above)
D61: QnM | E61: 4.2.3 | F61: Average annual expenditure for purchase of books/ e-books and subscription to journals/e-journals during the last five years (INR in Lakhs) 4.2.3.1: Annual expenditure for purchase of books / e-books and subscription to journals/e-journals year wise during last five years (INR in lakhs) | G61: 5 | H61: 4 (> 20L)
D62: QnM | E62: 4.2.4 | F62: Percentage per day usage of library by teachers and students ( foot falls and login data for online access) 4.2.6.1: Number of teachers and students using library per day over last one year | G62: 5 | H62: 4 (> 20%)
D63: QlM | E63: 4.3.1 | F63: Institution has an IT policy covering wi-fi, cyber security, etc., and allocated budget for updating its IT facilities Describe IT facilities including Wi-Fi with date and nature of updation within a maximum of 500 words | G63: 8
D64: QnM | E64: 4.3.2 | F64: Student - Computer ratio(Data for the latest completed academic year) | G64: 8 | H64: 4 (< 4:1)
D65: QnM | E65: 4.3.3 | F65: Bandwidth of internet connection in the Institution Options: A. ≥50 MBPS B. 35 MBPS - 50 MBPS C. 20 MBPS - 35 MBPS Opt One D. 5 MBPS - 20 MBPS E. <5 MBPS | G65: 10 | H65: 4 (all of the Above)
D66: QnM | E66: 4.3.4 | F66: Institution has Facilities for e-content development Facilities available for e-content development : 1. Media centre 2. Audio visual centre, 3. Lecture Capturing System(LCS) 4. Mixing equipment's and software's for editing | G66: 4 | H66: 4 (all of the Above)
D67: QnM | E67: 4.4.1 | F67: Average percentage expenditure incurred on maintenance of physical facilities and academic support facilities excluding salary component, during the last five years 4.4.1.1: Expenditure incurred on maintenance of physical facilities and academic support facilities excluding salary component year wise during last five years (INR in lakhs) | G67: 10 | H67: 4 (> 25%)
D68: QlM | E68: 4.4.2 | F68: There are established systems and procedures for maintaining and utilizing physical, academic and support facilities – laboratory, library, sports complex, computers, classrooms etc. Describe policy details of systems and procedures for maintaining and utilizing physical, academic and support facilities on the website within a minimum of 500 word and maximum of 1000 words | G68: 10
D69: QnM | E69: 5.1.1 | F69: Average percentage of students benefited by scholarships and freeships provided by the Government during the last five years 5.1.1.1: Number of students benefited by scholarships and freeships provided by the Government year wise during last five years | G69: 6 | H69: 4 (> 50%)
D70: QnM | E70: 5.1.2 | F70: Average percentage of students benefited by scholarships, freeships, etc. provided by the institution and non-government agencies during the last five years 5.1.2.1: Total number of students benefited by scholarships, freeships, etc provided by the institution and non-government agencies year wise during last five years | G70: 5 | H70: 4 (> 10%)
D71: QnM | E71: 5.1.3 | F71: Following Capacity development and skills enhancement activities are organised for improving students capability 1. Soft skills 2. Language and communication skills 3. Life skills (Yoga, physical fitness, health and hygiene) 4. Awareness of trends in technology | G71: 8 | H71: 4 (all of the Above)
D72: QnM | E72: 5.1.4 | F72: Average percentage of students benefited by guidance for competitive examinations and career counselling offered by the institution during the last five years 5.1.4.1: Number of students benefited by guidance for competitive examinations and career counselling offered by the institution year wise during last five years | G72: 6 | H72: 4 (> 80%)
D73: QnM | E73: 5.1.5 | F73: The institution adopts the following for redressal of student grievances including sexual harassment and ragging cases 1. Implementation of guidelines of statutory/regulatory bodies 2. Organisation wide awareness and undertakings on policies with zero tolerance 3. Mechanisms for submission of online/offline students’ grievances 4. Timely redressal of the grievances through appropriate committees | G73: 5 | H73: 4 (all of the Above)
D74: QnM | E74: 5.2.1 | F74: Average percentage of placement of outgoing students during the last five years 5.2.1.1: Number of outgoing students placed year wise during last five years | G74: 10 | H74: 4 (> 60%)
D75: QnM | E75: 5.2.2 | F75: Percentage of student progression to higher education (previous graduating batch) 5.2.2.1: Number of outgoing students progressing to higher education Data Requirements: (As per Data Template) Number of students proceeding from UG to PG:. PG to MPhil: PG to PhD: MPhil to PhD: PhD to Post doctoral: | G75: 10 | H75: 4 (> 30%)
D76: QnM | E76: 5.2.3 | F76: Average percentage of students qualifying in state/ national/ international level examinations during the last five years (eg: IIT/JAM/NET/SLET/GATE/GMAT/CAT/ GRE/TOEFL/Civil Services/State government examinations etc.) 5.2.3.1: Number of students qualifying in state/ national/ international level examinations (eg: IIT/JAM/NET/SLET/GATE/GMAT/CAT/ GRE/TOEFL/Civil Services/State government examinations) year wise during last five years 5.2.3.2: Number of students appearing in state/ national/ international level examinations (eg: IIT/JAM/ NET/SLET/GATE/GMAT/CAT, GRE/TOEFL/Civil Services/State government examinations) year wise during last five years | G76: 10 | H76: 4 (> 80%)
D77: QnM | E77: 5.3.1 | F77: Number of awards/medals for outstanding performance in sports/cultural activities at inter-university / state /national / international events (award for a team event should be counted as one) during the last five years 5.3.1.1: Number of awards/medals for outstanding performance in sports/cultural activities at inter-university / state / national / international level (award for a team event should be counted as one) year wise during last five years | G77: 10 | H77: 4 (> 100)
D78: QlM | E78: 5.3.2 | F78: Presence of an active Student Council & representation of students on academic & administrative bodies/committees of the institution Describe the Student Council activity and students role in academic & administrative bodies within a minimum of 500 characters and maximum of 500 words | G78: 10
D79: QnM | E79: 5.3.3 | F79: Average number of sports and cultural events / competitions organised by the institution per year 5.3.3.1: Number of sports and cultural events / competitions organised by the institution year wise during last five years | G79: 10 | H79: 4 (> 30)
D80: QlM | E80: 5.4.1 | F80: The Alumni Association/Chapters (registered and functional)contributes significantly to the development of the institution through financial and other support services Describe contribution of alumni association to the institution within a maximum of 500 words | G80: 5
D81: QnM | E81: 5.4.2 | F81: Alumni financial contribution during the last five years (in INR) Options: A. ≥ 15 Lakhs B. 10Lakhs - 15 Lakhs C. 5 Lakhs - 10 Lakhs D. 2 Lakhs - 5 | G81: 5 | H81: 4 (>15 L)
D82: QlM | E82: 6.1.1 | F82: The governance of the institution is reflective of an effective leadership in tune with the vision and mission of the Institution Describe the vision and mission statement of the institution on the nature of governance, perspective plans and participation of the teachers in the decision making bodies of the institution within a maximum of 500 words. | G82: 5
D83: QlM | E83: 6.1.2 | F83: The effective leadership is reflected in various institutional practices such as decentralization and participative management Upload a case study showing practicing decentralisation and participative management in the institution in not more than 500 words | G83: 5
D84: QlM | E84: 6.2.1 | F84: The institutional Strategic/ Perspective plan is effectively deployed Describe one activity successfully implemented based on the strategic plan within a maximum of 500 words | G84: 2
D85: QlM | E85: 6.2.2 | F85: The functioning of the institutional bodies is effective and efficient as visible from policies, administrative setup appointment and service rules, procedures, etc. Describe the Organogram of the Institution within a maximum of 500 words | G85: 4
D86: QnM | E86: 6.2.3 | F86: Implementation of e-governance in areas of operation: 1. Administration 2. Finance and Accounts 3. Student Admission and Support 4. Examination | G86: 4 | H86: 4 (all of the Above)
D87: QlM | E87: 6.3.1 | F87: The institution has effective welfare measures for teaching and non-teaching staff and avenues for career development/ progression Provide the list of existing welfare measures for teaching and non-teaching staff in maximum of 500 words | G87: 4
D88: QnM | E88: 6.3.2 | F88: Average percentage of teachers provided with financial support to attend conferences / workshops and towards membership fee of professional bodies during the last five years 6.3.2.1: Number of teachers provided with financial support to attend conferences / workshops and towards membership fee of professional bodies year wise during last five years | G88: 8 | H88: 4 (> 50%)
D89: QnM | E89: 6.3.3 | F89: Average number of professional development / administrative training programs organized by the Institution for teaching and non teaching staff during the last five years 6.3.3.1: Total number of professional development / administrative training Programmes organized by the Institution for teaching and non teaching staff year wise during last five years | G89: 8 | H89: 4 (> 30)
D90: QnM | E90: 6.3.4 | F90: Average percentage of teachers undergoing online/ face-to-face Faculty Development Programmes during the last five years (Professional Development Programmes, Orientation / Induction Programmes, Refresher Course, Short Term Course etc.,) 6.3.4.1: Total number of teachers attending professional development Programmes, viz., Orientation Programme, Refresher Course, Short Term Course, Faculty Development Programmes year wise during last five years. | G90: 10 | H90: 4 (> 50%)
D91: QlM | E91: 6.4.1 | F91: Institution conducts internal and external financial audits regularly Enumerate the various internal and external financial audits carried out during the last five years with the mechanism for settling audit objections within a maximum of 500 words | G91: 4
D92: QnM | E92: 6.4.2 | F92: Funds / Grants received from non-government bodies, individuals, philanthropists during the last five years (not covered in Criterion III and V) (INR in Lakhs) 6.4.2.1: Total Grants received from non-government bodies, individuals, philanthropists year wise during last five years (INR in Lakhs) | G92: 10 | H92: 4 (> 100 L)
D93: QlM | E93: 6.4.3 | F93: Institutional strategies for mobilisation of funds and the optimal utilisation of resources Describe the resource mobilisation policy and procedures of the Institution within a maximum of 500 words | G93: 6
D94: QlM | E94: 6.5.1 | F94: Internal Quality Assurance Cell (IQAC) has contributed significantly for institutionalizing the quality assurance strategies and processes visible in terms of – Incremental improvements made for the preceding five years with regard to quality (in case of first cycle) Incremental improvements made for the preceding five years with regard to quality and post accreditation quality initiatives (second and subsequent cycles) Describe two practices institutionalized as a result of IQAC initiatives within a maximum of 500 words | G94: 10
D95: QlM | E95: 6.5.2 | F95: The institution reviews its teaching learning process, structures & methodologies of operations and learning outcomes at periodic intervals through IQAC set up as per norms Describe any two examples of institutional reviews and implementation of teaching learning reforms facilitated by the IQAC within a maximum of 500 words each | G95: 10
D96: QnM | E96: 6.5.3 | F96: Quality assurance initiatives of the institution include: 1. Regular meeting of Internal Quality Assurance Cell (IQAC); Feedback collected, analysed and used for improvements 2. Collaborative quality initiatives with other institution(s) 3. Participation in NIRF 4. Any other quality audit recognized by state, national or international agencies (ISO Certification) | G96: 10 | H96: 4 (all 4 of the above)
D97: QlM | E97: 7.1.1 | F97: Measures initiated by the Institution for the promotion of gender equity during the last five years. Describe gender equity & sensitization in curricular and co-curricular activities, facilities for women on campus etc., within 500 words | G97: 5
D98: QnM | E98: 7.1.2 | F98: The Institution has facilities for alternate sources of energy and energy conservation measures 1. Solar energy 2. Biogas plant 3. Wheeling to the Grid 4. Sensor-based energy conservation 5. Use of LED bulbs/ power efficient equipment | G98: 5 | H98: 4 (Any 4 or all of the above )
D99: QlM | E99: 7.1.3 | F99: Describe the facilities in the Institution for the management of the following types of degradable and non-degradable waste (within 500 words) 1. Solid waste management 2. Liquid waste management 3. Biomedical waste management 4. E-waste management 5. Waste recycling system 6. Hazardous chemicals and radioactive waste management | G99: 4
D100: QnM | E100: 7.1.4 | F100: Water conservation facilities available in the Institution: 1. Rain water harvesting 2. Borewell /Open well recharge 3. Construction of tanks and bunds 4. Waste water recycling 5. Maintenance of water bodies and distribution system in the campus | G100: 4 | H100: 4 (Any 4 or all of the above )
D101: QnM | E101: 7.1.5 | F101: Green campus initiatives include (4) 7.1.5.1. The institutional initiatives for greening the campus are as follows: 1. Restricted entry of automobiles 2. Use of Bicycles/ Battery powered vehicles 3. Pedestrian Friendly pathways 4. Ban on use of Plastic 5. landscaping with trees and plants | G101: 4 | H101: 4 (Any 4 or all of the above )
...

Sheet Autonomous 107m
J1: RESPONSE | K1: Autonomous
A2: S. No | B2: Criteria © | C2: Key Indicator (KI) | D2: Metric (M) Type | E2: Metric (M) Num | F2: Metric (M) Description | G2: M Wt | H2: KI Wt | I2: © Wt | J2: Institute Name | K2: Metric Grade scale (0-4) | L2: M wise weighted Grade points | M2: KIwise weighted Grade points | N2: KIwise weighted Grade points Average | O2: ©Wise Weighted Average | P2: ©Wise Weighted Grade Point Average
A3: 1 | B3: 1. Curricular Aspects | C3: 1.1 Curriculum Planning and Implementation | D3: QlM | E3: 1.1.1 | F3: Curricula developed and implemented have relevance to the local, national, regional and global developmental needs which is reflected in Programme outcomes (POs), Programme Specific outcomes (PSOs) and Course Outcomes (COs) of the Programmes offered by the Institution Write description in maximum of 500 words | G3: 20 | H3: 50 | I3: 150 | L3: =K3*G3 -> 0 | M3: =SUM(L3:L5) -> 120 | N3: =M3/H3 -> 2.4 | O3: =SUM(M3:M13) -> 320 | P3: =O3/I3 -> 2.1333333
A4: 2 | B4: 1. Curricular Aspects | C4: 1.1 Curriculum Planning and Implementation | D4: QnM | E4: 1.1.2 | F4: Percentage of Programmes where syllabus revision was carried out during the last five years 1.1.2.1: How many Programmes were revised out of total number of Programmes offered during the same period within last five years? 1.1.2.2 : Number of all Programmes offered by the institution during the last five years | G4: 20 | J4: 92.86 | K4: =IF(J4>80,4,IF(AND(J4<=80,J4>60),3,IF(AND(J4<=60,J4>40),2,IF(AND(J4<=40,J4>20),1,IF(J4<=20,0))))) -> 4 | L4: =K4*G4 -> 80
A5: 3 | B5: 1. Curricular Aspects | C5: 1.1 Curriculum Planning and Implementation | D5: QnM | E5: 1.1.3 | F5: Average percentage of courses having focus on employability/ entrepreneurship/ skill development offered by the institution during the last five years 1.1.3.1: Number of courses having focus on employability/ entrepreneurship/ skill development year wise during last five years | G5: 10 | J5: 84.19 | K5: =IF(J5>80,4,IF(AND(J5<=80,J5>60),3,IF(AND(J5<=60,J5>40),2,IF(AND(J5<=40,J5>20),1,IF(J5<=20,0))))) -> 4 | L5: =K5*G5 -> 40
A6: 4 | B6: 1. Curricular Aspects | C6: 1.2 Academic Flexibility | D6: QnM | E6: 1.2.1 | F6: Percentage of new courses introduced of the total number of courses across all programs offered during the last five years 1.2.1.1: How many new courses are introduced within the last five years 1.2.1.2 : Number of courses offered by the institution across all Programmes during the last five years | G6: 20 | H6: 40 | J6: 38.71 | K6: =IF(J6>80,4,IF(AND(J6<=80,J6>60),3,IF(AND(J6<=60,J6>40),2,IF(AND(J6<=40,J6>20),1,IF(J6<=20,0))))) -> 1 | L6: =K6*G6 -> 20 | M6: =SUM(L6:L7) -> 100 | N6: =M6/H6 -> 2.5
A7: 5 | B7: 1. Curricular Aspects | C7: 1.2 Academic Flexibility | D7: QnM | E7: 1.2.2 | F7: Percentage of Programmes in which Choice Based Credit System (CBCS)/elective course system has been implemented (Data for the latest completed academic year ) 1.2.2.1: Number of Programmes in which CBCS/Elective course system implemented. | G7: 20 | J7: 81.25 | K7: =IF(J7>80,4,IF(AND(J7<=80,J7>60),3,IF(AND(J7<=60,J7>40),2,IF(AND(J7<=40,J7>20),1,IF(J7<=20,0))))) -> 4 | L7: =K7*G7 -> 80
A8: 6 | B8: 1. Curricular Aspects | C8: 1.3 Curriculum Enrichment | D8: QlM | E8: 1.3.1 | F8: Institution integrates crosscutting issues relevant to Professional Ethics, Gender, Human Values, Environment and Sustainability, Human Values into the Curriculum Write description in maximum of 500 words | G8: 10 | H8: 40 | L8: =K8*G8 -> 0 | M8: =SUM(L8:L11) -> 50 | N8: =M8/H8 -> 1.25
A9: 7 | B9: 1. Curricular Aspects | C9: 1.3 Curriculum Enrichment | D9: QnM | E9: 1.3.2 | F9: Number of value-added courses for imparting transferable and life skills offered during last five years 1.3.2.1: How many new value-added courses are added within the last 5 years | G9: 10 | J9: 87 | K9: =IF(J9>80,4,IF(AND(J9<=80,J9>60),3,IF(AND(J9<=60,J9>40),2,IF(AND(J9<=40,J9>20),1,IF(J9<=20,0))))) -> 4 | L9: =K9*G9 -> 40
A10: 8 | B10: 1. Curricular Aspects | C10: 1.3 Curriculum Enrichment | D10: QnM | E10: 1.3.3 | F10: Average Percentage of students enrolled in the courses under 1.3.2 above 1.3.3.1: Number of students enrolled in value added courses (beyond the curriculum) offered year wise during last five year | G10: 10 | J10: 32.64 | K10: =IF(J10>80,4,IF(AND(J10<=80,J10>60),3,IF(AND(J10<=60,J10>40),2,IF(AND(J10<=40,J10>20),1,IF(J10<=20,0))))) -> 1 | L10: =K10*G10 -> 10
A11: 9 | B11: 1. Curricular Aspects | C11: 1.3 Curriculum Enrichment | D11: QnM | E11: 1.3.4 | F11: Percentage of students undertaking field projects/ internships / student projects (Data for the latest completed academic year) 1.3.4.1: Number of students undertaking field projects / internships / student projects | G11: 10 | J11: 61.81 | K11: =IF(EXACT(J11,"A"),4,IF(EXACT(J11,"B"),3,IF(EXACT(J11,"C"),2,IF(EXACT(J11,"D"),1,0)))) -> 0 | L11: =K11*G11 -> 0
A12: 10 | B12: 1. Curricular Aspects | C12: 1.4 Feedback System | D12: QnM | E12: 1.4.1 | F12: Structured feedback for design and review of syllabus ( semester wise / year wise) is obtained from 1) Students, 2) Teachers, 3) Employers, 4) Alumni | G12: 10 | H12: 20 | J12: B | K12: =IF(EXACT(J12,"A"),4,IF(EXACT(J12,"B"),3,IF(EXACT(J12,"C"),2,IF(EXACT(J12,"D"),1,0)))) -> 3 | L12: =K12*G12 -> 30 | M12: =SUM(L12:L13) -> 50 | N12: =M12/H12 -> 2.5
A13: 11 | B13: 1. Curricular Aspects | C13: 1.4 Feedback System | D13: QnM | E13: 1.4.2 | F13: The feedback system of the Institution comprises of the following : A. Feedback collected, analysed and action taken and report made available on website B. Feedback collected, analysed and action taken C. Feedback collected and analysed D. Feedback collected E. Feedback not obtained | G13: 10 | J13: C | K13: =IF(EXACT(J13,"A"),4,IF(EXACT(J13,"B"),3,IF(EXACT(J13,"C"),2,IF(EXACT(J13,"D"),1,0)))) -> 2 | L13: =K13*G13 -> 20
A14: 12 | B14: 2. Teaching-Learning and Evaluation | C14: 2.1 Student Enrolment and Profile | D14: QnM | E14: 2.1.1 | F14: Average Enrolment percentage (Average of last five years) 2.1.1.1: Number of students admitted year wise during last five years 2.1.1.2: Number of sanctioned seats year wise during last five years | G14: 10 | H14: 20 | I14: 300 | J14: 85.42 | K14: =IF(J14>80,4,IF(AND(J14<=80,J14>60),3,IF(AND(J14<=60,J14>40),2,IF(AND(J14<=40,J14>20),1,IF(J14<=20,0))))) -> 4 | L14: =K14*G14 -> 40 | M14: =SUM(L14:L15) -> 80 | N14: =M14/H14 -> 4 | O14: =SUM(M14:M31) -> 240 | P14: =O14/I14 -> 0.8
A15: 13 | B15: 2. Teaching-Learning and Evaluation | C15: 2.1 Student Enrolment and Profile | D15: QnM | E15: 2.1.2 | F15: Average percentage of seats filled against reserved categories (SC, ST, OBC, Divyangjan, etc. as per applicable reservation policy ) during the last five years ( exclusive of supernumerary seats) 2.1.2.1: Number of actual students admitted from the reserved categories year wise during last five years | G15: 10 | J15: 97.91 | K15: =IF(J15>80,4,IF(AND(J15<=80,J15>60),3,IF(AND(J15<=60,J15>40),2,IF(AND(J15<=40,J15>20),1,IF(J15<=20,0))))) -> 4 | L15: =K15*G15 -> 40
A16: 14 | B16: 2. Teaching-Learning and Evaluation | C16: 2.2 Catering to Student Diversity | D16: QlM | E16: 2.2.1 | F16: The institution assesses the learning levels of the students and organises special Programmes for advanced learners and slow learners. Write description in of 500 words | G16: 15 | H16: 30 | L16: =K16*G16 -> 0 | M16: =SUM(L16:L17) -> 0 | N16: =M16/H16 -> 0
A17: 15 | B17: 2. Teaching-Learning and Evaluation | C17: 2.2 Catering to Student Diversity | D17: QnM | E17: 2.2.2 | F17: Student - Full time teacher ratio (Data for the latest completed academic year) | G17: 15 | J17: 16.13 | K17: =IF(J17>80,4,IF(AND(J17<=80,J17>60),3,IF(AND(J17<=60,J17>40),2,IF(AND(J17<=40,J17>20),1,IF(J17<=20,0))))) -> 0 | L17: =K17*G17 -> 0
A18: 16 | B18: 2. Teaching-Learning and Evaluation | C18: 2.3 Teaching-Learning Process | D18: QlM | E18: 2.3.1 | F18: Student centric methods, such as experiential learning, participative learning and problem solving methodologies are used for enhancing learning experiences Write description in maximum of 500 words | G18: 15 | H18: 50 | L18: =K18*G18 -> 0 | M18: =SUM(L18:L21) -> 0 | N18: =M18/H18 -> 0
A19: 17 | B19: 2. Teaching-Learning and Evaluation | C19: 2.3 Teaching-Learning Process | D19: QlM | E19: 2.3.2 | F19: Teachers use ICT enabled tools including online resources for effective teaching and learning process Write description in maximum of 500 words | G19: 15 | L19: =K19*G19 -> 0
A20: 18 | B20: 2. Teaching-Learning and Evaluation | C20: 2.3 Teaching-Learning Process | D20: QnM | E20: 2.3.3 | F20: Ratio of students to mentor for academic and other related issues (Data for the latest completed academic year ) 2.3.3.1: Number of mentors Number of students assigned to each Mentor | G20: 10 | J20: 0.79236111 | K20: =IF(J20>80,4,IF(AND(J20<=80,J20>60),3,IF(AND(J20<=60,J20>40),2,IF(AND(J20<=40,J20>20),1,IF(J20<=20,0))))) -> 0 | L20: =K20*G20 -> 0
A21: 19 | B21: 2. Teaching-Learning and Evaluation | C21: 2.3 Teaching-Learning Process | D21: QlM | E21: 2.3.4 | F21: Preparation and adherence of Academic Calendar and Teaching plans by the institution Describe the Preparation and adherence to Academic Calendar and Teaching plans by the institution within the minimum of 500 Characters and maximum of 500 words. | G21: 10 | L21: =K21*G21 -> 0
A22: 20 | B22: 2. Teaching-Learning and Evaluation | C22: 2.4 Teacher Profile and Quality | D22: QnM | E22: 2.4.1 | F22: Average percentage of full time teachers against sanctioned posts during the last five years | G22: 15 | H22: 50 | J22: 99.34 | K22: =IF(J22>80,4,IF(AND(J22<=80,J22>60),3,IF(AND(J22<=60,J22>40),2,IF(AND(J22<=40,J22>20),1,IF(J22<=20,0))))) -> 4 | L22: =K22*G22 -> 60 | M22: =SUM(L22:L24) -> 60 | N22: =M22/H22 -> 1.2
A23: 21 | B23: 2. Teaching-Learning and Evaluation | C23: 2.4 Teacher Profile and Quality | D23: QnM | E23: 2.4.2 | F23: Average percentage of full time teachers with Ph.D. / D.M. / M.Ch. / D.N.B Super speciality / D.Sc. / D.Litt. during the last five years 2.4.2.1: Number of full time teachers with Ph.D./ D.M. / M.Ch. / D.N.B Super speciality / D.Sc. / D.Litt. year wise during last five years | G23: 20 | J23: 11.09 | K23: =IF(J23>80,4,IF(AND(J23<=80,J23>60),3,IF(AND(J23<=60,J23>40),2,IF(AND(J23<=40,J23>20),1,IF(J23<=20,0))))) -> 0 | L23: =K23*G23 -> 0
A24: 22 | B24: 2. Teaching-Learning and Evaluation | C24: 2.4 Teacher Profile and Quality | D24: QnM | E24: 2.4.3 | F24: Average teaching experience of full time teachers in the same institution (Data for the latest completed academic year in number of years 2.4.3.1: Total experience of full-time teachers | G24: 15 | J24: 5.69 | K24: =IF(J24>80,4,IF(AND(J24<=80,J24>60),3,IF(AND(J24<=60,J24>40),2,IF(AND(J24<=40,J24>20),1,IF(J24<=20,0))))) -> 0 | L24: =K24*G24 -> 0
A25: 23 | B25: 2. Teaching-Learning and Evaluation | C25: 2.5 Evaluation Process and Reforms | D25: QnM | E25: 2.5.1 | F25: Average number of days from the date of last semester-end/ year- end examination till the declaration of results during the last five years 2.5.1.1: Number of days from the date of last semester-end/ year- end examination till the declaration of results year wise during the last five years | G25: 20 | H25: 50 | J25: 21 | K25: =IF(J25>80,4,IF(AND(J25<=80,J25>60),3,IF(AND(J25<=60,J25>40),2,IF(AND(J25<=40,J25>20),1,IF(J25<=20,0))))) -> 1 | L25: =K25*G25 -> 20 | M25: =SUM(L25:L27) -> 20 | N25: =M25/H25 -> 0.4
A26: 24 | B26: 2. Teaching-Learning and Evaluation | C26: 2.5 Evaluation Process and Reforms | D26: QnM | E26: 2.5.2 | F26: Average percentage of student complaints/grievances about evaluation against total number appeared in the examinations during the last five years 2.5.2.1: Number of complaints/grievances about evaluation year wise during last five years | G26: 15 | J26: 12.61 | K26: =IF(J26>80,4,IF(AND(J26<=80,J26>60),3,IF(AND(J26<=60,J26>40),2,IF(AND(J26<=40,J26>20),1,IF(J26<=20,0))))) -> 0 | L26: =K26*G26 -> 0
A27: 25 | B27: 2. Teaching-Learning and Evaluation | C27: 2.5 Evaluation Process and Reforms | D27: QlM | E27: 2.5.3 | F27: IT integration and reforms in the examination procedures and processes including Continuous Internal Assessment (CIA) have brought in considerable improvement in Examination Management System (EMS) of the Institution Describe the examination reforms with reference to the following within a minimum of 500 words and maximum 1000 words: | G27: 15 | L27: =K27*G27 -> 0
A28: 26 | B28: 2. Teaching-Learning and Evaluation | C28: 2.6 Student Performance and Learning Outcomes | D28: QlM | E28: 2.6.1 | F28: Programme outcomes and course outcomes for all Programmes offered by the institution are stated and displayed on website and communicated to teachers and students Describe Course Outcomes (COs) for all courses and mechanism of communication within a maximum of 500 words | G28: 20 | H28: 50 | L28: =K28*G28 -> 0 | M28: =SUM(L28:L30) -> 80 | N28: =M28/H28 -> 1.6
A29: 27 | B29: 2. Teaching-Learning and Evaluation | C29: 2.6 Student Performance and Learning Outcomes | D29: QlM | E29: 2.6.2 | F29: Attainment of program outcomes and course outcomes are evaluated by the institution Describe the method of measuring attainment of POs , PSOs and COs in not more than 500 words and the level of attainment of POs , PSOs and COs. | G29: 10 | L29: =K29*G29 -> 0
A30: 28 | B30: 2. Teaching-Learning and Evaluation | C30: 2.6 Student Performance and Learning Outcomes | D30: QnM | E30: 2.6.3 | F30: Pass percentage of students (Data for the latest completed academic year) 2.6.3.1: Total number of final year students who passed the examination conducted by Institution. 2.6.3.2: Total number of final year students who appeared for the examination | G30: 20 | J30: 90.9 | K30: =IF(J30>80,4,IF(AND(J30<=80,J30>60),3,IF(AND(J30<=60,J30>40),2,IF(AND(J30<=40,J30>20),1,IF(J30<=20,0))))) -> 4 | L30: =K30*G30 -> 80
A31: 29 | B31: 2. Teaching-Learning and Evaluation | C31: 2.7 Student Satisfaction Survey | D31: QnM | E31: 2.7.1 | F31: Online student satisfaction survey regarding to teaching learning process. (Online survey to be conducted) | G31: 50 | H31: 50 | J31: 3.48 | K31: =IF(EXACT(J31,"A"),4,IF(EXACT(J31,"B"),3,IF(EXACT(J31,"C"),2,IF(EXACT(J31,"D"),1,0)))) -> 0 | L31: =K31*G31 -> 0 | M31: =L31 -> 0 | N31: =M31/H31 -> 0
A32: 30 | B32: 3. Research, Innovations and Extension | C32: 3.1 Promotion of Research and Facilities | D32: QlM | E32: 3.1.1 | F32: The institution Research facilities are frequently updated and there is well defined policy for promotion of research which is uploaded on the institutional website and implemented Write description in maximum of 500 words | G32: 6 | H32: 20 | I32: 150 | L32: =K32*G32 -> 0 | M32: =SUM(L32:L34) -> 0 | N32: =M32/H32 -> 0 | O32: =SUM(M32:M54) -> 114 | P32: =O32/I32 -> 0.76
A33: 31 | B33: 3. Research, Innovations and Extension | C33: 3.1 Promotion of Research and Facilities | D33: QnM | E33: 3.1.2 | F33: The institution provides seed money to its teachers for research (Average per year) 3.1.2.1: The amount of seed money provided by institution to its teachers for research year wise during last five years (INR in lakhs) | G33: 8 | J33: 0 | K33: =IF(J33>80,4,IF(AND(J33<=80,J33>60),3,IF(AND(J33<=60,J33>40),2,IF(AND(J33<=40,J33>20),1,IF(J33<=20,0))))) -> 0 | L33: =K33*G33 -> 0
A34: 32 | B34: 3. Research, Innovations and Extension | C34: 3.1 Promotion of Research and Facilities | D34: QnM | E34: 3.1.3 | F34: Percentage of teachers awarded national / international fellowship for advanced studies/research during the last five years 3.1.3.1: The number of teachers awarded national / international fellowship for advanced studies / research year wise during last five years | G34: 6 | J34: 0.06 | K34: =IF(J34>80,4,IF(AND(J34<=80,J34>60),3,IF(AND(J34<=60,J34>40),2,IF(AND(J34<=40,J34>20),1,IF(J34<=20,0))))) -> 0 | L34: =K34*G34 -> 0
A35: 33 | B35: 3. Research, Innovations and Extension | C35: 3.2 Resource Mobilization for Research | D35: QnM | E35: 3.2.1 | F35: Grants received from Government and non-governmental agencies for research projects, endowments, Chairs in the institution during the last five years (INR in Lakhs) 3.2.1.1: Total Grants from Government and non-governmental agencies for research projects , endowments, Chairs in the institution during the last five years (INR in Lakhs) | G35: 2 | H35: 10 | J35: 116.67 | K35: =IF(J35>80,4,IF(AND(J35<=80,J35>60),3,IF(AND(J35<=60,J35>40),2,IF(AND(J35<=40,J35>20),1,IF(J35<=20,0))))) -> 4 | L35: =K35*G35 -> 8 | M35: =SUM(L35:L38) -> 14 | N35: =M35/H35 -> 1.4
A36: 34 | B36: 3. Research, Innovations and Extension | C36: 3.2 Resource Mobilization for Research | D36: QnM | E36: 3.2.2 | F36: Percentage of teachers having research projects during the last five years 3.2.2.1: Number of teachers having research projects during the last five years | G36: 2 | J36: 1.02 | K36: =IF(J36>80,4,IF(AND(J36<=80,J36>60),3,IF(AND(J36<=60,J36>40),2,IF(AND(J36<=40,J36>20),1,IF(J36<=20,0))))) -> 0 | L36: =K36*G36 -> 0
A37: 35 | B37: 3. Research, Innovations and Extension | C37: 3.2 Resource Mobilization for Research | D37: QnM | E37: 3.2.3 | F37: Percentage of teachers recognised as research guides 3.2.3.1: Number of teachers recognised as research guides | G37: 3 | J37: 3.03 | K37: =IF(J37>80,4,IF(AND(J37<=80,J37>60),3,IF(AND(J37<=60,J37>40),2,IF(AND(J37<=40,J37>20),1,IF(J37<=20,0))))) -> 0 | L37: =K37*G37 -> 0
A38: 36 | B38: 3. Research, Innovations and Extension | C38: 3.2 Resource Mobilization for Research | D38: QnM | E38: 3.2.4 | F38: Average percentage of departments having Research projects funded by government and non-government agencies during the last five years 3.2.4.1: Number of departments having Research projects funded by government and non-government agencies during the last five years | G38: 3 | J38: 43.57 | K38: =IF(J38>80,4,IF(AND(J38<=80,J38>60),3,IF(AND(J38<=60,J38>40),2,IF(AND(J38<=40,J38>20),1,IF(J38<=20,0))))) -> 2 | L38: =K38*G38 -> 6
A39: 37 | B39: 3. Research, Innovations and Extension | C39: 3.3 Innovation Ecosystem | D39: QlM | E39: 3.3.1 | F39: Institution has created an eco system for innovations, creation and transfer of knowledge supported by dedicated centers for research, entrepreneurship, community orientation, Incubation etc. Write description in maximum of 500 words | G39: 5 | H39: 10 | L39: =K39*G39 -> 0 | M39: =SUM(L39:L40) -> 10 | N39: =M39/H39 -> 1
A40: 38 | B40: 3. Research, Innovations and Extension | C40: 3.3 Innovation Ecosystem | D40: QnM | E40: 3.3.2 | F40: Number of workshops/seminars conducted on Research Methodology, Intellectual Property Rights (IPR), entrepreneurship and skills development during the last five years 3.3.2.1: Total number of workshops/seminars conducted on Research Methodology, Intellectual Property Rights (IPR) and entrepreneurship and skills development year wise during last five years | G40: 5 | J40: 43 | K40: =IF(J40>80,4,IF(AND(J40<=80,J40>60),3,IF(AND(J40<=60,J40>40),2,IF(AND(J40<=40,J40>20),1,IF(J40<=20,0))))) -> 2 | L40: =K40*G40 -> 10
A41: 39 | B41: 3. Research, Innovations and Extension | C41: 3.4 Research Publications and Awards | D41: QnM | E41: 3.4.1 | F41: The Institution ensures implementation of its stated Code of Ethics for research through the following: 1. Inclusion of research ethics in the research methodology course work 2. Presence of Ethics committee 3. Plagiarism check through software 4. Research Advisory Committee | G41: 5 | H41: 30 | J41: C | K41: =IF(EXACT(J41,"A"),4,IF(EXACT(J41,"B"),3,IF(EXACT(J41,"C"),2,IF(EXACT(J41,"D"),1,0)))) -> 2 | L41: =K41*G41 -> 10 | M41: =SUM(L41:L46) -> 10 | N41: =M41/H41 -> 0.33333333
A42: 40 | B42: 3. Research, Innovations and Extension | C42: 3.4 Research Publications and Awards | D42: QnM | E42: 3.4.2 | F42: Number of Ph.D’s registered per teacher (as per the data given w.r.t recognized Ph.D guides/ supervisors provided at 3.2.3 metric) during the last five years 3.4.2.1: How many Ph.Ds are registered within last 5 years 3.4.2.2 : Number of teachers recognized as guides during the last five years | G42: 5 | J42: 0 | K42: =IF(J42>80,4,IF(AND(J42<=80,J42>60),3,IF(AND(J42<=60,J42>40),2,IF(AND(J42<=40,J42>20),1,IF(J42<=20,0))))) -> 0 | L42: =K42*G42 -> 0
A43: 41 | B43: 3. Research, Innovations and Extension | C43: 3.4 Research Publications and Awards | D43: QnM | E43: 3.4.3 | F43: Number of research papers per teacher in the Journals notified on UGC website during the last five years 3.4.3.1: Number of research papers in the Journals notified on UGC website during the last five | G43: 5 | J43: 2.11 | K43: =IF(J43>80,4,IF(AND(J43<=80,J43>60),3,IF(AND(J43<=60,J43>40),2,IF(AND(J43<=40,J43>20),1,IF(J43<=20,0))))) -> 0 | L43: =K43*G43 -> 0
A44: 42 | B44: 3. Research, Innovations and Extension | C44: 3.4 Research Publications and Awards | D44: QnM | E44: 3.4.4 | F44: Number of books and chapters in edited volumes / books published per teacher during the last five years 3.4.4.1: Total number of books and chapters in edited volumes / books published, and papers in national/international conference-proceedings year wise during last five years | G44: 5 | J44: 0.22 | K44: =IF(J44>80,4,IF(AND(J44<=80,J44>60),3,IF(AND(J44<=60,J44>40),2,IF(AND(J44<=40,J44>20),1,IF(J44<=20,0))))) -> 0 | L44: =K44*G44 -> 0
A45: 43 | B45: 3. Research, Innovations and Extension | C45: 3.4 Research Publications and Awards | D45: QnM | E45: 3.4.5 | F45: Bibliometrics of the publications during the last five years based on average Citation index in Scopus/ Web of Science/ PubMed 3.4.5.1: Total number of Citations in Scopus in 5 years Total number of Citations in Web of Science in 5 years 3.4.5.2 : Total number of Publications in Scopus in 5 years Total number of Publications in Web of Science in 5 years | G45: 5 | J45: 1.81 | K45: =IF(J45>80,4,IF(AND(J45<=80,J45>60),3,IF(AND(J45<=60,J45>40),2,IF(AND(J45<=40,J45>20),1,IF(J45<=20,0))))) -> 0 | L45: =K45*G45 -> 0
A46: 44 | B46: 3. Research, Innovations and Extension | C46: 3.4 Research Publications and Awards | D46: QnM | E46: 3.4.6 | F46: Bibliometrics of the publications during the last five years based on Scopus/ Web of Science – h-index of the Institution 3.4.6.1: h-index of Scopus during the last five years h-index of Web of Science during the last five years | G46: 5 | J46: 8 | K46: =IF(EXACT(J46,"A"),4,IF(EXACT(J46,"B"),3,IF(EXACT(J46,"C"),2,IF(EXACT(J46,"D"),1,0)))) -> 0 | L46: =K46*G46 -> 0
A47: 45 | B47: 3. Research, Innovations and Extension | C47: 3.5 Consultancy | D47: QnM | E47: 3.5.1 | F47: Revenue generated from consultancy and corporate training during the last five years (INR in Lakhs) 3.5.1.1: Total amount generated from consultancy and corporate training year wise during last five years (INR in lakhs) | G47: 5 | H47: 10 | J47: 0 | K47: =IF(J47>80,4,IF(AND(J47<=80,J47>60),3,IF(AND(J47<=60,J47>40),2,IF(AND(J47<=40,J47>20),1,IF(J47<=20,0))))) -> 0 | L47: =K47*G47 -> 0 | M47: =SUM(L47:L48) -> 0 | N47: =M47/H47 -> 0
A48: 46 | B48: 3. Research, Innovations and Extension | C48: 3.5 Consultancy | D48: QnM | E48: 3.5.2 | F48: Total amount spent on developing facilities, training teachers and staff for undertaking consultancy during the last five years 3.5.2.1: Total amount spent on developing facilities, training teachers and staff for undertaking consultancy during the last five years | G48: 5 | J48: 0 | K48: =IF(J48>80,4,IF(AND(J48<=80,J48>60),3,IF(AND(J48<=60,J48>40),2,IF(AND(J48<=40,J48>20),1,IF(J48<=20,0))))) -> 0 | L48: =K48*G48 -> 0
A49: 47 | B49: 3. Research, Innovations and Extension | C49: 3.6 Extension Activities | D49: QlM | E49: 3.6.1 | F49: Extension activities are carried out in the neighbourhood community, sensitising students to social issues, for their holistic development, and impact thereof during the last five years Describe the impact of extension activities in sensitising students to social issues and holistic development within a maximum of 500 words | G49: 10 | H49: 50 | L49: =K49*G49 -> 0 | M49: =SUM(L49:L52) -> 60 | N49: =M49/H49 -> 1.2
A50: 48 | B50: 3. Research, Innovations and Extension | C50: 3.6 Extension Activities | D50: QnM | E50: 3.6.2 | F50: Number of awards and recognition received by the Institution, its teachers and students for extension activities from Government / Government recognised bodies during last five years 3.6.2.1: Total number of awards and recognition received for extension activities from Government /recognised bodies year wise during last five years | G50: 15 | J50: 0 | K50: =IF(J50>=50,4,IF(AND(J50<50,J50>40),3,IF(AND(J50<=40,J50>30),2,IF(AND(J50<=30,J50>20),1,IF(J50<=20,0))))) -> 0 | L50: =K50*G50 -> 0
A51: 49 | B51: 3. Research, Innovations and Extension | C51: 3.6 Extension Activities | D51: QnM | E51: 3.6.3 | F51: Number of extension and outreach programs conducted by the institution through NSS/NCC/Red cross/YRC etc., during the last five years ( including Government initiated programs such as Swachh Bharat, Aids Awareness, Gender Issue, etc. and those organised in collaboration with industry, community and NGOs) 3.6.3.1: Number of extension and outreach programs conducted in collaboration with industry, community and Non-Government Organisations through NSS/NCC/Red cross/YRC etc., year wise during last five years | G51: 10 | J51: 85 | K51: =IF(EXACT(J51,"A"),4,IF(EXACT(J51,"B"),3,IF(EXACT(J51,"C"),2,IF(EXACT(J51,"D"),1,0)))) -> 0 | L51: =K51*G51 -> 0
A52: 50 | B52: 3. Research, Innovations and Extension | C52: 3.6 Extension Activities | D52: QnM | E52: 3.6.4 | F52: Average percentage of students participating in extension activities listed at 3.6.3 above during the last five years 3.6.4.1: Total number of students participating in extension activities with Government Organisations, Non-Government Organisations and Programmes such as Swachh Bharat, Aids Awareness, Gender Issue, etc. year wise during last five years | G52: 15 | J52: 83.05 | K52: =IF(J52>80,4,IF(AND(J52<=80,J52>60),3,IF(AND(J52<=60,J52>40),2,IF(AND(J52<=40,J52>20),1,IF(J52<=20,0))))) -> 4 | L52: =K52*G52 -> 60
A53: 51 | B53: 3. Research, Innovations and Extension | C53: 3.7 Collaboration | D53: QnM | E53: 3.7.1 | F53: Number of Collaborative activities per year for research/ faculty exchange/ student exchange/ internship/ on –the-job training/ project work 3.7.1.1: Total number of Collaborative activities per year for research/ faculty exchange/ student exchange/ internship/ on –the-job training/ project work | G53: 10 | H53: 20 | J53: 0 | K53: =IF(J53>80,4,IF(AND(J53<=80,J53>60),3,IF(AND(J53<=60,J53>40),2,IF(AND(J53<=40,J53>20),1,IF(J53<=20,0))))) -> 0 | L53: =K53*G53 -> 0 | M53: =SUM(L53:L54) -> 20 | N53: =M53/H53 -> 1
A54: 52 | B54: 3. Research, Innovations and Extension | C54: 3.7 Collaboration | D54: QnM | E54: 3.7.2 | F54: Number of functional MoUs with institutions of national, international importance, other universities, industries, corporate houses etc. during the last five years (only functional MoUs with ongoing activities to be considered) 3.7.2.1: Number of functional MoUs with institutions of national, international importance, other Institutions, industries, corporate houses etc. year wise during last five years Data Template | G54: 10 | J54: 55 | K54: =IF(J54>80,4,IF(AND(J54<=80,J54>60),3,IF(AND(J54<=60,J54>40),2,IF(AND(J54<=40,J54>20),1,IF(J54<=20,0))))) -> 2 | L54: =K54*G54 -> 20
A55: 53 | B55: 4. Infrastructure and Learning Resources | C55: 4.1 Physical Facilities | D55: QlM | E55: 4.1.1 | F55: The Institution has adequate infrastructure and physical facilities for teaching – learning, viz., classrooms, laboratories, computing equipment, etc. Describe the adequacy of facilities for teaching –learning as per the minimum specified requirement by statutory bodies within a maximum of 500 words | G55: 6 | H55: 30 | I55: 100 | L55: =K55*G55 -> 0 | M55: =SUM(L55:L58) -> 0 | N55: =M55/H55 -> 0 | O55: =SUM(M55:M68) -> 64 | P55: =O55/I55 -> 0.64
A56: 54 | B56: 4. Infrastructure and Learning Resources | C56: 4.1 Physical Facilities | D56: QlM | E56: 4.1.2 | F56: The institution has adequate facilities for cultural activities, yoga, games (indoor, outdoor) and sports. (gymnasium, yoga centre, auditorium, etc.) Describe the adequacy facilities for cultural activities, yoga, games (indoor, outdoor) and sports which include specification about area/size, year of establishment and user rate within minimum of 500 characters and maximum of 500 words | G56: 4 | L56: =K56*G56 -> 0
A57: 55 | B57: 4. Infrastructure and Learning Resources | C57: 4.1 Physical Facilities | D57: QnM | E57: 4.1.3 | F57: Percentage of classrooms and seminar halls with ICT – enabled facilities such as smart class, LMS, etc. (Data for the latest completed academic year) 4.1.3.1: Number of classrooms and seminar halls with ICT facilities | G57: 10 | J57: 47.62 | K57: =IF(EXACT(J57,"A"),4,IF(EXACT(J57,"B"),3,IF(EXACT(J57,"C"),2,IF(EXACT(J57,"D"),1,0)))) -> 0 | L57: =K57*G57 -> 0
A58: 56 | B58: 4. Infrastructure and Learning Resources | C58: 4.1 Physical Facilities | D58: QnM | E58: 4.1.4 | F58: Average percentage of expenditure for infrastructure augmentation excluding salary during the last five years (INR in Lakhs) 4.1.4.1: Expenditure for infrastructure augmentation, excluding salary year wise during last five years (INR in lakhs) | G58: 10 | J58: 11.5 | K58: =IF(J58>80,4,IF(AND(J58<=80,J58>60),3,IF(AND(J58<=60,J58>40),2,IF(AND(J58<=40,J58>20),1,IF(J58<=20,0))))) -> 0 | L58: =K58*G58 -> 0
A59: 57 | B59: 4. Infrastructure and Learning Resources | C59: 4.2 Library as a Learning Resource | D59: QlM | E59: 4.2.1 | F59: Library is automated using Integrated Library Management System (ILMS) | G59: 5 | H59: 20 | L59: =K59*G59 -> 0 | M59: =SUM(L59:L62) -> 20 | N59: =M59/H59 -> 1
A60: 58 | B60: 4. Infrastructure and Learning Resources | C60: 4.2 Library as a Learning Resource | D60: QnM | E60: 4.2.2 | F60: Institution has access to the following: 1. e-journals 2. e-ShodhSindhu 3. Shodhganga Membership 4. e-books 5. Databases 6. Remote access to e-resources | G60: 5 | J60: A | K60: =IF(EXACT(J60,"A"),4,IF(EXACT(J60,"B"),3,IF(EXACT(J60,"C"),2,IF(EXACT(J60,"D"),1,0)))) -> 4 | L60: =K60*G60 -> 20
A61: 59 | B61: 4. Infrastructure and Learning Resources | C61: 4.2 Library as a Learning Resource | D61: QnM | E61: 4.2.3 | F61: Average annual expenditure for purchase of books/ e-books and subscription to journals/e-journals during the last five years (INR in Lakhs) 4.2.3.1: Annual expenditure for purchase of books / e-books and subscription to journals/e-journals year wise during last five years (INR in lakhs) | G61: 5 | J61: 11.52 | K61: =IF(J61>80,4,IF(AND(J61<=80,J61>60),3,IF(AND(J61<=60,J61>40),2,IF(AND(J61<=40,J61>20),1,IF(J61<=20,0))))) -> 0 | L61: =K61*G61 -> 0
A62: 60 | B62: 4. Infrastructure and Learning Resources | C62: 4.2 Library as a Learning Resource | D62: QnM | E62: 4.2.4 | F62: Percentage per day usage of library by teachers and students ( foot falls and login data for online access) 4.2.6.1: Number of teachers and students using library per day over last one year | G62: 5 | J62: 12.21 | K62: =IF(J62>80,4,IF(AND(J62<=80,J62>60),3,IF(AND(J62<=60,J62>40),2,IF(AND(J62<=40,J62>20),1,IF(J62<=20,0))))) -> 0 | L62: =K62*G62 -> 0
A63: 61 | B63: 4. Infrastructure and Learning Resources | C63: 4.3 IT Infrastructure | D63: QlM | E63: 4.3.1 | F63: Institution has an IT policy covering wi-fi, cyber security, etc., and allocated budget for updating its IT facilities Describe IT facilities including Wi-Fi with date and nature of updation within a maximum of 500 words | G63: 8 | H63: 30 | L63: =K63*G63 -> 0 | M63: =SUM(L63:L66) -> 44 | N63: =M63/H63 -> 1.4666667
A64: 62 | B64: 4. Infrastructure and Learning Resources | C64: 4.3 IT Infrastructure | D64: QnM | E64: 4.3.2 | F64: Student - Computer ratio(Data for the latest completed academic year) | G64: 8 | J64: 0.16736111 | K64: =IF(EXACT(J64,"A"),4,IF(EXACT(J64,"B"),3,IF(EXACT(J64,"C"),2,IF(EXACT(J64,"D"),1,0)))) -> 0 | L64: =K64*G64 -> 0
A65: 63 | B65: 4. Infrastructure and Learning Resources | C65: 4.3 IT Infrastructure | D65: QnM | E65: 4.3.3 | F65: Bandwidth of internet connection in the Institution Options: A. ≥50 MBPS B. 35 MBPS - 50 MBPS C. 20 MBPS - 35 MBPS Opt One D. 5 MBPS - 20 MBPS E. <5 MBPS | G65: 10 | J65: 50 | K65: =IF(J65>=50,4,IF(AND(J65<50,J65>=40),3,IF(AND(J65<40,J65>=30),2,IF(AND(J65<30,J65>=20),1,IF(J65<20,0))))) -> 4 | L65: =K65*G65 -> 40
A66: 64 | B66: 4. Infrastructure and Learning Resources | C66: 4.3 IT Infrastructure | D66: QnM | E66: 4.3.4 | F66: Institution has Facilities for e-content development Facilities available for e-content development : 1. Media centre 2. Audio visual centre, 3. Lecture Capturing System(LCS) 4. Mixing equipment's and software's for editing | G66: 4 | J66: D | K66: =IF(EXACT(J66,"A"),4,IF(EXACT(J66,"B"),3,IF(EXACT(J66,"C"),2,IF(EXACT(J66,"D"),1,0)))) -> 1 | L66: =K66*G66 -> 4
A67: 65 | B67: 4. Infrastructure and Learning Resources | C67: 4.4 Maintenance of Campus Infrastructure | D67: QnM | E67: 4.4.1 | F67: Average percentage expenditure incurred on maintenance of physical facilities and academic support facilities excluding salary component, during the last five years 4.4.1.1: Expenditure incurred on maintenance of physical facilities and academic support facilities excluding salary component year wise during last five years (INR in lakhs) | G67: 10 | H67: 20 | J67: 9.51 | K67: =IF(J67>80,4,IF(AND(J67<=80,J67>60),3,IF(AND(J67<=60,J67>40),2,IF(AND(J67<=40,J67>20),1,IF(J67<=20,0))))) -> 0 | L67: =K67*G67 -> 0 | M67: =SUM(L67:L68) -> 0 | N67: =M67/H67 -> 0
A68: 66 | B68: 4. Infrastructure and Learning Resources | C68: 4.4 Maintenance of Campus Infrastructure | D68: QlM | E68: 4.4.2 | F68: There are established systems and procedures for maintaining and utilizing physical, academic and support facilities – laboratory, library, sports complex, computers, classrooms etc. Describe policy details of systems and procedures for maintaining and utilizing physical, academic and support facilities on the website within a minimum of 500 word and maximum of 1000 words | G68: 10 | L68: =K68*G68 -> 0
A69: 67 | B69: 5. Student Support and Progression | C69: 5.1 Student Support | D69: QnM | E69: 5.1.1 | F69: Average percentage of students benefited by scholarships and freeships provided by the Government during the last five years 5.1.1.1: Number of students benefited by scholarships and freeships provided by the Government year wise during last five years | G69: 6 | H69: 30 | I69: 100 | J69: 48 | K69: =IF(EXACT(J69,"A"),4,IF(EXACT(J69,"B"),3,IF(EXACT(J69,"C"),2,IF(EXACT(J69,"D"),1,0)))) -> 0 | L69: =K69*G69 -> 0 | M69: =SUM(L69:L73) -> 39 | N69: =M69/H69 -> 1.3 | O69: =SUM(M69:M81) -> 104 | P69: =O69/I69 -> 1.04
A70: 68 | B70: 5. Student Support and Progression | C70: 5.1 Student Support | D70: QnM | E70: 5.1.2 | F70: Average percentage of students benefited by scholarships, freeships, etc. provided by the institution and non-government agencies during the last five years 5.1.2.1: Total number of students benefited by scholarships, freeships, etc provided by the institution and non-government agencies year wise during last five years | G70: 5 | J70: 0 | K70: =IF(EXACT(J70,"A"),4,IF(EXACT(J70,"B"),3,IF(EXACT(J70,"C"),2,IF(EXACT(J70,"D"),1,0)))) -> 0 | L70: =K70*G70 -> 0
A71: 69 | B71: 5. Student Support and Progression | C71: 5.1 Student Support | D71: QnM | E71: 5.1.3 | F71: Following Capacity development and skills enhancement activities are organised for improving students capability 1. Soft skills 2. Language and communication skills 3. Life skills (Yoga, physical fitness, health and hygiene) 4. Awareness of trends in technology | G71: 8 | J71: B | K71: =IF(EXACT(J71,"A"),4,IF(EXACT(J71,"B"),3,IF(EXACT(J71,"C"),2,IF(EXACT(J71,"D"),1,0)))) -> 3 | L71: =K71*G71 -> 24
A72: 70 | B72: 5. Student Support and Progression | C72: 5.1 Student Support | D72: QnM | E72: 5.1.4 | F72: Average percentage of students benefited by guidance for competitive examinations and career counselling offered by the institution during the last five years 5.1.4.1: Number of students benefited by guidance for competitive examinations and career counselling offered by the institution year wise during last five years | G72: 6 | J72: 3.49 | K72: =IF(EXACT(J72,"A"),4,IF(EXACT(J72,"B"),3,IF(EXACT(J72,"C"),2,IF(EXACT(J72,"D"),1,0)))) -> 0 | L72: =K72*G72 -> 0
A73: 71 | B73: 5. Student Support and Progression | C73: 5.1 Student Support | D73: QnM | E73: 5.1.5 | F73: The institution adopts the following for redressal of student grievances including sexual harassment and ragging cases 1. Implementation of guidelines of statutory/regulatory bodies 2. Organisation wide awareness and undertakings on policies with zero tolerance 3. Mechanisms for submission of online/offline students’ grievances 4. Timely redressal of the grievances through appropriate committees | G73: 5 | J73: B | K73: =IF(EXACT(J73,"A"),4,IF(EXACT(J73,"B"),3,IF(EXACT(J73,"C"),2,IF(EXACT(J73,"D"),1,0)))) -> 3 | L73: =K73*G73 -> 15
A74: 72 | B74: 5. Student Support and Progression | C74: 5.2 Student Progression | D74: QnM | E74: 5.2.1 | F74: Average percentage of placement of outgoing students during the last five years 5.2.1.1: Number of outgoing students placed year wise during last five years | G74: 10 | H74: 30 | J74: 44.94 | K74: =IF(EXACT(J74,"A"),4,IF(EXACT(J74,"B"),3,IF(EXACT(J74,"C"),2,IF(EXACT(J74,"D"),1,0)))) -> 0 | L74: =K74*G74 -> 0 | M74: =SUM(L74:L76) -> 40 | N74: =M74/H74 -> 1.3333333
A75: 73 | B75: 5. Student Support and Progression | C75: 5.2 Student Progression | D75: QnM | E75: 5.2.2 | F75: Percentage of student progression to higher education (previous graduating batch) 5.2.2.1: Number of outgoing students progressing to higher education Data Requirements: (As per Data Template) Number of students proceeding from UG to PG:. PG to MPhil: PG to PhD: MPhil to PhD: PhD to Post doctoral: | G75: 10 | J75: 7.46 | K75: =IF(EXACT(J75,"A"),4,IF(EXACT(J75,"B"),3,IF(EXACT(J75,"C"),2,IF(EXACT(J75,"D"),1,0)))) -> 0 | L75: =K75*G75 -> 0
A76: 74 | B76: 5. Student Support and Progression | C76: 5.2 Student Progression | D76: QnM | E76: 5.2.3 | F76: Average percentage of students qualifying in state/ national/ international level examinations during the last five years (eg: IIT/JAM/NET/SLET/GATE/GMAT/CAT/ GRE/TOEFL/Civil Services/State government examinations etc.) 5.2.3.1: Number of students qualifying in state/ national/ international level examinations (eg: IIT/JAM/NET/SLET/GATE/GMAT/CAT/ GRE/TOEFL/Civil Services/State government examinations) year wise during last five years 5.2.3.2: Number of students appearing in state/ national/ international level examinations (eg: IIT/JAM/ NET/SLET/GATE/GMAT/CAT, GRE/TOEFL/Civil Services/State government examinations) year wise during last five years | G76: 10 | J76: 100 | K76: =IF(J76>80,4,IF(AND(J76<=80,J76>60),3,IF(AND(J76<=60,J76>40),2,IF(AND(J76<=40,J76>20),1,IF(J76<=20,0))))) -> 4 | L76: =K76*G76 -> 40
A77: 75 | B77: 5. Student Support and Progression | C77: 5.3 Student Participation and Activities | D77: QnM | E77: 5.3.1 | F77: Number of awards/medals for outstanding performance in sports/cultural activities at inter-university / state /national / international events (award for a team event should be counted as one) during the last five years 5.3.1.1: Number of awards/medals for outstanding performance in sports/cultural activities at inter-university / state / national / international level (award for a team event should be counted as one) year wise during last five years | G77: 10 | H77: 30 | J77: 27 | K77: =IF(J77>80,4,IF(AND(J77<=80,J77>60),3,IF(AND(J77<=60,J77>40),2,IF(AND(J77<=40,J77>20),1,IF(J77<=20,0))))) -> 1 | L77: =K77*G77 -> 10 | M77: =SUM(L77:L79) -> 20 | N77: =M77/H77 -> 0.66666667
A78: 76 | B78: 5. Student Support and Progression | C78: 5.3 Student Participation and Activities | D78: QlM | E78: 5.3.2 | F78: Presence of an active Student Council & representation of students on academic & administrative bodies/committees of the institution Describe the Student Council activity and students role in academic & administrative bodies within a minimum of 500 characters and maximum of 500 words | G78: 10 | L78: =K78*G78 -> 0
A79: 77 | B79: 5. Student Support and Progression | C79: 5.3 Student Participation and Activities | D79: QnM | E79: 5.3.3 | F79: Average number of sports and cultural events / competitions organised by the institution per year 5.3.3.1: Number of sports and cultural events / competitions organised by the institution year wise during last five years | G79: 10 | J79: 22.8 | K79: =IF(J79>80,4,IF(AND(J79<=80,J79>60),3,IF(AND(J79<=60,J79>40),2,IF(AND(J79<=40,J79>20),1,IF(J79<=20,0))))) -> 1 | L79: =K79*G79 -> 10
A80: 78 | B80: 5. Student Support and Progression | C80: 5.4 Alumni Engagement | D80: QlM | E80: 5.4.1 | F80: The Alumni Association/Chapters (registered and functional)contributes significantly to the development of the institution through financial and other support services Describe contribution of alumni association to the institution within a maximum of 500 words | G80: 5 | H80: 10 | L80: =K80*G80 -> 0 | M80: =SUM(L80:L81) -> 5 | N80: =M80/H80 -> 0.5
A81: 79 | B81: 5. Student Support and Progression | C81: 5.4 Alumni Engagement | D81: QnM | E81: 5.4.2 | F81: Alumni financial contribution during the last five years (in INR) Options: A. ≥ 15 Lakhs B. 10Lakhs - 15 Lakhs C. 5 Lakhs - 10 Lakhs D. 2 Lakhs - 5 | G81: 5 | J81: D | K81: =IF(EXACT(J81,"A"),4,IF(EXACT(J81,"B"),3,IF(EXACT(J81,"C"),2,IF(EXACT(J81,"D"),1,0)))) -> 1 | L81: =K81*G81 -> 5
A82: 80 | B82: 6. Governance, Leadership and Management | C82: 6.1 Institutional Vision and Leadership | D82: QlM | E82: 6.1.1 | F82: The governance of the institution is reflective of an effective leadership in tune with the vision and mission of the Institution Describe the vision and mission statement of the institution on the nature of governance, perspective plans and participation of the teachers in the decision making bodies of the institution within a maximum of 500 words. | G82: 5 | H82: 10 | I82: 100 | L82: =K82*G82 -> 0 | M82: =SUM(L82:L83) -> 0 | O82: =SUM(M82:M96) -> 94 | P82: =O82/I82 -> 0.94
A83: 81 | B83: 6. Governance, Leadership and Management | C83: 6.1 Institutional Vision and Leadership | D83: QlM | E83: 6.1.2 | F83: The effective leadership is reflected in various institutional practices such as decentralization and participative management Upload a case study showing practicing decentralisation and participative management in the institution in not more than 500 words | G83: 5 | L83: =K83*G83 -> 0
A84: 82 | B84: 6. Governance, Leadership and Management | C84: 6.2 Strategy Development and Deployment | D84: QlM | E84: 6.2.1 | F84: The institutional Strategic/ Perspective plan is effectively deployed Describe one activity successfully implemented based on the strategic plan within a maximum of 500 words | G84: 2 | H84: 10 | L84: =K84*G84 -> 0 | M84: =SUM(L84:L86) -> 12 | N84: =M84/H84 -> 1.2
A85: 83 | B85: 6. Governance, Leadership and Management | C85: 6.2 Strategy Development and Deployment | D85: QlM | E85: 6.2.2 | F85: The functioning of the institutional bodies is effective and efficient as visible from policies, administrative setup appointment and service rules, procedures, etc. Describe the Organogram of the Institution within a maximum of 500 words | G85: 4 | L85: =K85*G85 -> 0
A86: 84 | B86: 6. Governance, Leadership and Management | C86: 6.2 Strategy Development and Deployment | D86: QnM | E86: 6.2.3 | F86: Implementation of e-governance in areas of operation: 1. Administration 2. Finance and Accounts 3. Student Admission and Support 4. Examination | G86: 4 | J86: B | K86: =IF(EXACT(J86,"A"),4,IF(EXACT(J86,"B"),3,IF(EXACT(J86,"C"),2,IF(EXACT(J86,"D"),1,0)))) -> 3 | L86: =K86*G86 -> 12
A87: 85 | B87: 6. Governance, Leadership and Management | C87: 6.3 Faculty Empowerment Strategies | D87: QlM | E87: 6.3.1 | F87: The institution has effective welfare measures for teaching and non-teaching staff and avenues for career development/ progression Provide the list of existing welfare measures for teaching and non-teaching staff in maximum of 500 words | G87: 4 | H87: 30 | L87: =K87*G87 -> 0 | M87: =SUM(L87:L90) -> 42 | N87: =M87/H87 -> 1.4
A88: 86 | B88: 6. Governance, Leadership and Management | C88: 6.3 Faculty Empowerment Strategies | D88: QnM | E88: 6.3.2 | F88: Average percentage of teachers provided with financial support to attend conferences / workshops and towards membership fee of professional bodies during the last five years 6.3.2.1: Number of teachers provided with financial support to attend conferences / workshops and towards membership fee of professional bodies year wise during last five years | G88: 8 | J88: 42.41 | K88: =IF(J88>80,4,IF(AND(J88<=80,J88>60),3,IF(AND(J88<=60,J88>40),2,IF(AND(J88<=40,J88>20),1,IF(J88<=20,0))))) -> 2 | L88: =K88*G88 -> 16
A89: 87 | B89: 6. Governance, Leadership and Management | C89: 6.3 Faculty Empowerment Strategies | D89: QnM | E89: 6.3.3 | F89: Average number of professional development / administrative training programs organized by the Institution for teaching and non teaching staff during the last five years 6.3.3.1: Total number of professional development / administrative training Programmes organized by the Institution for teaching and non teaching staff year wise during last five years | G89: 8 | J89: 51.2 | K89: =IF(J89>80,4,IF(AND(J89<=80,J89>60),3,IF(AND(J89<=60,J89>40),2,IF(AND(J89<=40,J89>20),1,IF(J89<=20,0))))) -> 2 | L89: =K89*G89 -> 16
A90: 88 | B90: 6. Governance, Leadership and Management | C90: 6.3 Faculty Empowerment Strategies | D90: QnM | E90: 6.3.4 | F90: Average percentage of teachers undergoing online/ face-to-face Faculty Development Programmes during the last five years (Professional Development Programmes, Orientation / Induction Programmes, Refresher Course, Short Term Course etc.,) 6.3.4.1: Total number of teachers attending professional development Programmes, viz., Orientation Programme, Refresher Course, Short Term Course, Faculty Development Programmes year wise during last five years. | G90: 10 | J90: 21.4 | K90: =IF(J90>80,4,IF(AND(J90<=80,J90>60),3,IF(AND(J90<=60,J90>40),2,IF(AND(J90<=40,J90>20),1,IF(J90<=20,0))))) -> 1 | L90: =K90*G90 -> 10
A91: 89 | B91: 6. Governance, Leadership and Management | C91: 6.4 Financial Management and Resource Mobilization | D91: QlM | E91: 6.4.1 | F91: Institution conducts internal and external financial audits regularly Enumerate the various internal and external financial audits carried out during the last five years with the mechanism for settling audit objections within a maximum of 500 words | G91: 4 | H91: 20 | L91: =K91*G91 -> 0 | M91: =SUM(L91:L93) -> 0 | N91: =M91/H91 -> 0
A92: 90 | B92: 6. Governance, Leadership and Management | C92: 6.4 Financial Management and Resource Mobilization | D92: QnM | E92: 6.4.2 | F92: Funds / Grants received from non-government bodies, individuals, philanthropists during the last five years (not covered in Criterion III and V) (INR in Lakhs) 6.4.2.1: Total Grants received from non-government bodies, individuals, philanthropists year wise during last five years (INR in Lakhs) | G92: 10 | J92: 5.99 | K92: =IF(J92>80,4,IF(AND(J92<=80,J92>60),3,IF(AND(J92<=60,J92>40),2,IF(AND(J92<=40,J92>20),1,IF(J92<=20,0))))) -> 0 | L92: =K92*G92 -> 0
A93: 91 | B93: 6. Governance, Leadership and Management | C93: 6.4 Financial Management and Resource Mobilization | D93: QlM | E93: 6.4.3 | F93: Institutional strategies for mobilisation of funds and the optimal utilisation of resources Describe the resource mobilisation policy and procedures of the Institution within a maximum of 500 words | G93: 6 | L93: =K93*G93 -> 0
A94: 92 | B94: 6. Governance, Leadership and Management | C94: 6.5 Internal Quality Assurance System (IQAS) | D94: QlM | E94: 6.5.1 | F94: Internal Quality Assurance Cell (IQAC) has contributed significantly for institutionalizing the quality assurance strategies and processes visible in terms of – Incremental improvements made for the preceding five years with regard to quality (in case of first cycle) Incremental improvements made for the preceding five years with regard to quality and post accreditation quality initiatives (second and subsequent cycles) Describe two practices institutionalized as a result of IQAC initiatives within a maximum of 500 words | G94: 10 | H94: 30 | L94: =K94*G94 -> 0 | M94: =SUM(L94:L96) -> 40 | N94: =M94/H94 -> 1.3333333
A95: 93 | B95: 6. Governance, Leadership and Management | C95: 6.5 Internal Quality Assurance System (IQAS) | D95: QlM | E95: 6.5.2 | F95: The institution reviews its teaching learning process, structures & methodologies of operations and learning outcomes at periodic intervals through IQAC set up as per norms Describe any two examples of institutional reviews and implementation of teaching learning reforms facilitated by the IQAC within a maximum of 500 words each | G95: 10 | L95: =K95*G95 -> 0
A96: 94 | B96: 6. Governance, Leadership and Management | C96: 6.5 Internal Quality Assurance System (IQAS) | D96: QnM | E96: 6.5.3 | F96: Quality assurance initiatives of the institution include: 1. Regular meeting of Internal Quality Assurance Cell (IQAC); Feedback collected, analysed and used for improvements 2. Collaborative quality initiatives with other institution(s) 3. Participation in NIRF 4. Any other quality audit recognized by state, national or international agencies (ISO Certification) | G96: 10 | J96: A | K96: =IF(EXACT(J96,"A"),4,IF(EXACT(J96,"B"),3,IF(EXACT(J96,"C"),2,IF(EXACT(J96,"D"),1,0)))) -> 4 | L96: =K96*G96 -> 40
A97: 95 | B97: 7. Institutional Values and Best Practices | C97: 7.1 Institutional Values and Social Responsibilities | D97: QlM | E97: 7.1.1 | F97: Measures initiated by the Institution for the promotion of gender equity during the last five years. Describe gender equity & sensitization in curricular and co-curricular activities, facilities for women on campus etc., within 500 words | G97: 5 | H97: 50 | I97: 100 | L97: =K97*G97 -> 0 | M97: =SUM(L97:L107) -> 59 | N97: =M97/H97 -> 1.18 | O97: =SUM(M97:M109) -> 59 | P97: =O97/I97 -> 0.59
A98: 96 | B98: 7. Institutional Values and Best Practices | C98: 7.1 Institutional Values and Social Responsibilities | D98: QnM | E98: 7.1.2 | F98: The Institution has facilities for alternate sources of energy and energy conservation measures 1. Solar energy 2. Biogas plant 3. Wheeling to the Grid 4. Sensor-based energy conservation 5. Use of LED bulbs/ power efficient equipment | G98: 5 | J98: A | K98: =IF(EXACT(J98,"A"),4,IF(EXACT(J98,"B"),3,IF(EXACT(J98,"C"),2,IF(EXACT(J98,"D"),1,0)))) -> 4 | L98: =K98*G98 -> 20
A99: 97 | B99: 7. Institutional Values and Best Practices | C99: 7.1 Institutional Values and Social Responsibilities | D99: QlM | E99: 7.1.3 | F99: Describe the facilities in the Institution for the management of the following types of degradable and non-degradable waste (within 500 words) 1. Solid waste management 2. Liquid waste management 3. Biomedical waste management 4. E-waste management 5. Waste recycling system 6. Hazardous chemicals and radioactive waste management | G99: 4 | L99: =K99*G99 -> 0
A100: 98 | B100: 7. Institutional Values and Best Practices | C100: 7.1 Institutional Values and Social Responsibilities | D100: QnM | E100: 7.1.4 | F100: Water conservation facilities available in the Institution: 1. Rain water harvesting 2. Borewell /Open well recharge 3. Construction of tanks and bunds 4. Waste water recycling 5. Maintenance of water bodies and distribution system in the campus | G100: 4 | J100: C | K100: =IF(EXACT(J100,"A"),4,IF(EXACT(J100,"B"),3,IF(EXACT(J100,"C"),2,IF(EXACT(J100,"D"),1,0)))) -> 2 | L100: =K100*G100 -> 8
...

Sheet 107(Qn&Ql)m-GS
A1: Grade Sheet
A2: Name of the Institution: | C2: ='Autonomous 107m'!$J$2 -> Institute Name
A3: Type of the Institution: | C3: ='Autonomous 107m'!K$1 -> Autonomous
A4: Dates of Visit:
A5: No | B5: Criteria | C5: Weightage (Wi | D5: Criterion-wise weighted Grade Point (CrWGPi) | E5: Criterion- wise Grade Point Averages (CrWGPi/Wi) | G5: Range of Institutional Cumulative Grade Point Average (CGPA) | H5: Letter Grade | I5: Status
A6: 1 | B6: Curricular Aspects | C6: 150 | D6: =SUM('Autonomous 107m'!O3:O13) -> 320 | E6: =D6/C6 -> 2.1333333 | G6: 3.51-4.00 | H6: A++ | I6: Accredited
A7: 2 | B7: Teaching-learning and Evaluation | C7: 300 | D7: =SUM('Autonomous 107m'!O14:O31) -> 240 | E7: =D7/C7 -> 0.8 | G7: 3.26-3.500 | H7: A+ | I7: Accredited
A8: 3 | B8: Research, Innovations and Extension | C8: 150 | D8: =SUM('Autonomous 107m'!O32:O54) -> 114 | E8: =D8/C8 -> 0.76 | G8: 3.01-3.25 | H8: A | I8: Accredited
A9: 4 | B9: Infrastructure and Learning Resources | C9: 100 | D9: =SUM('Autonomous 107m'!O55:O68) -> 64 | E9: =D9/C9 -> 0.64 | G9: 2.76-3.00 | H9: B++ | I9: Accredited
A10: 5 | B10: Student Support and Progression | C10: 100 | D10: =SUM('Autonomous 107m'!O69:O81) -> 104 | E10: =D10/C10 -> 1.04 | G10: 2.51-2.75 | H10: B+ | I10: Accredited
A11: 6 | B11: Governance, Leadership and Management | C11: 100 | D11: =SUM('Autonomous 107m'!O82:O96) -> 94 | E11: =D11/C11 -> 0.94 | G11: 2.01-2.50 | H11: B | I11: Accredited
A12: 7 | B12: Institutional Values and Best Practices | C12: 100 | D12: =SUM('Autonomous 107m'!O97:O109) -> 59 | E12: =D12/C12 -> 0.59 | G12: 1.51-2.00 | H12: C | I12: Accredited
A13: Total | C13: =SUM(C6:C12) -> 1000 | D13: =SUM(D6:D12) -> 995 | E13: =D13/C13 -> 0.995 | G13: ≤ 1.50 | H13: D | I13: Not Accredited
A15: =D13/C13 -> 0.995
A17: =IF(AND($A$15<=4,$A$15>=3.51),"A++",IF(AND($A$15<=3.5,$A$15>=3.26),"A+",IF(AND($A$15<=3.25,$A$15>3.01),"A",IF(AND($A$15<=3,$A$15>=2.76),"B++",IF(AND($A$15<=2.75,$A$15>=2.51),"B+",IF(AND($A$15<=2.5,$A$15>=2.01),"B",IF(AND($A$15<=2,$A$15>=1.51),"C","D"))))))) -> D
A19: Criterion wise - Grade Sheet
A20: Name of the Institution: | C20: ='Autonomous 107m'!$J$2 -> Institute Name
A21: Type of the Institution: | C21: ='Autonomous 107m'!$K$1 -> Autonomous
A22: Dates of Visit:
A23: No | B23: Criteria and Key Indicators | C23: Key Indicator Weightage (Wi) | D23: Key Indicator Wise Weighted Grade Points (KIWGP)i
A24: Criterion 1: Curricular Aspects
A25: 1.1 | B25: Curriculum Planning and Implementation | C25: 50 | D25: =SUM('Autonomous 107m'!M3:M5) -> 120
A26: 1.2 | B26: Academic Flexibility | C26: 40 | D26: =SUM('Autonomous 107m'!M6:M7) -> 100
A27: 1.3 | B27: Curriculum Enrichment | C27: 40 | D27: =SUM('Autonomous 107m'!M8:M11) -> 50
A28: 1.4 | B28: Feedback System | C28: 20 | D28: =SUM('Autonomous 107m'!M12:M13) -> 50
A29: Total | C29: =SUM(C25:C28) -> 150 | D29: =SUM(D25:D28) -> 320
D30: Grade | E30: =IF(AND($E$29<=4,$E$29>=3.51),"A++",IF(AND($E$29<=3.5,$E$29>=3.26),"A+",IF(AND($E$29<=3.25,$E$29>3.01),"A",IF(AND($E$29<=3,$E$29>=2.76),"B++",IF(AND($E$29<=2.75,$E$29>=2.51),"B+",IF(AND($E$29<=2.5,$E$29>=2.01),"B",IF(AND($E$29<=2,$E$29>=1.51),"C","D"))))))) -> D
A31: =80/70 -> 1.1428571
A32: Criterion 2: Teaching-learning and Evaluation
A33: 2.1 | B33: Student Enrollment and Profile | C33: 20 | D33: =SUM('Autonomous 107m'!M14:M15) -> 80
A34: 2.2 | B34: Catering to Student Diversity | C34: 30 | D34: =SUM('Autonomous 107m'!M16:M17) -> 0
A35: 2.3 | B35: Teaching- Learning Process | C35: 50 | D35: =SUM('Autonomous 107m'!M18:M21) -> 0
A36: 2.4 | B36: Teacher Profile and Quality | C36: 50 | D36: =SUM('Autonomous 107m'!M22:M24) -> 60
A37: 2.5 | B37: Evaluation Process and Reforms | C37: 50 | D37: =SUM('Autonomous 107m'!M25:M27) -> 20
A38: 2.6 | B38: Student Performance and Learning Outcomes | C38: 50 | D38: =SUM('Autonomous 107m'!M28:M30) -> 80
A39: 2.7 | B39: Student Satisfaction Survey | C39: 50 | D39: =SUM('Autonomous 107m'!M31) -> 0
A40: Total | C40: =SUM(C33:C39) -> 300 | D40: =SUM(D33:D39) -> 240
A41: =D40/C40 -> 0.8
A42: Criterion 3: Research, Innovations and Extension
A43: 3.1 | B43: Promotion of Research and Facilities | C43: 20 | D43: =SUM('Autonomous 107m'!M32:M34) -> 0
A44: 3.2 | B44: Resource Mobilization for Research | C44: 10 | D44: =SUM('Autonomous 107m'!M35:M38) -> 14
A45: 3.3 | B45: Innovation Ecosystem | C45: 10 | D45: =SUM('Autonomous 107m'!M39:M40) -> 10
A46: 3.4 | B46: Research Publications and Awards | C46: 30 | D46: =SUM('Autonomous 107m'!M41:M46) -> 10
A47: 3.5 | B47: Consultancy | C47: 10 | D47: =SUM('Autonomous 107m'!M47:M48) -> 0
A48: 3.6 | B48: Extension Activities | C48: 50 | D48: =SUM('Autonomous 107m'!M49:M52) -> 60
A49: 3.7 | B49: Collaboration | C49: 20 | D49: =SUM('Autonomous 107m'!M53:M54) -> 20
A50: Total | C50: =SUM(C43:C49) -> 150 | D50: =SUM(D43:D49) -> 114
A51: =D50/C50 -> 0.76
A52: Criterion 4: Infrastructure and Learning Resources
A53: 4.1 | B53: Physical Facilities | C53: 30 | D53: =SUM('Autonomous 107m'!M55:M58) -> 0
A54: 4.2 | B54: Library as a Learning Resource | C54: 20 | D54: =SUM('Autonomous 107m'!M59:M62) -> 20
A55: 4.3 | B55: IT Infrastructure | C55: 30 | D55: =SUM('Autonomous 107m'!M63:M66) -> 44
A56: 4.4 | B56: Maintenance of Campus Infrastructure | C56: 20 | D56: =SUM('Autonomous 107m'!M67:M68) -> 0
A57: Total | C57: =SUM(C53:C56) -> 100 | D57: =SUM(D53:D56) -> 64
A58: =D57/C57 -> 0.64
A59: Criterion 5: Student Support and Progression
A60: 5.1 | B60: Student Support | C60: 30 | D60: =SUM('Autonomous 107m'!M69:M73) -> 39
A61: 5.2 | B61: Student Progression | C61: 30 | D61: =SUM('Autonomous 107m'!M74:M76) -> 40
A62: 5.3 | B62: Student Participation and Activities | C62: 30 | D62: =SUM('Autonomous 107m'!M77:M79) -> 20
A63: 5.4 | B63: Alumni Engagement | C63: 10 | D63: =SUM('Autonomous 107m'!M80:M81) -> 5
A64: Total | C64: =SUM(C60:C63) -> 100 | D64: =SUM(D60:D63) -> 104
A65: =D64/C64 -> 1.04
A66: Criterion 6: Governance, Leadership and Management
A67: 6.1 | B67: Institutional Vision and Leadership | C67: 10 | D67: =SUM('Autonomous 107m'!M82:M83) -> 0
A68: 6.2 | B68: Strategy Development and Development | C68: 10 | D68: =SUM('Autonomous 107m'!M84:M86) -> 12
A69: 6.3 | B69: Faculty Empowerment Strategies | C69: 30 | D69: =SUM('Autonomous 107m'!M87:M90) -> 42
A70: 6.4 | B70: Financial Management and Resource Mobilization | C70: 20 | D70: =SUM('Autonomous 107m'!M91:M93) -> 0
A71: 6.5 | B71: Internal Quality Assurance System | C71: 30 | D71: =SUM('Autonomous 107m'!M94:M96) -> 40
A72: Total | C72: =SUM(C67:C71) -> 100 | D72: =SUM(D67:D71) -> 94
A73: =D72/C72 -> 0.94
A74: Criterion 7: Institutional Values and Best Practices
A75: 7.1 | B75: Institutional Values and Social Responsibilities | C75: 50 | D75: =SUM('Autonomous 107m'!M97:M107) -> 59
A76: 7.2 | B76: Best Practices | C76: 30 | D76: =SUM('Autonomous 107m'!M108) -> 0
A77: 7.3 | B77: Institutional Distinctiveness | C77: 20 | D77: =SUM('Autonomous 107m'!M109) -> 0
A78: Total | C78: =SUM(C75:C77) -> 100 | D78: =SUM(D75:D77) -> 59
A79: =D78/C78 -> 0.59
A80: Grand Total | C80: =SUM(C29,C40,C50,C57,C64,C72,C78) -> 1000 | D80: =SUM(D29,D40,D50,D57,D64,D72,D78) -> 995
A81: =D80/C80 -> 0.995
A82: =IF(AND($A$81<=4,$A$81>=3.51),"A++",IF(AND($A$81<=3.5,$A$81>=3.26),"A+",IF(AND($A$81<=3.25,$A$81>3.01),"A",IF(AND($A$81<=3,$A$81>=2.76),"B++",IF(AND($A$81<=2.75,$A$81>=2.51),"B+",IF(AND($A$81<=2.5,$A$81>=2.01),"B",IF(AND($A$81<=2,$A$81>=1.51),"C","D"))))))) -> D

Sheet 55m-Gradesheet(GS)
A5: No | B5: Criteria | C5: Weightage (Wi | D5: Criterion-wise weighted Grade Point (CrWGPi) | E5: Criterionwise Grade Point Averages (CrWGPi/Wi) | G5: Range of Institutional Cumulative Grade Point Average (CGPA) | H5: Letter Grade | I5: Status
A6: 1 | B6: Curricular Aspects | C6: 100 | D6: =SUM('Autonomous 107m'!M3:M8) -> 270 | E6: =D6/C6 -> 2.7 | G6: 3.51-4.00 | H6: A++ | I6: Accredited
A7: 2 | B7: Teaching-learning and Evaluation | C7: 350 | D7: =SUM('Autonomous 107m'!M9:M18) -> 130 | E7: =D7/C7 -> 0.37142857 | G7: 3.26-3.500 | H7: A+ | I7: Accredited
A8: 3 | B8: Research, Innovations and Extension | C8: 110 | D8: =SUM('Autonomous 107m'!M19:M27) -> 80 | E8: =D8/C8 -> 0.72727273 | G8: 3.01-3.25 | H8: A | I8: Accredited
A9: 4 | B9: Infrastructure and Learning Resources | C9: 100 | D9: =SUM('Autonomous 107m'!M28:M33) -> 80 | E9: =D9/C9 -> 0.8 | G9: 2.76-3.00 | H9: B++ | I9: Accredited
A10: 5 | B10: Student Support and Progression | C10: 140 | D10: =SUM('Autonomous 107m'!M34:M42) -> 34 | E10: =D10/C10 -> 0.24285714 | G10: 2.51-2.75 | H10: B+ | I10: Accredited
A11: 6 | B11: Governance, Leadership and Management | C11: 100 | D11: =SUM('Autonomous 107m'!M43:M51) -> 60 | E11: =D11/C11 -> 0.6 | G11: 2.01-2.50 | H11: B | I11: Accredited
A12: 7 | B12: Institutional Values and Best Practices | C12: 100 | D12: =SUM('Autonomous 107m'!M52:M57) -> 20 | E12: =D12/C12 -> 0.2 | G12: 1.51-2.00 | H12: C | I12: Accredited
C13: =SUM(C6:C12) -> 1000 | D13: =SUM(D6:D12) -> 674 | E13: =D13/C13 -> 0.674 | G13: ≤ 1.50 | H13: D | I13: Not Accredited
D14: Grade | E14: =IF(AND($E$13<=4,$E$13>=3.51),"A++",IF(AND($E$13<=3.5,$E$13>=3.26),"A+",IF(AND($E$13<=3.25,$E$13>3.01),"A",IF(AND($E$13<=3,$E$13>=2.76),"B++",IF(AND($E$13<=2.75,$E$13>=2.51),"B+",IF(AND($E$13<=2.5,$E$13>=2.01),"B",IF(AND($E$13<=2,$E$13>=1.51),"C","D"))))))) -> D
A16: No | B16: Criteria and Key Indicators | C16: Key Indicator Weightage (Wi) | D16: Key Indicator Wise Weighted Grade Points (KIWGP)i | E16: Key Indicator wise Grade Point Averages (CrWGPi/Wi)
A17: Criterion 1: Curricular Aspects
A18: 1.1 | B18: Curriculum Planning and Implementation | C18: 20 | D18: =SUM('Autonomous 107m'!L3) -> 0
A19: 1.2 | B19: Academic Flexibility | C19: 30 | D19: =SUM('Autonomous 107m'!L4:L5) -> 120
A20: 1.3 | B20: 1.3 Curriculum Enrichment | C20: 30 | D20: =SUM('Autonomous 107m'!L6:L7) -> 100
A21: 1.4 | B21: 1.4 Feedback System | C21: 20 | D21: =SUM('Autonomous 107m'!L8) -> 0
C22: =SUM(C18:C21) -> 100 | D22: =SUM(D18:D21) -> 220
D23: Grade | E23: *
A24: Criterion 2: Teaching-learning and Evaluation
A25: 2.1 | B25: Student Enrollment and Profile | C25: 40 | D25: =SUM('Autonomous 107m'!L9:L10) -> 50
A26: 2.2 | B26: Catering to Student Diversity | C26: 40 | D26: =SUM('Autonomous 107m'!L11) -> 0
A27: 2.3 | B27: Teaching- Learning Process | C27: 40 | D27: =SUM('Autonomous 107m'!L12) -> 30
A28: 2.4 | B28: Teacher Profile and Quality | C28: 40 | D28: =SUM('Autonomous 107m'!L13:L14) -> 60
A29: 2.5 | B29: Evaluation Process and Reforms | C29: 40 | D29: =SUM('Autonomous 107m'!L15) -> 40
A30: 2.6 | B30: Student Performance and Learning Outcomes | C30: 90 | D30: =SUM('Autonomous 107m'!L16:L17) -> 0
A31: 2.7 | B31: Student Satisfaction Survey | C31: 60 | D31: =SUM('Autonomous 107m'!L18) -> 0
C32: =SUM(C25:C31) -> 350 | D32: =SUM(D25:D31) -> 180
D33: Grade | E33: =IF(AND($E$32<=4,$E$32>=3.51),"A++",IF(AND($E$32<=3.5,$E$32>=3.26),"A+",IF(AND($E$32<=3.25,$E$32>3.01),"A",IF(AND($E$32<=3,$E$32>=2.76),"B++",IF(AND($E$32<=2.75,$E$32>=2.51),"B+",IF(AND($E$32<=2.5,$E$32>=2.01),"B",IF(AND($E$32<=2,$E$32>=1.51),"C","D"))))))) -> D
A34: Criterion 3: Research, Innovations and Extension
A35: 3.1 | B35: Resource Mobilization for Research | C35: 10 | D35: =SUM('Autonomous 107m'!L19) -> 0
A36: 3.2 | B36: Innovation Ecosystem | C36: 15 | D36: =SUM('Autonomous 107m'!L20:L21) -> 0
A37: 3.3 | B37: Research Publications and Awards | C37: 25 | D37: =SUM('Autonomous 107m'!L22:L23) -> 60
A38: 3.4 | B38: Extension Activities | C38: 40 | D38: =SUM('Autonomous 107m'!L24:L26) -> 20
A39: 3.5 | B39: Collaboration | C39: 20 | D39: =SUM('Autonomous 107m'!L27) -> 0
C40: =SUM(C35:C39) -> 110 | D40: =SUM(D35:D39) -> 80
D41: Grade | E41: =IF(AND($E$47<=4,$E$47>=3.51),"A++",IF(AND($E$47<=3.5,$E$47>=3.26),"A+",IF(AND($E$47<=3.25,$E$47>3.01),"A",IF(AND($E$47<=3,$E$47>=2.76),"B++",IF(AND($E$47<=2.75,$E$47>=2.51),"B+",IF(AND($E$47<=2.5,$E$47>=2.01),"B",IF(AND($E$47<=2,$E$47>=1.51),"C","D"))))))) -> D
A42: Criterion 4: Infrastructure and Learning Resources
A43: 4.1 | B43: Physical Facilities | C43: 30 | D43: =SUM('Autonomous 107m'!L28:L29) -> 0
A44: 4.2 | B44: Library as a Learning Resource | C44: 20 | D44: =SUM('Autonomous 107m'!L30) -> 80
A45: 4.3 | B45: IT Infrastructure | C45: 30 | D45: =SUM('Autonomous 107m'!L31:L32) -> 0
A46: 4.4 | B46: Maintenance of Campus Infrastructure | C46: 20 | D46: =SUM('Autonomous 107m'!L33) -> 0
C47: =SUM(C43:C46) -> 100 | D47: =SUM(D43:D46) -> 80
D48: Grade | E48: =IF(AND($E$47<=4,$E$47>=3.51),"A++",IF(AND($E$47<=3.5,$E$47>=3.26),"A+",IF(AND($E$47<=3.25,$E$47>3.01),"A",IF(AND($E$47<=3,$E$47>=2.76),"B++",IF(AND($E$47<=2.75,$E$47>=2.51),"B+",IF(AND($E$47<=2.5,$E$47>=2.01),"B",IF(AND($E$47<=2,$E$47>=1.51),"C","D"))))))) -> D
A49: Criterion 5: Student Support and Progression
A50: 5.1 | B50: Student Support | C50: 50 | D50: =SUM('Autonomous 107m'!L34:L37) -> 8
A51: 5.2 | B51: Student Progression | C51: 30 | D51: =SUM('Autonomous 107m'!L38:L39) -> 6
A52: 5.3 | B52: Student Participation and Activities | C52: 50 | D52: =SUM('Autonomous 107m'!L40:L41) -> 20
A53: 5.4 | B53: Alumni Engagement | C53: 10 | D53: =SUM('Autonomous 107m'!L42) -> 0
C54: =SUM(C50:C53) -> 140 | D54: =SUM(D50:D53) -> 34
D55: Grade | E55: =IF(AND($E$54<=4,$E$54>=3.51),"A++",IF(AND($E$54<=3.5,$E$54>=3.26),"A+",IF(AND($E$54<=3.25,$E$54>3.01),"A",IF(AND($E$54<=3,$E$54>=2.76),"B++",IF(AND($E$54<=2.75,$E$54>=2.51),"B+",IF(AND($E$54<=2.5,$E$54>=2.01),"B",IF(AND($E$54<=2,$E$54>=1.51),"C","D"))))))) -> D
A56: Criterion 6: Governance, Leadership and Management
A57: 6.1 | B57: Institutional Vision and Leadership | C57: 10 | D57: =SUM('Autonomous 107m'!L43) -> 0
A58: 6.2 | B58: Strategy Development and Development | C58: 10 | D58: =SUM('Autonomous 107m'!L44:L45) -> 0
A59: 6.3 | B59: Faculty Empowerment Strategies | C59: 35 | D59: =SUM('Autonomous 107m'!L46:L48) -> 0
A60: 6.4 | B60: Financial Management and Resource Mobilization | C60: 15 | D60: =SUM('Autonomous 107m'!L49) -> 0
A61: 6.5 | B61: Internal Quality Assurance System | C61: 30 | D61: =SUM('Autonomous 107m'!L50:L51) -> 0
C62: =SUM(C57:C61) -> 100 | D62: =SUM(D57:D61) -> 0
D63: Grade | E63: =IF(AND($E$62<=4,$E$62>=3.51),"A++",IF(AND($E$62<=3.5,$E$62>=3.26),"A+",IF(AND($E$62<=3.25,$E$62>3.01),"A",IF(AND($E$62<=3,$E$62>=2.76),"B++",IF(AND($E$62<=2.75,$E$62>=2.51),"B+",IF(AND($E$62<=2.5,$E$62>=2.01),"B",IF(AND($E$62<=2,$E$62>=1.51),"C","D"))))))) -> D
A64: Criterion 7: Institutional Values and Best Practices
A65: 7.1 | B65: Institutional Values and Social Responsibilities | C65: 50 | D65: =SUM('Autonomous 107m'!L52:L55) -> 80
A66: 7.2 | B66: Best Practices | C66: 30 | D66: =SUM('Autonomous 107m'!L56) -> 0
A67: 7.3 | B67: Institutional Distinctiveness | C67: 20 | D67: =SUM('Autonomous 107m'!L57) -> 0
C68: =SUM(C65:C67) -> 100 | D68: =SUM(D65:D67) -> 80
D69: Grade | E69: =IF(AND($E$68<=4,$E$68>=3.51),"A++",IF(AND($E$68<=3.5,$E$68>=3.26),"A+",IF(AND($E$68<=3.25,$E$68>3.01),"A",IF(AND($E$68<=3,$E$68>=2.76),"B++",IF(AND($E$68<=2.75,$E$68>=2.51),"B+",IF(AND($E$68<=2.5,$E$68>=2.01),"B",IF(AND($E$68<=2,$E$68>=1.51),"C","D"))))))) -> D

Sheet Qn (72m)
J1: Response | K1: Autonomous
A2: S. No | B2: Criteria © | C2: Key Indicator (KI) | D2: Metric (M) Type | E2: Metric (M) Num | F2: Metric (M) Description | G2: M Wt | H2: KI Wt | I2: © Wt | J2: Institute Name | K2: Metric Grade scale (0-4) | L2: M wise weighted Grade points | M2: KIwise weighted Grade points | N2: KIwise weighted Grade points Average | O2: ©Wise Weighted Average | P2: ©Wise Weighted Grade Point Average
A3: 1 | B3: 1. Curricular Aspects | C3: 1.2 Academic Flexibility | D3: QnM | E3: 1.1.2 | F3: Percentage of Programmes where syllabus revision was carried out during the last five years 1.1.2.1: How many Programmes were revised out of total number of Programmes offered during the same period within last five years? 1.1.2.2 : Number of all Programmes offered by the institution during the last five years | G3: 20 | H3: 30 | I3: 120 | J3: =VLOOKUP(E3,'Autonomous 107m'!$E$3:$J$109,6,0) -> 92.86 | K3: =IF(J3>80,4,IF(AND(J3<=80,J3>60),3,IF(AND(J3<=60,J3>40),2,IF(AND(J3<=40,J3>20),1,IF(J3<=20,0))))) -> 4 | L3: =K3*G3 -> 80 | M3: 120 | N3: =M3/H3 -> 4 | O3: =SUM(M3:M11) -> 410 | P3: =O3/I3 -> 3.4166667
A4: 2 | B4: 1. Curricular Aspects | C4: 1.2 Academic Flexibility | D4: QnM | E4: 1.1.3 | F4: Average percentage of courses having focus on employability/ entrepreneurship/ skill development offered by the institution during the last five years 1.1.3.1: Number of courses having focus on employability/ entrepreneurship/ skill development year wise during last five years | G4: 10 | J4: =VLOOKUP(E4,'Autonomous 107m'!$E$3:$J$109,6,0) -> 84.19 | K4: =IF(J4>80,4,IF(AND(J4<=80,J4>60),3,IF(AND(J4<=60,J4>40),2,IF(AND(J4<=40,J4>20),1,IF(J4<=20,0))))) -> 4 | L4: =K4*G4 -> 40
A5: 3 | B5: 1. Curricular Aspects | C5: 1.3 Curriculum Enrichment | D5: QnM | E5: 1.2.1 | F5: Percentage of new courses introduced of the total number of courses across all programs offered during the last five years 1.2.1.1: How many new courses are introduced within the last five years 1.2.1.2 : Number of courses offered by the institution across all Programmes during the last five years | G5: 20 | H5: 40 | J5: =VLOOKUP(E5,'Autonomous 107m'!$E$3:$J$109,6,0) -> 38.71 | K5: =IF(J5>80,4,IF(AND(J5<=80,J5>60),3,IF(AND(J5<=60,J5>40),2,IF(AND(J5<=40,J5>20),1,IF(J5<=20,0))))) -> 1 | L5: =K5*G5 -> 20 | M5: 160 | N5: =M5/H5 -> 4
A6: 4 | B6: 1. Curricular Aspects | C6: 1.4 Feedback System | D6: QnM | E6: 1.2.2 | F6: Percentage of Programmes in which Choice Based Credit System (CBCS)/elective course system has been implemented (Data for the latest completed academic year ) 1.2.2.1: Number of Programmes in which CBCS/Elective course system implemented. | G6: 20 | J6: =VLOOKUP(E6,'Autonomous 107m'!$E$3:$J$109,6,0) -> 81.25 | K6: =IF(J6>80,4,IF(AND(J6<=80,J6>60),3,IF(AND(J6<=60,J6>40),2,IF(AND(J6<=40,J6>20),1,IF(J6<=20,0))))) -> 4 | L6: =K6*G6 -> 80
A7: 5 | B7: 2. Teaching-Learning and Evaluation | C7: 2.1 Student Enrolment and Profile | D7: QnM | E7: 1.3.2 | F7: Number of value-added courses for imparting transferable and life skills offered during last five years 1.3.2.1: How many new value-added courses are added within the last 5 years | G7: 10 | H7: 30 | J7: =VLOOKUP(E7,'Autonomous 107m'!$E$3:$J$109,6,0) -> 87 | K7: =IF(J7>80,4,IF(AND(J7<=80,J7>60),3,IF(AND(J7<=60,J7>40),2,IF(AND(J7<=40,J7>20),1,IF(J7<=20,0))))) -> 4 | L7: =K7*G7 -> 40 | M7: 80 | N7: =M7/H7 -> 2.6666667
A8: 6 | B8: 2. Teaching-Learning and Evaluation | C8: 2.1 Student Enrolment and Profile | D8: QnM | E8: 1.3.3 | F8: Average Percentage of students enrolled in the courses under 1.3.2 above 1.3.3.1: Number of students enrolled in value added courses (beyond the curriculum) offered year wise during last five year | G8: 10 | J8: =VLOOKUP(E8,'Autonomous 107m'!$E$3:$J$109,6,0) -> 32.64 | K8: =IF(J8>80,4,IF(AND(J8<=80,J8>60),3,IF(AND(J8<=60,J8>40),2,IF(AND(J8<=40,J8>20),1,IF(J8<=20,0))))) -> 1 | L8: =K8*G8 -> 10
A9: 7 | B9: 2. Teaching-Learning and Evaluation | C9: 2.2 Student Teacher Ratio | D9: QnM | E9: 1.3.4 | F9: Percentage of students undertaking field projects/ internships / student projects (Data for the latest completed academic year) 1.3.4.1: Number of students undertaking field projects / internships / student projects | G9: 10 | J9: =VLOOKUP(E9,'Autonomous 107m'!$E$3:$J$109,6,0) -> 61.81 | K9: =IF(J9>80,4,IF(AND(J9<=80,J9>60),3,IF(AND(J9<=60,J9>40),2,IF(AND(J9<=40,J9>20),1,IF(J9<=20,0))))) -> 3 | L9: =K9*G9 -> 30
A10: 8 | B10: 2. Teaching-Learning and Evaluation | C10: 2.4 Teacher Profile and Quality | D10: QnM | E10: 1.4.1 | F10: Structured feedback for design and review of syllabus ( semester wise / year wise) is obtained from 1) Students, 2) Teachers, 3) Employers, 4) Alumni | G10: 10 | H10: 20 | J10: =VLOOKUP(E10,'Autonomous 107m'!$E$3:$J$109,6,0) -> B | K10: =IF(EXACT(J10,"A"),4,IF(EXACT(J10,"B"),3,IF(EXACT(J10,"C"),2,IF(EXACT(J10,"D"),1,0)))) -> 3 | L10: =K10*G10 -> 30 | M10: 50 | N10: =M10/H10 -> 2.5
A11: 9 | B11: 2. Teaching-Learning and Evaluation | C11: 2.4 Teacher Profile and Quality | D11: QnM | E11: 1.4.2 | F11: The feedback system of the Institution comprises of the following : A. Feedback collected, analysed and action taken and report made available on website B. Feedback collected, analysed and action taken C. Feedback collected and analysed D. Feedback collected E. Feedback not obtained | G11: 10 | J11: =VLOOKUP(E11,'Autonomous 107m'!$E$3:$J$109,6,0) -> C | K11: =IF(EXACT(J11,"A"),4,IF(EXACT(J11,"B"),3,IF(EXACT(J11,"C"),2,IF(EXACT(J11,"D"),1,0)))) -> 2 | L11: =K11*G11 -> 20
A12: 10 | B12: 2. Teaching-Learning and Evaluation | C12: 2.6 Student Performance and Learning Outcomes | D12: QnM | E12: 2.1.1 | F12: Average Enrolment percentage (Average of last five years) 2.1.1.1: Number of students admitted year wise during last five years 2.1.1.2: Number of sanctioned seats year wise during last five years | G12: 10 | H12: 20 | I12: 200 | J12: =VLOOKUP(E12,'Autonomous 107m'!$E$3:$J$109,6,0) -> 85.42 | K12: =IF(J12>80,4,IF(AND(J12<=80,J12>60),3,IF(AND(J12<=60,J12>40),2,IF(AND(J12<=40,J12>20),1,IF(J12<=20,0))))) -> 4 | L12: =K12*G12 -> 40 | M12: 80 | N12: =M12/H12 -> 4 | O12: =SUM(M12:M22) -> 619 | P12: =O12/I12 -> 3.095
A13: 11 | B13: 2. Teaching-Learning and Evaluation | C13: 2.7 Student Satisfaction Survey | D13: QnM | E13: 2.1.2 | F13: Average percentage of seats filled against reserved categories (SC, ST, OBC, Divyangjan, etc. as per applicable reservation policy ) during the last five years ( exclusive of supernumerary seats) 2.1.2.1: Number of actual students admitted from the reserved categories year wise during last five years | G13: 10 | J13: =VLOOKUP(E13,'Autonomous 107m'!$E$3:$J$109,6,0) -> 97.91 | K13: =IF(J13>80,4,IF(AND(J13<=80,J13>60),3,IF(AND(J13<=60,J13>40),2,IF(AND(J13<=40,J13>20),1,IF(J13<=20,0))))) -> 4 | L13: =K13*G13 -> 40
A14: 12 | B14: 3. Research, Innovations and Extension | C14: 3.1 Resource Mobilization for Research | D14: QnM | E14: 2.2.2 | F14: Student - Full time teacher ratio (Data for the latest completed academic year) | G14: 15 | H14: 15 | J14: =VLOOKUP(E14,'Autonomous 107m'!$E$3:$J$109,6,0) -> 16.13 | K14: =IF(J14>80,4,IF(AND(J14<=80,J14>60),3,IF(AND(J14<=60,J14>40),2,IF(AND(J14<=40,J14>20),1,IF(J14<=20,0))))) -> 0 | L14: =K14*G14 -> 0 | M14: 45 | N14: =M14/H14 -> 3
A15: 13 | B15: 3. Research, Innovations and Extension | C15: 3.2 Innovation Ecosystem | D15: QnM | E15: 2.3.3 | F15: Ratio of students to mentor for academic and other related issues (Data for the latest completed academic year ) 2.3.3.1: Number of mentors Number of students assigned to each Mentor | G15: 10 | H15: 10 | J15: =VLOOKUP(E15,'Autonomous 107m'!$E$3:$J$109,6,0) -> 0.79236111 | K15: =IF(J15>80,4,IF(AND(J15<=80,J15>60),3,IF(AND(J15<=60,J15>40),2,IF(AND(J15<=40,J15>20),1,IF(J15<=20,0))))) -> 0 | L15: =K15*G15 -> 0 | M15: 30 | N15: =M15/H15 -> 3
A16: 14 | B16: 3. Research, Innovations and Extension | C16: 3.3 Research Publications and Awards | D16: QnM | E16: 2.4.1 | F16: Average percentage of full time teachers against sanctioned posts during the last five years | G16: 15 | H16: 50 | J16: =VLOOKUP(E16,'Autonomous 107m'!$E$3:$J$109,6,0) -> 99.34 | K16: =IF(J16>80,4,IF(AND(J16<=80,J16>60),3,IF(AND(J16<=60,J16>40),2,IF(AND(J16<=40,J16>20),1,IF(J16<=20,0))))) -> 4 | L16: =K16*G16 -> 60 | M16: 110 | N16: =M16/H16 -> 2.2
A17: 15 | B17: 3. Research, Innovations and Extension | C17: 3.3 Research Publications and Awards | D17: QnM | E17: 2.4.2 | F17: Average percentage of full time teachers with Ph.D. / D.M. / M.Ch. / D.N.B Super speciality / D.Sc. / D.Litt. during the last five years 2.4.2.1: Number of full time teachers with Ph.D./ D.M. / M.Ch. / D.N.B Super speciality / D.Sc. / D.Litt. year wise during last five years | G17: 20 | J17: =VLOOKUP(E17,'Autonomous 107m'!$E$3:$J$109,6,0) -> 11.09 | K17: =IF(J17>80,4,IF(AND(J17<=80,J17>60),3,IF(AND(J17<=60,J17>40),2,IF(AND(J17<=40,J17>20),1,IF(J17<=20,0))))) -> 0 | L17: =K17*G17 -> 0
A18: 16 | B18: 3. Research, Innovations and Extension | C18: 3.4 Extension Activities | D18: QnM | E18: 2.4.3 | F18: Average teaching experience of full time teachers in the same institution (Data for the latest completed academic year in number of years 2.4.3.1: Total experience of full-time teachers | G18: 15 | J18: =VLOOKUP(E18,'Autonomous 107m'!$E$3:$J$109,6,0) -> 5.69 | K18: =IF(J18>80,4,IF(AND(J18<=80,J18>60),3,IF(AND(J18<=60,J18>40),2,IF(AND(J18<=40,J18>20),1,IF(J18<=20,0))))) -> 0 | L18: =K18*G18 -> 0
A19: 17 | B19: 3. Research, Innovations and Extension | C19: 3.5 Collaboration | D19: QnM | E19: 2.5.1 | F19: Average number of days from the date of last semester-end/ year- end examination till the declaration of results during the last five years 2.5.1.1: Number of days from the date of last semester-end/ year- end examination till the declaration of results year wise during the last five years | G19: 20 | H19: 35 | J19: =VLOOKUP(E19,'Autonomous 107m'!$E$3:$J$109,6,0) -> 21 | K19: =IF(J19>80,4,IF(AND(J19<=80,J19>60),3,IF(AND(J19<=60,J19>40),2,IF(AND(J19<=40,J19>20),1,IF(J19<=20,0))))) -> 1 | L19: =K19*G19 -> 20 | M19: 100 | N19: =M19/H19 -> 2.8571429
A20: 18 | B20: 4. Infrastructure and Learning Resources | C20: 4.1 Physical Facilities | D20: QnM | E20: 2.5.2 | F20: Average percentage of student complaints/grievances about evaluation against total number appeared in the examinations during the last five years 2.5.2.1: Number of complaints/grievances about evaluation year wise during last five years | G20: 15 | J20: =VLOOKUP(E20,'Autonomous 107m'!$E$3:$J$109,6,0) -> 12.61 | K20: =IF(J20>80,4,IF(AND(J20<=80,J20>60),3,IF(AND(J20<=60,J20>40),2,IF(AND(J20<=40,J20>20),1,IF(J20<=20,0))))) -> 0 | L20: =K20*G20 -> 0
A21: 19 | B21: 4. Infrastructure and Learning Resources | C21: 4.3 IT Infrastructure | D21: QnM | E21: 2.6.3 | F21: Pass percentage of students (Data for the latest completed academic year) 2.6.3.1: Total number of final year students who passed the examination conducted by Institution. 2.6.3.2: Total number of final year students who appeared for the examination | G21: 20 | H21: 20 | J21: =VLOOKUP(E21,'Autonomous 107m'!$E$3:$J$109,6,0) -> 90.9 | K21: =IF(J21>80,4,IF(AND(J21<=80,J21>60),3,IF(AND(J21<=60,J21>40),2,IF(AND(J21<=40,J21>20),1,IF(J21<=20,0))))) -> 4 | L21: =K21*G21 -> 80 | M21: 80 | N21: =M21/H21 -> 4
A22: 20 | B22: 4. Infrastructure and Learning Resources | C22: 4.4 Maintenance of Campus Infrastructure | D22: QnM | E22: 2.7.1 | F22: Online student satisfaction survey regarding to teaching learning process. (Online survey to be conducted) | G22: 50 | H22: 50 | J22: =VLOOKUP(E22,'Autonomous 107m'!$E$3:$J$109,6,0) -> 3.48 | K22: =IF(J22>80,4,IF(AND(J22<=80,J22>60),3,IF(AND(J22<=60,J22>40),2,IF(AND(J22<=40,J22>20),1,IF(J22<=20,0))))) -> 0 | L22: =K22*G22 -> 0 | M22: 174 | N22: =M22/H22 -> 3.48
A23: 21 | B23: 5. Student Support and Progression | C23: 5.1 Student Support | D23: QnM | E23: 3.1.2 | F23: The institution provides seed money to its teachers for research (Average per year) 3.1.2.1: The amount of seed money provided by institution to its teachers for research year wise during last five years (INR in lakhs) | G23: 8 | H23: 14 | I23: 129 | J23: =VLOOKUP(E23,'Autonomous 107m'!$E$3:$J$109,6,0) -> 0 | K23: =IF(J23>80,4,IF(AND(J23<=80,J23>60),3,IF(AND(J23<=60,J23>40),2,IF(AND(J23<=40,J23>20),1,IF(J23<=20,0))))) -> 0 | L23: =K23*G23 -> 0 | M23: 0 | N23: =M23/H23 -> 0 | O23: =SUM(M23:M42) -> 207 | P23: =O23/I23 -> 1.6046512
A24: 22 | B24: 5. Student Support and Progression | C24: 5.1 Student Support | D24: QnM | E24: 3.1.3 | F24: Percentage of teachers awarded national / international fellowship for advanced studies/research during the last five years 3.1.3.1: The number of teachers awarded national / international fellowship for advanced studies / research year wise during last five years | G24: 6 | J24: =VLOOKUP(E24,'Autonomous 107m'!$E$3:$J$109,6,0) -> 0.06 | K24: =IF(J24>80,4,IF(AND(J24<=80,J24>60),3,IF(AND(J24<=60,J24>40),2,IF(AND(J24<=40,J24>20),1,IF(J24<=20,0))))) -> 0 | L24: =K24*G24 -> 0
A25: 23 | B25: 5. Student Support and Progression | C25: 5.1 Student Support | D25: QnM | E25: 3.2.1 | F25: Grants received from Government and non-governmental agencies for research projects, endowments, Chairs in the institution during the last five years (INR in Lakhs) 3.2.1.1: Total Grants from Government and non-governmental agencies for research projects , endowments, Chairs in the institution during the last five years (INR in Lakhs) | G25: 2 | H25: 10 | J25: =VLOOKUP(E25,'Autonomous 107m'!$E$3:$J$109,6,0) -> 116.67 | K25: =IF(J25>80,4,IF(AND(J25<=80,J25>60),3,IF(AND(J25<=60,J25>40),2,IF(AND(J25<=40,J25>20),1,IF(J25<=20,0))))) -> 4 | L25: =K25*G25 -> 8 | M25: 17 | N25: =M25/H25 -> 1.7
A26: 24 | B26: 5. Student Support and Progression | C26: 5.1 Student Support | D26: QnM | E26: 3.2.2 | F26: Percentage of teachers having research projects during the last five years 3.2.2.1: Number of teachers having research projects during the last five years | G26: 2 | J26: =VLOOKUP(E26,'Autonomous 107m'!$E$3:$J$109,6,0) -> 1.02 | K26: =IF(J26>80,4,IF(AND(J26<=80,J26>60),3,IF(AND(J26<=60,J26>40),2,IF(AND(J26<=40,J26>20),1,IF(J26<=20,0))))) -> 0 | L26: =K26*G26 -> 0
A27: 25 | B27: 5. Student Support and Progression | C27: 5.2 Student Progression | D27: QnM | E27: 3.2.3 | F27: Percentage of teachers recognised as research guides 3.2.3.1: Number of teachers recognised as research guides | G27: 3 | J27: =VLOOKUP(E27,'Autonomous 107m'!$E$3:$J$109,6,0) -> 3.03 | K27: =IF(J27>80,4,IF(AND(J27<=80,J27>60),3,IF(AND(J27<=60,J27>40),2,IF(AND(J27<=40,J27>20),1,IF(J27<=20,0))))) -> 0 | L27: =K27*G27 -> 0
A28: 26 | B28: 5. Student Support and Progression | C28: 5.2 Student Progression | D28: QnM | E28: 3.2.4 | F28: Average percentage of departments having Research projects funded by government and non-government agencies during the last five years 3.2.4.1: Number of departments having Research projects funded by government and non-government agencies during the last five years | G28: 3 | J28: =VLOOKUP(E28,'Autonomous 107m'!$E$3:$J$109,6,0) -> 43.57 | K28: =IF(J28>80,4,IF(AND(J28<=80,J28>60),3,IF(AND(J28<=60,J28>40),2,IF(AND(J28<=40,J28>20),1,IF(J28<=20,0))))) -> 2 | L28: =K28*G28 -> 6
A29: 27 | B29: 5. Student Support and Progression | C29: 5.3 Student Participation and Activities | D29: QnM | E29: 3.3.2 | F29: Number of workshops/seminars conducted on Research Methodology, Intellectual Property Rights (IPR), entrepreneurship and skills development during the last five years 3.3.2.1: Total number of workshops/seminars conducted on Research Methodology, Intellectual Property Rights (IPR) and entrepreneurship and skills development year wise during last five years | G29: 5 | H29: 5 | J29: =VLOOKUP(E29,'Autonomous 107m'!$E$3:$J$109,6,0) -> 43 | K29: =IF(J29>80,4,IF(AND(J29<=80,J29>60),3,IF(AND(J29<=60,J29>40),2,IF(AND(J29<=40,J29>20),1,IF(J29<=20,0))))) -> 2 | L29: =K29*G29 -> 10 | M29: 15 | N29: =M29/H29 -> 3
A30: 28 | B30: 5. Student Support and Progression | C30: 5.3 Student Participation and Activities | D30: QnM | E30: 3.4.1 | F30: The Institution ensures implementation of its stated Code of Ethics for research through the following: 1. Inclusion of research ethics in the research methodology course work 2. Presence of Ethics committee 3. Plagiarism check through software 4. Research Advisory Committee | G30: 5 | H30: 30 | J30: =VLOOKUP(E30,'Autonomous 107m'!$E$3:$J$109,6,0) -> C | K30: =IF(EXACT(J30,"A"),4,IF(EXACT(J30,"B"),3,IF(EXACT(J30,"C"),2,IF(EXACT(J30,"D"),1,0)))) -> 2 | L30: =K30*G30 -> 10 | M30: 45 | N30: =M30/H30 -> 1.5
A31: 29 | B31: 6. Governance, Leadership and Management | C31: 6.2 Strategy Development and Deployment | D31: QnM | E31: 3.4.2 | F31: Number of Ph.D’s registered per teacher (as per the data given w.r.t recognized Ph.D guides/ supervisors provided at 3.2.3 metric) during the last five years 3.4.2.1: How many Ph.Ds are registered within last 5 years 3.4.2.2 : Number of teachers recognized as guides during the last five years | G31: 5 | J31: =VLOOKUP(E31,'Autonomous 107m'!$E$3:$J$109,6,0) -> 0 | K31: =IF(J31>80,4,IF(AND(J31<=80,J31>60),3,IF(AND(J31<=60,J31>40),2,IF(AND(J31<=40,J31>20),1,IF(J31<=20,0))))) -> 0 | L31: =K31*G31 -> 0
A32: 30 | B32: 6. Governance, Leadership and Management | C32: 6.3 Faculty Empowerment Strategies | D32: QnM | E32: 3.4.3 | F32: Number of research papers per teacher in the Journals notified on UGC website during the last five years 3.4.3.1: Number of research papers in the Journals notified on UGC website during the last five | G32: 5 | J32: =VLOOKUP(E32,'Autonomous 107m'!$E$3:$J$109,6,0) -> 2.11 | K32: =IF(J32>80,4,IF(AND(J32<=80,J32>60),3,IF(AND(J32<=60,J32>40),2,IF(AND(J32<=40,J32>20),1,IF(J32<=20,0))))) -> 0 | L32: =K32*G32 -> 0
A33: 31 | B33: 6. Governance, Leadership and Management | C33: 6.3 Faculty Empowerment Strategies | D33: QnM | E33: 3.4.4 | F33: Number of books and chapters in edited volumes / books published per teacher during the last five years 3.4.4.1: Total number of books and chapters in edited volumes / books published, and papers in national/international conference-proceedings year wise during last five years | G33: 5 | J33: =VLOOKUP(E33,'Autonomous 107m'!$E$3:$J$109,6,0) -> 0.22 | K33: =IF(J33>80,4,IF(AND(J33<=80,J33>60),3,IF(AND(J33<=60,J33>40),2,IF(AND(J33<=40,J33>20),1,IF(J33<=20,0))))) -> 0 | L33: =K33*G33 -> 0
A34: 32 | B34: 6. Governance, Leadership and Management | C34: 6.5 Internal Quality Assurance System (IQAS) | D34: QnM | E34: 3.4.5 | F34: Bibliometrics of the publications during the last five years based on average Citation index in Scopus/ Web of Science/ PubMed 3.4.5.1: Total number of Citations in Scopus in 5 years Total number of Citations in Web of Science in 5 years 3.4.5.2 : Total number of Publications in Scopus in 5 years Total number of Publications in Web of Science in 5 years | G34: 5 | J34: =VLOOKUP(E34,'Autonomous 107m'!$E$3:$J$109,6,0) -> 1.81 | K34: =IF(J34>80,4,IF(AND(J34<=80,J34>60),3,IF(AND(J34<=60,J34>40),2,IF(AND(J34<=40,J34>20),1,IF(J34<=20,0))))) -> 0 | L34: =K34*G34 -> 0
A35: 33 | B35: 7. Institutional Values and Best Practices | C35: 7.1 Institutional Values and Social Responsibilities | D35: QnM | E35: 3.4.6 | F35: ibliometrics of the publications during the last five years based on Scopus/ Web of Science – h-index of the Institution 3.4.6.1: h-index of Scopus during the last five years h-index of Web of Science during the last five years | G35: 5 | J35: =VLOOKUP(E35,'Autonomous 107m'!$E$3:$J$109,6,0) -> 8 | K35: =IF(J35>80,4,IF(AND(J35<=80,J35>60),3,IF(AND(J35<=60,J35>40),2,IF(AND(J35<=40,J35>20),1,IF(J35<=20,0))))) -> 0 | L35: =K35*G35 -> 0
A36: 34 | B36: 7. Institutional Values and Best Practices | C36: 7.1 Institutional Values and Social Responsibilities | D36: QnM | E36: 3.5.1 | F36: Revenue generated from consultancy and corporate training during the last five years (INR in Lakhs) 3.5.1.1: Total amount generated from consultancy and corporate training year wise during last five years (INR in lakhs) | G36: 5 | H36: 10 | J36: =VLOOKUP(E36,'Autonomous 107m'!$E$3:$J$109,6,0) -> 0 | K36: =IF(J36>80,4,IF(AND(J36<=80,J36>60),3,IF(AND(J36<=60,J36>40),2,IF(AND(J36<=40,J36>20),1,IF(J36<=20,0))))) -> 0 | L36: =K36*G36 -> 0 | M36: 0 | N36: =M36/H36 -> 0
A37: 35 | D37: QnM | E37: 3.5.2 | F37: Total amount spent on developing facilities, training teachers and staff for undertaking consultancy during the last five years 3.5.2.1: Total amount spent on developing facilities, training teachers and staff for undertaking consultancy during the last five years | G37: 5 | J37: =VLOOKUP(E37,'Autonomous 107m'!$E$3:$J$109,6,0) -> 0 | K37: =IF(J37>80,4,IF(AND(J37<=80,J37>60),3,IF(AND(J37<=60,J37>40),2,IF(AND(J37<=40,J37>20),1,IF(J37<=20,0))))) -> 0
A38: 36 | D38: QnM | E38: 3.6.2 | F38: Number of awards and recognition received by the Institution, its teachers and students for extension activities from Government / Government recognised bodies during last five years 3.6.2.1: Total number of awards and recognition received for extension activities from Government /recognised bodies year wise during last five years | G38: 15 | H38: 40 | J38: =VLOOKUP(E38,'Autonomous 107m'!$E$3:$J$109,6,0) -> 0 | K38: =IF(J38>80,4,IF(AND(J38<=80,J38>60),3,IF(AND(J38<=60,J38>40),2,IF(AND(J38<=40,J38>20),1,IF(J38<=20,0))))) -> 0 | M38: 100 | N38: =M38/H38 -> 2.5
A39: 37 | D39: QnM | E39: 3.6.3 | F39: Number of extension and outreach programs conducted by the institution through NSS/NCC/Red cross/YRC etc., during the last five years ( including Government initiated programs such as Swachh Bharat, Aids Awareness, Gender Issue, etc. and those organised in collaboration with industry, community and NGOs) 3.6.3.1: Number of extension and outreach programs conducted in collaboration with industry, community and Non-Government Organisations through NSS/NCC/Red cross/YRC etc., year wise during last five years | G39: 10 | J39: =VLOOKUP(E39,'Autonomous 107m'!$E$3:$J$109,6,0) -> 85 | K39: =IF(J39>80,4,IF(AND(J39<=80,J39>60),3,IF(AND(J39<=60,J39>40),2,IF(AND(J39<=40,J39>20),1,IF(J39<=20,0))))) -> 4
A40: 38 | D40: QnM | E40: 3.6.4 | F40: Average percentage of students participating in extension activities listed at 3.6.3 above during the last five years 3.6.4.1: Total number of students participating in extension activities with Government Organisations, Non-Government Organisations and Programmes such as Swachh Bharat, Aids Awareness, Gender Issue, etc. year wise during last five years | G40: 15 | J40: =VLOOKUP(E40,'Autonomous 107m'!$E$3:$J$109,6,0) -> 83.05 | K40: =IF(J40>80,4,IF(AND(J40<=80,J40>60),3,IF(AND(J40<=60,J40>40),2,IF(AND(J40<=40,J40>20),1,IF(J40<=20,0))))) -> 4
A41: 39 | D41: QnM | E41: 3.7.1 | F41: Number of Collaborative activities per year for research/ faculty exchange/ student exchange/ internship/ on –the-job training/ project work 3.7.1.1: Total number of Collaborative activities per year for research/ faculty exchange/ student exchange/ internship/ on –the-job training/ project work | G41: 10 | H41: 20 | J41: =VLOOKUP(E41,'Autonomous 107m'!$E$3:$J$109,6,0) -> 0 | K41: =IF(J41>80,4,IF(AND(J41<=80,J41>60),3,IF(AND(J41<=60,J41>40),2,IF(AND(J41<=40,J41>20),1,IF(J41<=20,0))))) -> 0 | M41: 30 | N41: =M41/H41 -> 1.5
A42: 40 | D42: QnM | E42: 3.7.2 | F42: Number of functional MoUs with institutions of national, international importance, other universities, industries, corporate houses etc. during the last five years (only functional MoUs with ongoing activities to be considered) 3.7.2.1: Number of functional MoUs with institutions of national, international importance, other Institutions, industries, corporate houses etc. year wise during last five years Data Template | G42: 10 | J42: =VLOOKUP(E42,'Autonomous 107m'!$E$3:$J$109,6,0) -> 55 | K42: =IF(J42>80,4,IF(AND(J42<=80,J42>60),3,IF(AND(J42<=60,J42>40),2,IF(AND(J42<=40,J42>20),1,IF(J42<=20,0))))) -> 2
A43: 41 | D43: QnM | E43: 4.1.3 | F43: Percentage of classrooms and seminar halls with ICT – enabled facilities such as smart class, LMS, etc. (Data for the latest completed academic year) 4.1.3.1: Number of classrooms and seminar halls with ICT facilities | G43: 10 | H43: 20 | I43: 67 | J43: =VLOOKUP(E43,'Autonomous 107m'!$E$3:$J$109,6,0) -> 47.62 | K43: =IF(J43>80,4,IF(AND(J43<=80,J43>60),3,IF(AND(J43<=60,J43>40),2,IF(AND(J43<=40,J43>20),1,IF(J43<=20,0))))) -> 2 | M43: 30 | N43: =M43/H43 -> 1.5 | O43: =SUM(M43:M51) -> 153 | P43: =O43/I43 -> 2.2835821
A44: 42 | D44: QnM | E44: 4.1.4 | F44: Average percentage of expenditure for infrastructure augmentation excluding salary during the last five years (INR in Lakhs) 4.1.4.1: Expenditure for infrastructure augmentation, excluding salary year wise during last five years (INR in lakhs) | G44: 10 | J44: =VLOOKUP(E44,'Autonomous 107m'!$E$3:$J$109,6,0) -> 11.5 | K44: =IF(J44>80,4,IF(AND(J44<=80,J44>60),3,IF(AND(J44<=60,J44>40),2,IF(AND(J44<=40,J44>20),1,IF(J44<=20,0))))) -> 0
A45: 43 | D45: QnM | E45: 4.2.2 | F45: Institution has access to the following: 1. e-journals 2. e-ShodhSindhu 3. Shodhganga Membership 4. e-books 5. Databases 6. Remote access to e-resources | G45: 5 | H45: 15 | J45: =VLOOKUP(E45,'Autonomous 107m'!$E$3:$J$109,6,0) -> A | K45: =IF(EXACT(J45,"A"),4,IF(EXACT(J45,"B"),3,IF(EXACT(J45,"C"),2,IF(EXACT(J45,"D"),1,0)))) -> 4 | M45: 45 | N45: =M45/H45 -> 3
A46: 44 | D46: QnM | E46: 4.2.3 | F46: Average annual expenditure for purchase of books/ e-books and subscription to journals/e-journals during the last five years (INR in Lakhs) 4.2.3.1: Annual expenditure for purchase of books / e-books and subscription to journals/e-journals year wise during last five years (INR in lakhs) | G46: 5 | J46: =VLOOKUP(E46,'Autonomous 107m'!$E$3:$J$109,6,0) -> 11.52 | K46: =IF(J46>80,4,IF(AND(J46<=80,J46>60),3,IF(AND(J46<=60,J46>40),2,IF(AND(J46<=40,J46>20),1,IF(J46<=20,0))))) -> 0
A47: 45 | D47: QnM | E47: 4.2.4 | F47: Percentage per day usage of library by teachers and students ( foot falls and login data for online access) 4.2.6.1: Number of teachers and students using library per day over last one year | G47: 5 | J47: =VLOOKUP(E47,'Autonomous 107m'!$E$3:$J$109,6,0) -> 12.21 | K47: =IF(J47>80,4,IF(AND(J47<=80,J47>60),3,IF(AND(J47<=60,J47>40),2,IF(AND(J47<=40,J47>20),1,IF(J47<=20,0))))) -> 0
A48: 46 | D48: QnM | E48: 4.3.2 | F48: Student - Computer ratio(Data for the latest completed academic year) | G48: 8 | H48: 22 | J48: =VLOOKUP(E48,'Autonomous 107m'!$E$3:$J$109,6,0) -> 0.16736111 | K48: =IF(J48>80,4,IF(AND(J48<=80,J48>60),3,IF(AND(J48<=60,J48>40),2,IF(AND(J48<=40,J48>20),1,IF(J48<=20,0))))) -> 0 | M48: 68 | N48: =M48/H48 -> 3.0909091
A49: 47 | D49: QnM | E49: 4.3.3 | F49: Bandwidth of internet connection in the Institution Options: A. ≥50 MBPS B. 35 MBPS - 50 MBPS C. 20 MBPS - 35 MBPS Opt One D. 5 MBPS - 20 MBPS E. <5 MBPS | G49: 10 | J49: =VLOOKUP(E49,'Autonomous 107m'!$E$3:$J$109,6,0) -> 50 | K49: =IF(J49>80,4,IF(AND(J49<=80,J49>60),3,IF(AND(J49<=60,J49>40),2,IF(AND(J49<=40,J49>20),1,IF(J49<=20,0))))) -> 2
A50: 48 | D50: QnM | E50: 4.3.4 | F50: Institution has Facilities for e-content development Facilities available for e-content development : 1. Media centre 2. Audio visual centre, 3. Lecture Capturing System(LCS) 4. Mixing equipment's and software's for editing | G50: 4 | J50: =VLOOKUP(E50,'Autonomous 107m'!$E$3:$J$109,6,0) -> D | K50: =IF(EXACT(J50,"A"),4,IF(EXACT(J50,"B"),3,IF(EXACT(J50,"C"),2,IF(EXACT(J50,"D"),1,0)))) -> 1
A51: 49 | D51: QnM | E51: 4.4.1 | F51: Average percentage expenditure incurred on maintenance of physical facilities and academic support facilities excluding salary component, during the last five years 4.4.1.1: Expenditure incurred on maintenance of physical facilities and academic support facilities excluding salary component year wise during last five years (INR in lakhs) | G51: 10 | H51: 10 | J51: =VLOOKUP(E51,'Autonomous 107m'!$E$3:$J$109,6,0) -> 9.51 | K51: =IF(J51>80,4,IF(AND(J51<=80,J51>60),3,IF(AND(J51<=60,J51>40),2,IF(AND(J51<=40,J51>20),1,IF(J51<=20,0))))) -> 0 | M51: 10 | N51: =M51/H51 -> 1
A52: 50 | D52: QnM | E52: 5.1.1 | F52: Average percentage of students benefited by scholarships and freeships provided by the Government during the last five years 5.1.1.1: Number of students benefited by scholarships and freeships provided by the Government year wise during last five years | G52: 6 | H52: 30 | I52: 85 | J52: =VLOOKUP(E52,'Autonomous 107m'!$E$3:$J$109,6,0) -> 48 | K52: =IF(J52>80,4,IF(AND(J52<=80,J52>60),3,IF(AND(J52<=60,J52>40),2,IF(AND(J52<=40,J52>20),1,IF(J52<=20,0))))) -> 2 | M52: 63 | N52: =M52/H52 -> 2.1 | O52: =SUM(M52:M62) -> 208 | P52: =O52/I52 -> 2.4470588
A53: 51 | D53: QnM | E53: 5.1.2 | F53: Average percentage of students benefited by scholarships, freeships, etc. provided by the institution and non-government agencies during the last five years 5.1.2.1: Total number of students benefited by scholarships, freeships, etc provided by the institution and non-government agencies year wise during last five years | G53: 5 | J53: =VLOOKUP(E53,'Autonomous 107m'!$E$3:$J$109,6,0) -> 0 | K53: =IF(J53>80,4,IF(AND(J53<=80,J53>60),3,IF(AND(J53<=60,J53>40),2,IF(AND(J53<=40,J53>20),1,IF(J53<=20,0))))) -> 0
A54: 52 | D54: QnM | E54: 5.1.3 | F54: Following Capacity development and skills enhancement activities are organised for improving students capability 1. Soft skills 2. Language and communication skills 3. Life skills (Yoga, physical fitness, health and hygiene) 4. Awareness of trends in technology | G54: 8 | J54: =VLOOKUP(E54,'Autonomous 107m'!$E$3:$J$109,6,0) -> B | K54: =IF(EXACT(J54,"A"),4,IF(EXACT(J54,"B"),3,IF(EXACT(J54,"C"),2,IF(EXACT(J54,"D"),1,0)))) -> 3
A55: 53 | D55: QnM | E55: 5.1.4 | F55: Average percentage of students benefited by guidance for competitive examinations and career counselling offered by the institution during the last five years 5.1.4.1: Number of students benefited by guidance for competitive examinations and career counselling offered by the institution year wise during last five years | G55: 6 | J55: =VLOOKUP(E55,'Autonomous 107m'!$E$3:$J$109,6,0) -> 3.49 | K55: =IF(J55>80,4,IF(AND(J55<=80,J55>60),3,IF(AND(J55<=60,J55>40),2,IF(AND(J55<=40,J55>20),1,IF(J55<=20,0))))) -> 0
A56: 54 | D56: QnM | E56: 5.1.5 | F56: The institution adopts the following for redressal of student grievances including sexual harassment and ragging cases 1. Implementation of guidelines of statutory/regulatory bodies 2. Organisation wide awareness and undertakings on policies with zero tolerance 3. Mechanisms for submission of online/offline students’ grievances 4. Timely redressal of the grievances through appropriate committees | G56: 5 | J56: =VLOOKUP(E56,'Autonomous 107m'!$E$3:$J$109,6,0) -> B | K56: =IF(EXACT(J56,"A"),4,IF(EXACT(J56,"B"),3,IF(EXACT(J56,"C"),2,IF(EXACT(J56,"D"),1,0)))) -> 3
A57: 55 | D57: QnM | E57: 5.2.1 | F57: Average percentage of placement of outgoing students during the last five years 5.2.1.1: Number of outgoing students placed year wise during last five years | G57: 10 | H57: 30 | J57: =VLOOKUP(E57,'Autonomous 107m'!$E$3:$J$109,6,0) -> 44.94 | K57: =IF(J57>80,4,IF(AND(J57<=80,J57>60),3,IF(AND(J57<=60,J57>40),2,IF(AND(J57<=40,J57>20),1,IF(J57<=20,0))))) -> 2 | M57: 80 | N57: =M57/H57 -> 2.6666667
A58: 56 | D58: QnM | E58: 5.2.2 | F58: Percentage of student progression to higher education (previous graduating batch) 5.2.2.1: Number of outgoing students progressing to higher education Data Requirements: (As per Data Template) Number of students proceeding from UG to PG:. PG to MPhil: PG to PhD: MPhil to PhD: PhD to Post doctoral: | G58: 10 | J58: =VLOOKUP(E58,'Autonomous 107m'!$E$3:$J$109,6,0) -> 7.46 | K58: =IF(J58>80,4,IF(AND(J58<=80,J58>60),3,IF(AND(J58<=60,J58>40),2,IF(AND(J58<=40,J58>20),1,IF(J58<=20,0))))) -> 0
A59: 57 | D59: QnM | E59: 5.2.3 | F59: Average percentage of students qualifying in state/ national/ international level examinations during the last five years (eg: IIT/JAM/NET/SLET/GATE/GMAT/CAT/ GRE/TOEFL/Civil Services/State government examinations etc.) 5.2.3.1: Number of students qualifying in state/ national/ international level examinations (eg: IIT/JAM/NET/SLET/GATE/GMAT/CAT/ GRE/TOEFL/Civil Services/State government examinations) year wise during last five years 5.2.3.2: Number of students appearing in state/ national/ international level examinations (eg: IIT/JAM/ NET/SLET/GATE/GMAT/CAT, GRE/TOEFL/Civil Services/State government examinations) year wise during last five years | G59: 10 | J59: =VLOOKUP(E59,'Autonomous 107m'!$E$3:$J$109,6,0) -> 100 | K59: =IF(J59>80,4,IF(AND(J59<=80,J59>60),3,IF(AND(J59<=60,J59>40),2,IF(AND(J59<=40,J59>20),1,IF(J59<=20,0))))) -> 4
A60: 58 | D60: QnM | E60: 5.3.1 | F60: Number of awards/medals for outstanding performance in sports/cultural activities at inter-university / state /national / international events (award for a team event should be counted as one) during the last five years 5.3.1.1: Number of awards/medals for outstanding performance in sports/cultural activities at inter-university / state / national / international level (award for a team event should be counted as one) year wise during last five years | G60: 10 | H60: 20 | J60: =VLOOKUP(E60,'Autonomous 107m'!$E$3:$J$109,6,0) -> 27 | K60: =IF(J60>80,4,IF(AND(J60<=80,J60>60),3,IF(AND(J60<=60,J60>40),2,IF(AND(J60<=40,J60>20),1,IF(J60<=20,0))))) -> 1 | M60: 60 | N60: =M60/H60 -> 3
A61: 59 | D61: QnM | E61: 5.3.3 | F61: Average number of sports and cultural events / competitions organised by the institution per year 5.3.3.1: Number of sports and cultural events / competitions organised by the institution year wise during last five years | G61: 10 | J61: =VLOOKUP(E61,'Autonomous 107m'!$E$3:$J$109,6,0) -> 22.8 | K61: =IF(J61>80,4,IF(AND(J61<=80,J61>60),3,IF(AND(J61<=60,J61>40),2,IF(AND(J61<=40,J61>20),1,IF(J61<=20,0))))) -> 1
A62: 60 | D62: QnM | E62: 5.4.2 | F62: Alumni financial contribution during the last five years (in INR) Options: A. ≥ 15 Lakhs B. 10Lakhs - 15 Lakhs C. 5 Lakhs - 10 Lakhs D. 2 Lakhs - 5 | G62: 5 | H62: 5 | J62: =VLOOKUP(E62,'Autonomous 107m'!$E$3:$J$109,6,0) -> D | K62: =IF(EXACT(J62,"A"),4,IF(EXACT(J62,"B"),3,IF(EXACT(J62,"C"),2,IF(EXACT(J62,"D"),1,0)))) -> 1 | M62: 5 | N62: =M62/H62 -> 1
A63: 61 | D63: QnM | E63: 6.2.3 | F63: Implementation of e-governance in areas of operation: 1. Administration 2. Finance and Accounts 3. Student Admission and Support 4. Examination | G63: 4 | H63: 4 | I63: 50 | J63: =VLOOKUP(E63,'Autonomous 107m'!$E$3:$J$109,6,0) -> B | K63: =IF(EXACT(J63,"A"),4,IF(EXACT(J63,"B"),3,IF(EXACT(J63,"C"),2,IF(EXACT(J63,"D"),1,0)))) -> 3 | M63: 12 | N63: =M63/H63 -> 3 | O63: =SUM(M63:M68) -> 148 | P63: =O63/I63 -> 2.96
A64: 62 | D64: QnM | E64: 6.3.2 | F64: Average percentage of teachers provided with financial support to attend conferences / workshops and towards membership fee of professional bodies during the last five years 6.3.2.1: Number of teachers provided with financial support to attend conferences / workshops and towards membership fee of professional bodies year wise during last five years | G64: 8 | H64: 26 | J64: =VLOOKUP(E64,'Autonomous 107m'!$E$3:$J$109,6,0) -> 42.41 | K64: =IF(J64>80,4,IF(AND(J64<=80,J64>60),3,IF(AND(J64<=60,J64>40),2,IF(AND(J64<=40,J64>20),1,IF(J64<=20,0))))) -> 2 | M64: 76 | N64: =M64/H64 -> 2.9230769
A65: 63 | D65: QnM | E65: 6.3.3 | F65: Average number of professional development / administrative training programs organized by the Institution for teaching and non teaching staff during the last five years 6.3.3.1: Total number of professional development / administrative training Programmes organized by the Institution for teaching and non teaching staff year wise during last five years | G65: 8 | J65: =VLOOKUP(E65,'Autonomous 107m'!$E$3:$J$109,6,0) -> 51.2 | K65: =IF(J65>80,4,IF(AND(J65<=80,J65>60),3,IF(AND(J65<=60,J65>40),2,IF(AND(J65<=40,J65>20),1,IF(J65<=20,0))))) -> 2
A66: 64 | D66: QnM | E66: 6.3.4 | F66: Average percentage of teachers undergoing online/ face-to-face Faculty Development Programmes during the last five years (Professional Development Programmes, Orientation / Induction Programmes, Refresher Course, Short Term Course etc.,) 6.3.4.1: Total number of teachers attending professional development Programmes, viz., Orientation Programme, Refresher Course, Short Term Course, Faculty Development Programmes year wise during last five years. | G66: 10 | J66: =VLOOKUP(E66,'Autonomous 107m'!$E$3:$J$109,6,0) -> 21.4 | K66: =IF(J66>80,4,IF(AND(J66<=80,J66>60),3,IF(AND(J66<=60,J66>40),2,IF(AND(J66<=40,J66>20),1,IF(J66<=20,0))))) -> 1
A67: 65 | D67: QnM | E67: 6.4.2 | F67: Funds / Grants received from non-government bodies, individuals, philanthropists during the last five years (not covered in Criterion III and V) (INR in Lakhs) 6.4.2.1: Total Grants received from non-government bodies, individuals, philanthropists year wise during last five years (INR in Lakhs) | G67: 10 | H67: 10 | J67: =VLOOKUP(E67,'Autonomous 107m'!$E$3:$J$109,6,0) -> 5.99 | K67: =IF(J67>80,4,IF(AND(J67<=80,J67>60),3,IF(AND(J67<=60,J67>40),2,IF(AND(J67<=40,J67>20),1,IF(J67<=20,0))))) -> 0 | M67: 20 | N67: =M67/H67 -> 2
A68: 66 | D68: QnM | E68: 6.5.3 | F68: Quality assurance initiatives of the institution include: 1. Regular meeting of Internal Quality Assurance Cell (IQAC); Feedback collected, analysed and used for improvements 2. Collaborative quality initiatives with other institution(s) 3. Participation in NIRF 4. Any other quality audit recognized by state, national or international agencies (ISO Certification) | G68: 10 | H68: 10 | J68: =VLOOKUP(E68,'Autonomous 107m'!$E$3:$J$109,6,0) -> A | K68: =IF(EXACT(J68,"A"),4,IF(EXACT(J68,"B"),3,IF(EXACT(J68,"C"),2,IF(EXACT(J68,"D"),1,0)))) -> 4 | M68: 40 | N68: =M68/H68 -> 4
A69: 67 | D69: QnM | E69: 7.1.2 | F69: The Institution has facilities for alternate sources of energy and energy conservation measures 1. Solar energy 2. Biogas plant 3. Wheeling to the Grid 4. Sensor-based energy conservation 5. Use of LED bulbs/ power efficient equipment | G69: 5 | H69: 27 | I69: 27 | J69: =VLOOKUP(E69,'Autonomous 107m'!$E$3:$J$109,6,0) -> A | K69: =IF(EXACT(J69,"A"),4,IF(EXACT(J69,"B"),3,IF(EXACT(J69,"C"),2,IF(EXACT(J69,"D"),1,0)))) -> 4 | M69: 59 | N69: =M69/H69 -> 2.1851852 | O69: =SUM(M69) -> 59 | P69: =O69/I69 -> 2.1851852
A70: 68 | D70: QnM | E70: 7.1.4 | F70: Water conservation facilities available in the Institution: 1. Rain water harvesting 2. Borewell /Open well recharge 3. Construction of tanks and bunds 4. Waste water recycling 5. Maintenance of water bodies and distribution system in the campus | G70: 4 | J70: =VLOOKUP(E70,'Autonomous 107m'!$E$3:$J$109,6,0) -> C | K70: =IF(EXACT(J70,"A"),4,IF(EXACT(J70,"B"),3,IF(EXACT(J70,"C"),2,IF(EXACT(J70,"D"),1,0)))) -> 2
A71: 69 | D71: QnM | E71: 7.1.5 | F71: Green campus initiatives include (4) 7.1.5.1. The institutional initiatives for greening the campus are as follows: 1. Restricted entry of automobiles 2. Use of Bicycles/ Battery powered vehicles 3. Pedestrian Friendly pathways 4. Ban on use of Plastic 5. landscaping with trees and plants | G71: 4 | J71: =VLOOKUP(E71,'Autonomous 107m'!$E$3:$J$109,6,0) -> B | K71: =IF(EXACT(J71,"A"),4,IF(EXACT(J71,"B"),3,IF(EXACT(J71,"C"),2,IF(EXACT(J71,"D"),1,0)))) -> 3
A72: 70 | D72: QnM | E72: 7.1.6 | F72: Quality audits on environment and energy are regularly undertaken by the institution (5) 7.1.7.1. The institutional environment and energy initiatives are confirmed through the following 1.Green audit 2. Energy audit 3.Environment audit 4.Clean and green campus recognitions/awards 5. Beyond the campus environmental promotional activities | G72: 5 | J72: =VLOOKUP(E72,'Autonomous 107m'!$E$3:$J$109,6,0) -> D | K72: =IF(J72>80,4,IF(AND(J72<=80,J72>60),3,IF(AND(J72<=60,J72>40),2,IF(AND(J72<=40,J72>20),1,IF(J72<=20,0))))) -> 4
A73: 71 | D73: QnM | E73: 7.1.7 | F73: The Institution has disabled-friendly, barrier free environment 1. Built environment with ramps/lifts for easy access to classrooms. 2. Disabled-friendly washrooms 3. Signage including tactile path, lights, display boards and signposts 4. Assistive technology and facilities for persons with disabilities ( Divyangjan) accessible website, screen-reading software, mechanized equipment 5. Provision for enquiry and information : Human assistance, reader, scribe, soft copies of reading material, screen reading | G73: 4 | J73: =VLOOKUP(E73,'Autonomous 107m'!$E$3:$J$109,6,0) -> D | K73: =IF(EXACT(J73,"A"),4,IF(EXACT(J73,"B"),3,IF(EXACT(J73,"C"),2,IF(EXACT(J73,"D"),1,0)))) -> 1
A74: 72 | D74: QnM | E74: 7.1.10 | F74: The Institution has a prescribed code of conduct for students, teachers, administrators and other staff and conducts periodic programmes in this regard. 1. The Code of Conduct is displayed on the website 2. There is a committee to monitor adherence to the Code of Conduct 3. Institution organizes professional ethics programmes for students, teachers, administrators and other staff 4. Annual awareness programmes on Code of Conduct are organized | G74: 5 | J74: =VLOOKUP(E74,'Autonomous 107m'!$E$3:$J$109,6,0) -> C | K74: =IF(J74>80,4,IF(AND(J74<=80,J74>60),3,IF(AND(J74<=60,J74>40),2,IF(AND(J74<=40,J74>20),1,IF(J74<=20,0))))) -> 4
J76: Graphical Representation of Grade points
F78: Row Labels | G78: Average of Metric | J78: Criteria Wise QnM Grade Points(0-4)
F79: 1. Curricular Aspects | G79: 3.25
F80: 2. Teaching-Learning and Evaluation | G80: 3
F81: 3. Research, Innovations and Extension | G81: 0.83333333
F82: 4. Infrastructure and Learning Resources | G82: 1.3333333
F83: 5. Student Support and Progression | G83: 1.25
F84: 6. Governance, Leadership and Management | G84: 0
F85: 7. Institutional Values and Best Practices | G85: 0
F86: (blank) | G86: 1.7368421
F87: Grand Total | G87: 1.6527778
F93: Row Labels | G93: Average of Metric
F94: 1.2 Academic Flexibility | G94: 4
F95: 1.3 Curriculum Enrichment | G95: 1
F96: 1.4 Feedback System | G96: 4
F97: 2.1 Student Enrolment and Profile | G97: 2.5
F98: 2.2 Student Teacher Ratio | G98: 3
F99: 2.4 Teacher Profile and Quality | G99: 2.5
F100: 2.6 Student Performance and Learning Outcomes | G100: 4 | J100: Key Indicator Wise QnM Grade Points(0-4)
F101: 2.7 Student Satisfaction Survey | G101: 4
F102: 3.1 Resource Mobilization for Research | G102: 0
F103: 3.2 Innovation Ecosystem | G103: 0
F104: 3.3 Research Publications and Awards | G104: 2
F105: 3.4 Extension Activities | G105: 0
F106: 3.5 Collaboration | G106: 1
F107: 4.1 Physical Facilities | G107: 0
...

Sheet 72 Qnm-GS
A1: Quantitative Grade Sheet
A2: Name of the Institution: | C2: ='Autonomous 107m'!$J$2 -> Institute Name
A3: Type of the Institution: | C3: ='Autonomous 107m'!K$1 -> Autonomous
A4: Dates of Visit:
A5: No | B5: Criteria | C5: Weightage (Wi | D5: Criterion-wise weighted Grade Point (CrWGPi) | E5: Criterion- wise Grade Point Averages (CrWGPi/Wi) | G5: Range of Institutional Cumulative Grade Point Average (CGPA) | H5: Letter Grade | I5: Status
A6: 1 | B6: Curricular Aspects | C6: 120 | D6: =SUM('Qn (72m)'!O3:O11) -> 410 | E6: =D6/C6 -> 3.4166667 | G6: 3.51-4.00 | H6: A++ | I6: Accredited
A7: 2 | B7: Teaching-learning and Evaluation | C7: 200 | D7: =SUM('Qn (72m)'!O12:O22) -> 619 | E7: =D7/C7 -> 3.095 | G7: 3.26-3.500 | H7: A+ | I7: Accredited
A8: 3 | B8: Research, Innovations and Extension | C8: 129 | D8: =SUM('Qn (72m)'!O23:O42) -> 207 | E8: =D8/C8 -> 1.6046512 | G8: 3.01-3.25 | H8: A | I8: Accredited
A9: 4 | B9: Infrastructure and Learning Resources | C9: 67 | D9: =SUM('Qn (72m)'!O43:O51) -> 153 | E9: =D9/C9 -> 2.2835821 | G9: 2.76-3.00 | H9: B++ | I9: Accredited
A10: 5 | B10: Student Support and Progression | C10: 85 | D10: =SUM('Qn (72m)'!O52:O62) -> 208 | E10: =D10/C10 -> 2.4470588 | G10: 2.51-2.75 | H10: B+ | I10: Accredited
A11: 6 | B11: Governance, Leadership and Management | C11: 50 | D11: =SUM('Qn (72m)'!O63:O68) -> 148 | E11: =D11/C11 -> 2.96 | G11: 2.01-2.50 | H11: B | I11: Accredited
A12: 7 | B12: Institutional Values and Best Practices | C12: 27 | D12: =SUM('Qn (72m)'!O69:O74) -> 59 | E12: =D12/C12 -> 2.1851852 | G12: 1.51-2.00 | H12: C | I12: Accredited
A13: Total | C13: =SUM(C6:C12) -> 678 | D13: =SUM(D6:D12) -> 1804 | E13: =D13/C13 -> 2.660767 | G13: ≤ 1.50 | H13: D | I13: Not Accredited
A15: =D13/C13 -> 2.660767
A17: =IF(AND($A$15<=4,$A$15>=3.51),"A++",IF(AND($A$15<=3.5,$A$15>=3.26),"A+",IF(AND($A$15<=3.25,$A$15>3.01),"A",IF(AND($A$15<=3,$A$15>=2.76),"B++",IF(AND($A$15<=2.75,$A$15>=2.51),"B+",IF(AND($A$15<=2.5,$A$15>=2.01),"B",IF(AND($A$15<=2,$A$15>=1.51),"C","D"))))))) -> B+
A19: Criterion wise - Quantitative Grade Sheet
A20: Name of the Institution: | C20: ='Autonomous 107m'!$J$2 -> Institute Name
A21: Type of the Institution: | C21: ='Autonomous 107m'!$K$1 -> Autonomous
A22: Dates of Visit:
A23: No | B23: Criteria and Key Indicators | C23: Key Indicator Weightage (Wi) | D23: Key Indicator Wise Weighted Grade Points (KIWGP)i
A24: Criterion 1: Curricular Aspects
A25: 1.1 | B25: Curriculum Planning and Implementation | C25: 30 | D25: =SUM('Qn (72m)'!M3:M4) -> 120
A26: 1.2 | B26: Academic Flexibility | C26: 40 | D26: =SUM('Qn (72m)'!M5:M6) -> 160
A27: 1.3 | B27: Curriculum Enrichment | C27: 30 | D27: =SUM('Qn (72m)'!M7:M9) -> 80
A28: 1.4 | B28: Feedback System | C28: 20 | D28: =SUM('Qn (72m)'!M10:M11) -> 50
A29: Total | C29: =SUM(C25:C28) -> 120 | D29: =SUM(D25:D28) -> 410
A30: =D29/C29 -> 3.4166667
A31: Criterion 2: Teaching-learning and Evaluation
A32: 2.1 | B32: Student Enrollment and Profile | C32: 20 | D32: =SUM('Qn (72m)'!M12:M13) -> 80
A33: 2.2 | B33: Catering to Student Diversity | C33: 15 | D33: =SUM('Qn (72m)'!M14) -> 45
A34: 2.3 | B34: Teaching- Learning Process | C34: 10 | D34: =SUM('Qn (72m)'!M15) -> 30
A35: 2.4 | B35: Teacher Profile and Quality | C35: 50 | D35: =SUM('Qn (72m)'!M16:M18) -> 110
A36: 2.5 | B36: Evaluation Process and Reforms | C36: 35 | D36: =SUM('Qn (72m)'!M19:M20) -> 100
A37: 2.6 | B37: Student Performance and Learning Outcomes | C37: 20 | D37: =SUM('Qn (72m)'!M19:M20) -> 100
A38: 2.7 | B38: Student Satisfaction Survey | C38: 50 | D38: =SUM('Qn (72m)'!M22) -> 174
A39: Total | C39: =SUM(C32:C38) -> 200 | D39: =SUM(D32:D38) -> 639
A40: =D39/C39 -> 3.195
A41: Criterion 3: Research, Innovations and Extension
A42: 3.1 | B42: Promotion of Research and Facilities | C42: 14 | D42: =SUM('Qn (72m)'!M23:M24) -> 0
A43: 3.2 | B43: Resource Mobilization for Research | C43: 10 | D43: =SUM('Qn (72m)'!M25:M28) -> 17
A44: 3.3 | B44: Innovation Ecosystem | C44: 5 | D44: =SUM('Qn (72m)'!M29) -> 15
A45: 3.4 | B45: Research Publications and Awards | C45: 30 | D45: =SUM('Qn (72m)'!M30:M35) -> 45
A46: 3.5 | B46: Consultancy | C46: 10 | D46: =SUM('Qn (72m)'!M36:M37) -> 0
A47: 3.6 | B47: Extension Activities | C47: 40 | D47: =SUM('Qn (72m)'!M38:M40) -> 100
A48: 3.7 | B48: Collaboration | C48: 20 | D48: =SUM('Qn (72m)'!M41:M42) -> 30
A49: Total | C49: =SUM(C42:C48) -> 129 | D49: =SUM(D42:D48) -> 207
A50: =D49/C49 -> 1.6046512
A51: Criterion 4: Infrastructure and Learning Resources
A52: 4.1 | B52: Physical Facilities | C52: 20 | D52: =SUM('Qn (72m)'!M43:M44) -> 30
A53: 4.2 | B53: Library as a Learning Resource | C53: 15 | D53: =SUM('Qn (72m)'!M45:M47) -> 45
A54: 4.3 | B54: IT Infrastructure | C54: 22 | D54: =SUM('Qn (72m)'!M48:M50) -> 68
A55: 4.4 | B55: Maintenance of Campus Infrastructure | C55: 10 | D55: =SUM('Qn (72m)'!M51) -> 10
A56: Total | C56: =SUM(C52:C55) -> 67 | D56: =SUM(D52:D55) -> 153
A57: =D56/C56 -> 2.2835821
A58: Criterion 5: Student Support and Progression
A59: 5.1 | B59: Student Support | C59: 30 | D59: =SUM('Qn (72m)'!M52:M56) -> 63
A60: 5.2 | B60: Student Progression | C60: 30 | D60: =SUM('Qn (72m)'!M57:M59) -> 80
A61: 5.3 | B61: Student Participation and Activities | C61: 20 | D61: =SUM('Qn (72m)'!M60:M61) -> 60
A62: 5.4 | B62: Alumni Engagement | C62: 5 | D62: =SUM('Qn (72m)'!M62) -> 5
A63: Total | C63: =SUM(C59:C62) -> 85 | D63: =SUM(D59:D62) -> 208
A64: =D63/C63 -> 2.4470588
A65: Criterion 6: Governance, Leadership and Management
A66: 6.2 | B66: Strategy Development and Development | C66: 4 | D66: =SUM('Qn (72m)'!M63) -> 12
A67: 6.3 | B67: Faculty Empowerment Strategies | C67: 26 | D67: =SUM('Qn (72m)'!M64:M66) -> 76
A68: 6.4 | B68: Financial Management and Resource Mobilization | C68: 10 | D68: =SUM('Qn (72m)'!M67) -> 20
A69: 6.5 | B69: Internal Quality Assurance System | C69: 10 | D69: =SUM('Qn (72m)'!M68) -> 40
A70: Total | C70: =SUM(C66:C69) -> 50 | D70: =SUM(D66:D69) -> 148
A71: =D70/C70 -> 2.96
A72: Criterion 7: Institutional Values and Best Practices
A73: 7.1 | B73: Institutional Values and Social Responsibilities | C73: 27 | D73: =SUM('Qn (72m)'!M69:M74) -> 59
A74: Total | C74: =SUM(C73:C73) -> 27 | D74: =SUM(D73:D73) -> 59
A75: =D74/C74 -> 2.1851852
A76: Grand Total | C76: =SUM(C29,C39,C49,C56,C63,C70,C74) -> 678 | D76: =SUM(D29,D39,D49,D56,D63,D70,D74) -> 1824
A77: =D76/C76 -> 2.6902655
A78: =IF(AND($A$77<=4,$A$77>=3.51),"A++",IF(AND($A$77<=3.5,$A$77>=3.26),"A+",IF(AND($A$77<=3.25,$A$77>3.01),"A",IF(AND($A$77<=3,$A$77>=2.76),"B++",IF(AND($A$77<=2.75,$A$77>=2.51),"B+",IF(AND($A$77<=2.5,$A$77>=2.01),"B",IF(AND($A$77<=2,$A$77>=1.51),"C","D"))))))) -> B+

Sheet Ql (35m)
A2: S. No | B2: Criteria © | C2: Key Indicator (KI) | D2: Metric (M) Type | E2: Metric (M) Num | F2: Metric (M) Description | G2: M Wt | H2: KI Wt | I2: © Wt | J2: Response | K2: Metric Grade scale (0-4) | L2: M wise weighted Grade points | M2: KIwise weighted Grade points | N2: KIwise weighted Grade points Average | O2: ©Wise Weighted Average | P2: ©Wise Weighted Grade Point Average
A3: 1 | B3: 1. Curricular Aspects | C3: 1.1 Curriculum Planning and Implementation | D3: QlM | E3: 1.1.1 | F3: Curricula developed and implemented have relevance to the local, national, regional and global developmental needs which is reflected in Programme outcomes (POs), Programme Specific outcomes (PSOs) and Course Outcomes (COs) of the Programmes offered by the Institution Write description in maximum of 500 words | G3: 20 | H3: 20 | I3: 30 | K3: =IF(J3>80,4,IF(AND(J3<=80,J3>60),3,IF(AND(J3<=60,J3>40),2,IF(AND(J3<=40,J3>20),1,IF(J3<=20,0))))) -> 0 | L3: =K3*H3 -> 0 | M3: =L3+L4 -> 0 | N3: =M3/I3 -> 0 | O3: =M3 -> 0 | P3: =O3/I3 -> 0
A4: 2 | B4: 1. Curricular Aspects | C4: 1.3 Curriculum Enrichment | D4: QlM | E4: 1.3.1 | F4: Institution integrates crosscutting issues relevant to Professional Ethics, Gender, Human Values, Environment and Sustainability, Human Values into the Curriculum Write description in maximum of 500 words | G4: 10 | H4: 10 | K4: =IF(J4>80,4,IF(AND(J4<=80,J4>60),3,IF(AND(J4<=60,J4>40),2,IF(AND(J4<=40,J4>20),1,IF(J4<=20,0))))) -> 0 | L4: =K4*H4 -> 0
A5: 3 | B5: 2. Teaching-Learning and Evaluation | C5: 2.2 Catering to Student Diversity | D5: QlM | E5: 2.2.1 | F5: The institution assesses the learning levels of the students and organises special Programmes for advanced learners and slow learners. Write description in of 500 words | G5: 15 | H5: 15 | I5: 100 | K5: =IF(J5>80,4,IF(AND(J5<=80,J5>60),3,IF(AND(J5<=60,J5>40),2,IF(AND(J5<=40,J5>20),1,IF(J5<=20,0))))) -> 0 | L5: =K5*H5 -> 0 | M5: =L5 -> 0 | N5: =M5/I5 -> 0 | O5: =N5+N6+N9+N10 -> 0 | P5: =O5/I5 -> 0
A6: 4 | B6: 2. Teaching-Learning and Evaluation | C6: 2.3 Teaching-Learning Process | D6: QlM | E6: 2.3.1 | F6: Student centric methods, such as experiential learning, participative learning and problem solving methodologies are used for enhancing learning experiences Write description in maximum of 500 words | G6: 15 | H6: 40 | K6: =IF(J6>80,4,IF(AND(J6<=80,J6>60),3,IF(AND(J6<=60,J6>40),2,IF(AND(J6<=40,J6>20),1,IF(J6<=20,0))))) -> 0 | L6: =K6*H6 -> 0 | M6: =L6+L7+L8 -> 0 | N6: =M6/H6 -> 0
A7: 5 | B7: 2. Teaching-Learning and Evaluation | C7: 2.3 Teaching-Learning Process | D7: QlM | E7: 2.3.2 | F7: Teachers use ICT enabled tools including online resources for effective teaching and learning process Write description in maximum of 500 words | G7: 15 | K7: =IF(J7>80,4,IF(AND(J7<=80,J7>60),3,IF(AND(J7<=60,J7>40),2,IF(AND(J7<=40,J7>20),1,IF(J7<=20,0))))) -> 0 | L7: =K7*H7 -> 0
A8: 6 | B8: 2. Teaching-Learning and Evaluation | C8: 2.3 Teaching-Learning Process | D8: QlM | E8: 2.3.4 | F8: Preparation and adherence of Academic Calendar and Teaching plans by the institution Describe the Preparation and adherence to Academic Calendar and Teaching plans by the institution within the minimum of 500 Characters and maximum of 500 words. | G8: 10 | K8: =IF(J8>80,4,IF(AND(J8<=80,J8>60),3,IF(AND(J8<=60,J8>40),2,IF(AND(J8<=40,J8>20),1,IF(J8<=20,0))))) -> 0 | L8: =K8*H8 -> 0
A9: 7 | B9: 2. Teaching-Learning and Evaluation | C9: 2.5 Evaluation Process and Reforms | D9: QlM | E9: 2.5.3 | F9: IT integration and reforms in the examination procedures and processes including Continuous Internal Assessment (CIA) have brought in considerable improvement in Examination Management System (EMS) of the Institution Describe the examination reforms with reference to the following within a minimum of 500 words and maximum 1000 words: | G9: 15 | H9: 15 | K9: =IF(J9>80,4,IF(AND(J9<=80,J9>60),3,IF(AND(J9<=60,J9>40),2,IF(AND(J9<=40,J9>20),1,IF(J9<=20,0))))) -> 0 | L9: =K9*H9 -> 0 | M9: =L9 -> 0 | N9: =M9/H9 -> 0
A10: 8 | B10: 2. Teaching-Learning and Evaluation | C10: 2.6 Student Performance and Learning Outcomes | D10: QlM | E10: 2.6.1 | F10: Programme outcomes and course outcomes for all Programmes offered by the institution are stated and displayed on website and communicated to teachers and students Describe Course Outcomes (COs) for all courses and mechanism of communication within a maximum of 500 words | G10: 20 | H10: 30 | K10: =IF(J10>80,4,IF(AND(J10<=80,J10>60),3,IF(AND(J10<=60,J10>40),2,IF(AND(J10<=40,J10>20),1,IF(J10<=20,0))))) -> 0 | L10: =K10*H10 -> 0 | M10: =L10+L11 -> 0 | N10: =M10/H10 -> 0
A11: 9 | B11: 2. Teaching-Learning and Evaluation | C11: 2.6 Student Performance and Learning Outcomes | D11: QlM | E11: 2.6.2 | F11: Attainment of program outcomes and course outcomes are evaluated by the institution Describe the method of measuring attainment of POs , PSOs and COs in not more than 500 words and the level of attainment of POs , PSOs and COs. | G11: 10 | K11: =IF(J11>80,4,IF(AND(J11<=80,J11>60),3,IF(AND(J11<=60,J11>40),2,IF(AND(J11<=40,J11>20),1,IF(J11<=20,0))))) -> 0 | L11: =K11*H11 -> 0
A12: 10 | B12: 3. Research, Innovations and Extension | C12: 3.1 Promotion of Research and Facilities | D12: QlM | E12: 3.1.1 | F12: The institution Research facilities are frequently updated and there is well defined policy for promotion of research which is uploaded on the institutional website and implemented Write description in maximum of 500 words | G12: 6 | H12: 6 | I12: 21 | K12: =IF(J12>80,4,IF(AND(J12<=80,J12>60),3,IF(AND(J12<=60,J12>40),2,IF(AND(J12<=40,J12>20),1,IF(J12<=20,0))))) -> 0 | L12: =K12*H12 -> 0 | M12: =L12 -> 0 | N12: =M12/H12 -> 0 | O12: =N12+N13+N14 -> 0 | P12: =O12/I12 -> 0
A13: 11 | B13: 3. Research, Innovations and Extension | C13: 3.3 Innovation Ecosystem | D13: QlM | E13: 3.3.1 | F13: Institution has created an eco system for innovations, creation and transfer of knowledge supported by dedicated centers for research, entrepreneurship, community orientation, Incubation etc. Write description in maximum of 500 words | G13: 5 | H13: 5 | K13: =IF(J13>80,4,IF(AND(J13<=80,J13>60),3,IF(AND(J13<=60,J13>40),2,IF(AND(J13<=40,J13>20),1,IF(J13<=20,0))))) -> 0 | L13: =K13*H13 -> 0 | M13: =L13 -> 0 | N13: =M13/H13 -> 0
A14: 12 | B14: 3. Research, Innovations and Extension | C14: 3.6 Extension Activities | D14: QlM | E14: 3.6.1 | F14: Extension activities are carried out in the neighbourhood community, sensitising students to social issues, for their holistic development, and impact thereof during the last five years Describe the impact of extension activities in sensitising students to social issues and holistic development within a maximum of 500 words | G14: 10 | H14: 10 | K14: =IF(J14>80,4,IF(AND(J14<=80,J14>60),3,IF(AND(J14<=60,J14>40),2,IF(AND(J14<=40,J14>20),1,IF(J14<=20,0))))) -> 0 | L14: =K14*H14 -> 0 | M14: =L14 -> 0 | N14: =M14/H14 -> 0
A15: 13 | B15: 4. Infrastructure and Learning Resources | C15: 4.1 Physical Facilities | D15: QlM | E15: 4.1.1 | F15: The Institution has adequate infrastructure and physical facilities for teaching – learning, viz., classrooms, laboratories, computing equipment, etc. Describe the adequacy of facilities for teaching –learning as per the minimum specified requirement by statutory bodies within a maximum of 500 words | G15: 6 | H15: 10 | I15: 33 | K15: =IF(J15>80,4,IF(AND(J15<=80,J15>60),3,IF(AND(J15<=60,J15>40),2,IF(AND(J15<=40,J15>20),1,IF(J15<=20,0))))) -> 0 | L15: =K15*H15 -> 0 | M15: =L15+L16 -> 0 | N15: =M15/H15 -> 0 | O15: =N15+N17+N18+N19 -> 0 | P15: =O15/I15 -> 0
A16: 14 | B16: 4. Infrastructure and Learning Resources | C16: 4.1 Physical Facilities | D16: QlM | E16: 4.1.2 | F16: The institution has adequate facilities for cultural activities, yoga, games (indoor, outdoor) and sports. (gymnasium, yoga centre, auditorium, etc.) Describe the adequacy facilities for cultural activities, yoga, games (indoor, outdoor) and sports which include specification about area/size, year of establishment and user rate within minimum of 500 characters and maximum of 500 words | G16: 4 | K16: =IF(J16>80,4,IF(AND(J16<=80,J16>60),3,IF(AND(J16<=60,J16>40),2,IF(AND(J16<=40,J16>20),1,IF(J16<=20,0))))) -> 0 | L16: =K16*H16 -> 0
A17: 15 | B17: 4. Infrastructure and Learning Resources | C17: 4.2 Library as a Learning Resource | D17: QlM | E17: 4.2.1 | F17: Library is automated using Integrated Library Management System (ILMS) | G17: 5 | H17: 5 | K17: =IF(J17>80,4,IF(AND(J17<=80,J17>60),3,IF(AND(J17<=60,J17>40),2,IF(AND(J17<=40,J17>20),1,IF(J17<=20,0))))) -> 0 | L17: =K17*H17 -> 0 | M17: =L17 -> 0 | N17: =M17/H17 -> 0
A18: 16 | B18: 4. Infrastructure and Learning Resources | C18: 4.3 IT Infrastructure | D18: QlM | E18: 4.3.1 | F18: Institution has an IT policy covering wi-fi, cyber security, etc., and allocated budget for updating its IT facilities Describe IT facilities including Wi-Fi with date and nature of updation within a maximum of 500 words | G18: 8 | H18: 8 | K18: =IF(J18>80,4,IF(AND(J18<=80,J18>60),3,IF(AND(J18<=60,J18>40),2,IF(AND(J18<=40,J18>20),1,IF(J18<=20,0))))) -> 0 | L18: =K18*H18 -> 0 | M18: =L18 -> 0 | N18: =M18/H18 -> 0
A19: 17 | B19: 4. Infrastructure and Learning Resources | C19: 4.4 Maintenance of Campus Infrastructure | D19: QlM | E19: 4.4.2 | F19: There are established systems and procedures for maintaining and utilizing physical, academic and support facilities – laboratory, library, sports complex, computers, classrooms etc. Describe policy details of systems and procedures for maintaining and utilizing physical, academic and support facilities on the website within a minimum of 500 word and maximum of 1000 words | G19: 10 | H19: 10 | K19: =IF(J19>80,4,IF(AND(J19<=80,J19>60),3,IF(AND(J19<=60,J19>40),2,IF(AND(J19<=40,J19>20),1,IF(J19<=20,0))))) -> 0 | L19: =K19*H19 -> 0 | M19: =L19 -> 0 | N19: =M19/H19 -> 0
A20: 18 | B20: 5. Student Support and Progression | C20: 5.3 Student Participation and Activities | D20: QlM | E20: 5.3.2 | F20: Presence of an active Student Council & representation of students on academic & administrative bodies/committees of the institution Describe the Student Council activity and students role in academic & administrative bodies within a minimum of 500 characters and maximum of 500 words | G20: 10 | H20: 10 | I20: 15 | K20: =IF(J20>80,4,IF(AND(J20<=80,J20>60),3,IF(AND(J20<=60,J20>40),2,IF(AND(J20<=40,J20>20),1,IF(J20<=20,0))))) -> 0 | L20: =K20*H20 -> 0 | M20: =L20 -> 0 | N20: =M20/H20 -> 0 | O20: =N20+N21 -> 0 | P20: =O20/I20 -> 0
A21: 19 | B21: 5. Student Support and Progression | C21: 5.4 Alumni Engagement | D21: QlM | E21: 5.4.1 | F21: The Alumni Association/Chapters (registered and functional)contributes significantly to the development of the institution through financial and other support services Describe contribution of alumni association to the institution within a maximum of 500 words | G21: 5 | H21: 5 | K21: =IF(J21>80,4,IF(AND(J21<=80,J21>60),3,IF(AND(J21<=60,J21>40),2,IF(AND(J21<=40,J21>20),1,IF(J21<=20,0))))) -> 0 | L21: =K21*H21 -> 0 | M21: =L21 -> 0 | N21: =M21/H21 -> 0
A22: 20 | B22: 6. Governance, Leadership and Management | C22: 6.1 Institutional Vision and Leadership | D22: QlM | E22: 6.1.1 | F22: The governance of the institution is reflective of an effective leadership in tune with the vision and mission of the Institution Describe the vision and mission statement of the institution on the nature of governance, perspective plans and participation of the teachers in the decision making bodies of the institution within a maximum of 500 words. | G22: 5 | H22: 10 | I22: 50 | K22: =IF(J22>80,4,IF(AND(J22<=80,J22>60),3,IF(AND(J22<=60,J22>40),2,IF(AND(J22<=40,J22>20),1,IF(J22<=20,0))))) -> 0 | L22: =K22*H22 -> 0 | M22: =L22+L23 -> 0 | N22: =M22/H22 -> 0 | O22: =N22+N24+N26+N27+N29 -> 0 | P22: =O22/I22 -> 0
A23: 21 | B23: 6. Governance, Leadership and Management | C23: 6.1 Institutional Vision and Leadership | D23: QlM | E23: 6.1.2 | F23: The effective leadership is reflected in various institutional practices such as decentralization and participative management Upload a case study showing practicing decentralisation and participative management in the institution in not more than 500 words | G23: 5 | K23: =IF(J23>80,4,IF(AND(J23<=80,J23>60),3,IF(AND(J23<=60,J23>40),2,IF(AND(J23<=40,J23>20),1,IF(J23<=20,0))))) -> 0 | L23: =K23*H23 -> 0
A24: 22 | B24: 6. Governance, Leadership and Management | C24: 6.2 Strategy Development and Deployment | D24: QlM | E24: 6.2.1 | F24: The institutional Strategic/ Perspective plan is effectively deployed Describe one activity successfully implemented based on the strategic plan within a maximum of 500 words | G24: 2 | H24: 6 | K24: =IF(J24>80,4,IF(AND(J24<=80,J24>60),3,IF(AND(J24<=60,J24>40),2,IF(AND(J24<=40,J24>20),1,IF(J24<=20,0))))) -> 0 | L24: =K24*H24 -> 0 | M24: =L24+L25 -> 0 | N24: =M24/H24 -> 0
A25: 23 | B25: 6. Governance, Leadership and Management | C25: 6.2 Strategy Development and Deployment | D25: QlM | E25: 6.2.2 | F25: The functioning of the institutional bodies is effective and efficient as visible from policies, administrative setup appointment and service rules, procedures, etc. Describe the Organogram of the Institution within a maximum of 500 words | G25: 4 | K25: =IF(J25>80,4,IF(AND(J25<=80,J25>60),3,IF(AND(J25<=60,J25>40),2,IF(AND(J25<=40,J25>20),1,IF(J25<=20,0))))) -> 0 | L25: =K25*H25 -> 0
A26: 24 | B26: 6. Governance, Leadership and Management | C26: 6.3 Faculty Empowerment Strategies | D26: QlM | E26: 6.3.1 | F26: The institution has effective welfare measures for teaching and non-teaching staff and avenues for career development/ progression Provide the list of existing welfare measures for teaching and non-teaching staff in maximum of 500 words | G26: 4 | H26: 4 | K26: =IF(J26>80,4,IF(AND(J26<=80,J26>60),3,IF(AND(J26<=60,J26>40),2,IF(AND(J26<=40,J26>20),1,IF(J26<=20,0))))) -> 0 | L26: =K26*H26 -> 0 | M26: =L26 -> 0 | N26: =M26/H26 -> 0
A27: 25 | B27: 6. Governance, Leadership and Management | C27: 6.4 Financial Management and Resource Mobilization | D27: QlM | E27: 6.4.1 | F27: Institution conducts internal and external financial audits regularly Enumerate the various internal and external financial audits carried out during the last five years with the mechanism for settling audit objections within a maximum of 500 words | G27: 4 | H27: 10 | K27: =IF(J27>80,4,IF(AND(J27<=80,J27>60),3,IF(AND(J27<=60,J27>40),2,IF(AND(J27<=40,J27>20),1,IF(J27<=20,0))))) -> 0 | L27: =K27*H27 -> 0 | M27: =L27+L28 -> 0 | N27: =M27/H27 -> 0
A28: 26 | B28: 6. Governance, Leadership and Management | C28: 6.4 Financial Management and Resource Mobilization | D28: QlM | E28: 6.4.3 | F28: Institutional strategies for mobilisation of funds and the optimal utilisation of resources Describe the resource mobilisation policy and procedures of the Institution within a maximum of 500 words | G28: 6 | K28: =IF(J28>80,4,IF(AND(J28<=80,J28>60),3,IF(AND(J28<=60,J28>40),2,IF(AND(J28<=40,J28>20),1,IF(J28<=20,0))))) -> 0 | L28: =K28*H28 -> 0
A29: 27 | B29: 6. Governance, Leadership and Management | C29: 6.5 Internal Quality Assurance System (IQAS) | D29: QlM | E29: 6.5.1 | F29: Internal Quality Assurance Cell (IQAC) has contributed significantly for institutionalizing the quality assurance strategies and processes visible in terms of – Incremental improvements made for the preceding five years with regard to quality (in case of first cycle) Incremental improvements made for the preceding five years with regard to quality and post accreditation quality initiatives (second and subsequent cycles) Describe two practices institutionalized as a result of IQAC initiatives within a maximum of 500 words | G29: 10 | H29: 20 | K29: =IF(J29>80,4,IF(AND(J29<=80,J29>60),3,IF(AND(J29<=60,J29>40),2,IF(AND(J29<=40,J29>20),1,IF(J29<=20,0))))) -> 0 | L29: =K29*H29 -> 0 | M29: =L29+L30 -> 0 | N29: =M29/H29 -> 0
A30: 28 | B30: 6. Governance, Leadership and Management | C30: 6.5 Internal Quality Assurance System (IQAS) | D30: QlM | E30: 6.5.2 | F30: The institution reviews its teaching learning process, structures & methodologies of operations and learning outcomes at periodic intervals through IQAC set up as per norms Describe any two examples of institutional reviews and implementation of teaching learning reforms facilitated by the IQAC within a maximum of 500 words each | G30: 10 | K30: =IF(J30>80,4,IF(AND(J30<=80,J30>60),3,IF(AND(J30<=60,J30>40),2,IF(AND(J30<=40,J30>20),1,IF(J30<=20,0))))) -> 0 | L30: =K30*H30 -> 0
A31: 29 | B31: 7. Institutional Values and Best Practices | C31: 7.1 Institutional Values and Social Responsibilities | D31: QlM | E31: 7.1.1 | F31: Measures initiated by the Institution for the promotion of gender equity during the last five years. Describe gender equity & sensitization in curricular and co-curricular activities, facilities for women on campus etc., within 500 words | G31: 5 | H31: 23 | I31: 73 | K31: =IF(J31>80,4,IF(AND(J31<=80,J31>60),3,IF(AND(J31<=60,J31>40),2,IF(AND(J31<=40,J31>20),1,IF(J31<=20,0))))) -> 0 | L31: =K31*H31 -> 0 | M31: =L31+L32+L33+L34+L35 -> 0 | N31: =M31/H31 -> 0 | O31: =N31+N36+N37 -> 0 | P31: =O31/I31 -> 0
A32: 30 | B32: 7. Institutional Values and Best Practices | C32: 7.1 Institutional Values and Social Responsibilities | D32: QlM | E32: 7.1.3 | F32: Describe the facilities in the Institution for the management of the following types of degradable and non-degradable waste (within 500 words) 1. Solid waste management 2. Liquid waste management 3. Biomedical waste management 4. E-waste management 5. Waste recycling system 6. Hazardous chemicals and radioactive waste management | G32: 4 | K32: =IF(J32>80,4,IF(AND(J32<=80,J32>60),3,IF(AND(J32<=60,J32>40),2,IF(AND(J32<=40,J32>20),1,IF(J32<=20,0))))) -> 0 | L32: =K32*H32 -> 0
A33: 31 | B33: 7. Institutional Values and Best Practices | C33: 7.1 Institutional Values and Social Responsibilities | D33: QlM | E33: 7.1.8 | F33: Describe the Institutional efforts/initiatives in providing an inclusive environment i.e., tolerance and harmony towards cultural, regional, linguistic, communal socioeconomic and other diversities (within 500 words). | G33: 5 | K33: =IF(J33>80,4,IF(AND(J33<=80,J33>60),3,IF(AND(J33<=60,J33>40),2,IF(AND(J33<=40,J33>20),1,IF(J33<=20,0))))) -> 0 | L33: =K33*H33 -> 0
A34: 32 | B34: 7. Institutional Values and Best Practices | C34: 7.1 Institutional Values and Social Responsibilities | D34: QlM | E34: 7.1.9 | F34: Sensitization of students and employees of the Institution to the constitutional obligations: values, rights, duties and responsibilities of citizens Describe the various activities in the Institution for inculcating values for being responsible citizens as reflected in the Constitution of India within 500 words. | G34: 4 | K34: =IF(J34>80,4,IF(AND(J34<=80,J34>60),3,IF(AND(J34<=60,J34>40),2,IF(AND(J34<=40,J34>20),1,IF(J34<=20,0))))) -> 0 | L34: =K34*H34 -> 0
A35: 33 | B35: 7. Institutional Values and Best Practices | C35: 7.1 Institutional Values and Social Responsibilities | D35: QlM | E35: 7.1.11 | F35: Institution celebrates / organizes national and international commemorative days, events and festivals Describe the efforts of the Institution in celebrating /organizing national and international commemorative days, events and festivals during the last five years within 500 words | G35: 5 | K35: =IF(J35>80,4,IF(AND(J35<=80,J35>60),3,IF(AND(J35<=60,J35>40),2,IF(AND(J35<=40,J35>20),1,IF(J35<=20,0))))) -> 0 | L35: =K35*H35 -> 0
A36: 34 | B36: 7. Institutional Values and Best Practices | C36: 7.2 Best Practices | D36: QlM | E36: 7.2.1 | F36: Describe two best practices successfully implemented by the Institution as per NAAC format provided in the Manual. | G36: 30 | H36: 30 | K36: =IF(J36>80,4,IF(AND(J36<=80,J36>60),3,IF(AND(J36<=60,J36>40),2,IF(AND(J36<=40,J36>20),1,IF(J36<=20,0))))) -> 0 | L36: =K36*H36 -> 0 | M36: =L36 -> 0 | N36: =M36/H36 -> 0
A37: 35 | B37: 7. Institutional Values and Best Practices | C37: 7.3 Institutional Distinctiveness | D37: QlM | E37: 7.3.1 | F37: Portray the performance of the Institution in one area distinctive to its priority and thrust within 1000 words | G37: 20 | H37: 20 | K37: =IF(J37>80,4,IF(AND(J37<=80,J37>60),3,IF(AND(J37<=60,J37>40),2,IF(AND(J37<=40,J37>20),1,IF(J37<=20,0))))) -> 0 | L37: =K37*H37 -> 0 | M37: =L37 -> 0 | N37: =M37/H37 -> 0
B40: Row Labels | C40: Sum of KI | I40: Graphical Representation of Grade points
B41: 1.1 Curriculum Planning and Implementation | C41: 30
B42: 1.3 Curriculum Enrichment
B43: 2.2 Catering to Student Diversity | C43: 15
B44: 2.3 Teaching-Learning Process | C44: 40 | I44: Criteria Wise QlM Grade Points(0-4)
B45: 2.5 Evaluation Process and Reforms | C45: 15 | F45: Row Labels | G45: Average of Metric
B46: 2.6 Student Performance and Learning Outcomes | C46: 30 | F46: 1.1.1 | G46: 0
B47: 3.1 Promotion of Research and Facilities | C47: 6 | F47: 1.3.1 | G47: 0
B48: 3.3 Innovation Ecosystem | C48: 5 | F48: 2.2.1 | G48: 0
B49: 3.6 Extension Activities | C49: 10 | F49: 2.3.1 | G49: 0
B50: 4.1 Physical Facilities | C50: 10 | F50: 2.3.2 | G50: 0
B51: 4.2 Library as a Learning Resource | C51: 5 | F51: 2.3.4 | G51: 0
B52: 4.3 IT Infrastructure | C52: 8 | F52: 2.5.3 | G52: 0
B53: 4.4 Maintenance of Campus Infrastructure | C53: 10 | F53: 2.6.1 | G53: 0
B54: 5.3 Student Participation and Activities | C54: 10 | F54: 2.6.2 | G54: 0
B55: 5.4 Alumni Engagement | C55: 5 | F55: 3.1.1 | G55: 0
B56: 6.1 Institutional Vision and Leadership | C56: 10 | F56: 3.3.1 | G56: 0
B57: 6.2 Strategy Development and Deployment | C57: 6 | F57: 3.6.1 | G57: 0
... B62: 7.2 Best Practices | C62: 30 | F62: 4.4.2 | G62: 0
B63: 7.3 Institutional Distinctiveness | C63: 20 | F63: 5.3.2 | G63: 0 | I63: Key Indicator Wise QlM Grade Points(0-4)
B64: Grand Total | C64: 322 | F64: 5.4.1 | G64: 0
F65: 6.1.1 | G65: 0
F66: 6.1.2 | G66: 0
F67: 6.2.1 | G67: 0
F68: 6.2.2 | G68: 0
F69: 6.3.1 | G69: 0
F70: 6.4.1 | G70: 0
F71: 6.4.3 | G71: 0
F72: 6.5.1 | G72: 0
F73: 6.5.2 | G73: 0
F74: 7.1.1 | G74: 0
F75: 7.1.11 | G75: 0
F76: 7.1.3 | G76: 0
... F81: Grand Total | G81: 0
F84: Row Labels | G84: Average of Metric
F85: 1.1 Curriculum Planning and Implementation | G85: 0
F86: 1.3 Curriculum Enrichment | G86: 0 | I86: Metric Wise QlM Grade Points(0-4)
F87: 2.2 Catering to Student Diversity | G87: 0
F88: 2.3 Teaching-Learning Process | G88: 0
F89: 2.5 Evaluation Process and Reforms | G89: 0
F90: 2.6 Student Performance and Learning Outcomes | G90: 0
F91: 3.1 Promotion of Research and Facilities | G91: 0
F92: 3.3 Innovation Ecosystem | G92: 0
F93: 3.6 Extension Activities | G93: 0
F94: 4.1 Physical Facilities | G94: 0
F95: 4.2 Library as a Learning Resource | G95: 0
F96: 4.3 IT Infrastructure | G96: 0
F97: 4.4 Maintenance of Campus Infrastructure | G97: 0
F98: 5.3 Student Participation and Activities | G98: 0
... F108: Grand Total | G108: 0
F110: Row Labels | G110: Average of Metric
F111: 1. Curricular Aspects | G111: 0
F112: 2. Teaching-Learning and Evaluation | G112: 0
F113: 3. Research, Innovations and Extension | G113: 0
F114: 4. Infrastructure and Learning Resources | G114: 0
F115: 5. Student Support and Progression | G115: 0
F116: 6. Governance, Leadership and Management | G116: 0
F117: 7. Institutional Values and Best Practices | G117: 0
F118: Grand Total | G118: 0

Sheet 35 Qlm-GS (2)
A1: Quantitative Grade Sheet
A2: Name of the Institution: | C2: ='Autonomous 107m'!$J$2 -> Institute Name
A3: Type of the Institution: | C3: ='Autonomous 107m'!K$1 -> Autonomous
A4: Dates of Visit:
A5: No | B5: Criteria | C5: Weightage (Wi | D5: Criterion-wise weighted Grade Point (CrWGPi) | E5: Criterion- wise Grade Point Averages (CrWGPi/Wi) | G5: Range of Institutional Cumulative Grade Point Average (CGPA) | H5: Letter Grade | I5: Status
A6: 1 | B6: Curricular Aspects | C6: 30 | D6: =SUM('Ql (35m)'!O3:O4) -> 0 | E6: =D6/C6 -> 0 | G6: 3.51-4.00 | H6: A++ | I6: Accredited
A7: 2 | B7: Teaching-learning and Evaluation | C7: 100 | D7: =SUM('Ql (35m)'!O5:O11) -> 0 | E7: =D7/C7 -> 0 | G7: 3.26-3.500 | H7: A+ | I7: Accredited
A8: 3 | B8: Research, Innovations and Extension | C8: 21 | D8: =SUM('Ql (35m)'!O12:O14) -> 0 | E8: =D8/C8 -> 0 | G8: 3.01-3.25 | H8: A | I8: Accredited
A9: 4 | B9: Infrastructure and Learning Resources | C9: 33 | D9: =SUM('Ql (35m)'!O15:O19) -> 0 | E9: =D9/C9 -> 0 | G9: 2.76-3.00 | H9: B++ | I9: Accredited
A10: 5 | B10: Student Support and Progression | C10: 15 | D10: =SUM('Ql (35m)'!O20:O21) -> 0 | E10: =D10/C10 -> 0 | G10: 2.51-2.75 | H10: B+ | I10: Accredited
A11: 6 | B11: Governance, Leadership and Management | C11: 50 | D11: =SUM('Ql (35m)'!O22:O30) -> 0 | E11: =D11/C11 -> 0 | G11: 2.01-2.50 | H11: B | I11: Accredited
A12: 7 | B12: Institutional Values and Best Practices | C12: 73 | D12: =SUM('Ql (35m)'!O31:O37) -> 0 | E12: =D12/C12 -> 0 | G12: 1.51-2.00 | H12: C | I12: Accredited
A13: Total | C13: =SUM(C6:C12) -> 322 | D13: =SUM(D6:D12) -> 0 | E13: =D13/C13 -> 0 | G13: ≤ 1.50 | H13: D | I13: Not Accredited
A15: =D13/C13 -> 0
A17: =IF(AND($A$15<=4,$A$15>=3.51),"A++",IF(AND($A$15<=3.5,$A$15>=3.26),"A+",IF(AND($A$15<=3.25,$A$15>3.01),"A",IF(AND($A$15<=3,$A$15>=2.76),"B++",IF(AND($A$15<=2.75,$A$15>=2.51),"B+",IF(AND($A$15<=2.5,$A$15>=2.01),"B",IF(AND($A$15<=2,$A$15>=1.51),"C","D"))))))) -> D
A20: Quantitative Grade Sheet
A21: Name of the Institution: | C21: ='Autonomous 107m'!$J$2 -> Institute Name
A22: Type of the Institution: | C22: ='Autonomous 107m'!$K$1 -> Autonomous
A23: Dates of Visit:
A24: No | B24: Criteria and Key Indicators | C24: Key Indicator Weightage (Wi) | D24: Key Indicator Wise Weighted Grade Points (KIWGP)i
A25: Criterion 1: Curricular Aspects
A26: 1.1 | B26: Curriculum Planning and Implementation | C26: 20 | D26: =SUM('Ql (35m)'!M7) -> 0
A27: 1.3 | B27: Curriculum Enrichment | C27: 10 | D27: =SUM('Ql (35m)'!M8) -> 0
A28: Total | C28: =SUM(C26:C27) -> 30 | D28: =SUM(D26:D27) -> 0
A29: =D28/C28 -> 0
A30: Criterion 2: Teaching-learning and Evaluation
A31: 2.2 | B31: Catering to Student Diversity | C31: 15 | D31: =SUM('Ql (35m)'!M10) -> 0
A32: 2.3 | B32: Teaching-Learning Process | C32: 40 | D32: =SUM('Ql (35m)'!M11) -> 0
A33: 2.5 | B33: Evaluation Process and Reforms | C33: 15 | D33: =SUM('Ql (35m)'!M12) -> 0
A34: 2.6 | B34: Student Performance and Learning Outcomes | C34: 30 | D34: =SUM('Ql (35m)'!M12) -> 0
A35: Total | C35: =SUM(C31:C34) -> 100 | D35: =SUM(D31:D34) -> 0
A36: =D35/C35 -> 0
A37: Criterion 3: Research, Innovations and Extension
A38: 3.1 | B38: Promotion of Research and Facilities | C38: 6 | D38: =SUM('Ql (35m)'!M13) -> 0
A39: 3.3 | B39: Innovation Ecosystem | C39: 5 | D39: =SUM('Ql (35m)'!M14) -> 0
A40: 3.6 | B40: Extension Activities | C40: 10 | D40: =SUM('Ql (35m)'!M14:M15) -> 0
A41: Total | C41: =SUM(C38:C40) -> 21 | D41: =SUM(D38:D40) -> 0
A42: =D41/C41 -> 0
A43: Criterion 4: Infrastructure and Learning Resources
A44: 4.1 | B44: Physical Facilities | C44: 10 | D44: =SUM('Ql (35m)'!M16) -> 0
A45: 4.2 | B45: Library as a Learning Resource | C45: 5 | D45: =SUM('Ql (35m)'!M17) -> 0
A46: 4.3 | B46: IT Infrastructure | C46: 8 | D46: =SUM('Ql (35m)'!M18) -> 0
A47: 4.4 | B47: Maintenance of Campus Infrastructure | C47: 10 | D47: =SUM('Ql (35m)'!M18) -> 0
A48: Total | C48: =SUM(C44:C47) -> 33 | D48: =SUM(D44:D47) -> 0
A49: =D48/C48 -> 0
A50: Criterion 5: Student Support and Progression
A51: 5.3 | B51: Student Participation and Activities | C51: 10 | D51: =SUM('Ql (35m)'!M19) -> 0
A52: 5.4 | B52: Alumni Engagement | C52: 5 | D52: =SUM('Ql (35m)'!M20) -> 0
A53: Total | C53: =SUM(C51:C52) -> 15 | D53: =SUM(D51:D52) -> 0
A54: =D53/C53 -> 0
A55: Criterion 6: Governance, Leadership and Management
A56: 6.1 | B56: Institutional Vision and Leadership | C56: 10 | D56: =SUM('Ql (35m)'!M20) -> 0
A57: 6.2 | B57: Strategy Development and Development | C57: 6 | D57: =SUM('Ql (35m)'!M21) -> 0
A58: 6.3 | B58: Faculty Empowerment Strategies | C58: 4 | D58: =SUM('Ql (35m)'!M22) -> 0
A59: 6.4 | B59: Financial Management and Resource Mobilization | C59: 10 | D59: =SUM('Ql (35m)'!M23) -> 0
A60: 6.5 | B60: Internal Quality Assurance System | C60: 20 | D60: =SUM('Ql (35m)'!M24) -> 0
A61: Total | C61: =SUM(C56:C60) -> 50 | D61: =SUM(D56:D58) -> 0
A62: =D61/C61 -> 0
A63: Criterion 7: Institutional Values and Best Practices
A64: 7.1 | B64: Institutional Values and Social Responsibilities | C64: 23 | D64: =SUM('Ql (35m)'!M44:M45) -> 0
A65: 7.2 | B65: Best Practices | C65: 30 | D65: =SUM('Ql (35m)'!M46) -> 0
A66: 7.3 | B66: Institutional Distinctiveness | C66: 20 | D66: =SUM('Ql (35m)'!M47) -> 0
A67: Total | C67: =SUM(C64:C66) -> 73 | D67: =SUM(D64:D64) -> 0
A68: =D67/C67 -> 0
A69: Grand Total | C69: =SUM(C67,C61,C53,C48,C41,C35,C28) -> 322 | D69: =SUM(D67,D61,D53,D48,D41,D35,D28) -> 0
A70: =D69/C69 -> 0
A71: =IF(AND($A$70<=4,$A$70>=3.51),"A++",IF(AND($A$70<=3.5,$A$70>=3.26),"A+",IF(AND($A$70<=3.25,$A$70>3.01),"A",IF(AND($A$70<=3,$A$70>=2.76),"B++",IF(AND($A$70<=2.75,$A$70>=2.51),"B+",IF(AND($A$70<=2.5,$A$70>=2.01),"B",IF(AND($A$70<=2,$A$70>=1.51),"C","D"))))))) -> D

Sheet 21m-GS
A1: Qualitative Grade Sheet
A2: Name of the Institution:
A3: Type of the Institution:
A4: Dates of Visit:
A5: No | B5: Criteria | C5: Weightage (Wi | D5: Criterion-wise weighted Grade Point (CrWGPi) | E5: Criterionwise Grade Point Averages (CrWGPi/Wi) | G5: Range of Institutional Cumulative Grade Point Average (CGPA) | H5: Letter Grade | I5: Status
A6: 1 | B6: Curricular Aspects | C6: 30 | D6: =SUM('Ql (35m)'!O3:O4) -> 0 | E6: =D6/C6 -> 0 | G6: 3.51-4.00 | H6: A++ | I6: Accredited
A7: 2 | B7: Teaching-learning and Evaluation | C7: 125 | D7: =SUM('Ql (35m)'!O5:O7) -> 0 | E7: =D7/C7 -> 0 | G7: 3.26-3.500 | H7: A+ | I7: Accredited
A8: 3 | B8: Research, Innovations and Extension | C8: 30 | D8: =SUM('Ql (35m)'!O8:O10) -> 0 | E8: =D8/C8 -> 0 | G8: 3.01-3.25 | H8: A | I8: Accredited
A9: 4 | B9: Infrastructure and Learning Resources | C9: 60 | D9: =SUM('Ql (35m)'!O11:O13) -> 0 | E9: =D9/C9 -> 0 | G9: 2.76-3.00 | H9: B++ | I9: Accredited
A10: 5 | B10: Student Support and Progression | C10: 10 | D10: =SUM('Ql (35m)'!O14) -> 0 | E10: =D10/C10 -> 0 | G10: 2.51-2.75 | H10: B+ | I10: Accredited
A11: 6 | B11: Governance, Leadership and Management | C11: 54 | D11: =SUM('Ql (35m)'!O15:O19) -> 0 | E11: =D11/C11 -> 0 | G11: 2.01-2.50 | H11: B | I11: Accredited
A12: 7 | B12: Institutional Values and Best Practices | C12: 70 | D12: =SUM('Ql (35m)'!O20:O23) -> 0 | E12: =D12/C12 -> 0 | G12: 1.51-2.00 | H12: C | I12: Accredited
C13: =SUM(C6:C12) -> 379 | D13: =SUM(D6:D12) -> 0 | E13: =D13/C13 -> 0 | G13: ≤ 1.50 | H13: D | I13: Not Accredited
D14: Grade | E14: =IF(AND($E$13<=4,$E$13>=3.51),"A++",IF(AND($E$13<=3.5,$E$13>=3.26),"A+",IF(AND($E$13<=3.25,$E$13>3.01),"A",IF(AND($E$13<=3,$E$13>=2.76),"B++",IF(AND($E$13<=2.75,$E$13>=2.51),"B+",IF(AND($E$13<=2.5,$E$13>=2.01),"B",IF(AND($E$13<=2,$E$13>=1.51),"C","D"))))))) -> D
A16: Qualitative Grade Sheet
A17: Name of the Institution:
A18: Type of the Institution:
A19: Dates of Visit:
A20: No | B20: Criteria and Key Indicators | C20: Key Indicator Weightage (Wi) | D20: Key Indicator Wise Weighted Grade Points (KIWGP)i | E20: Key Indicator wise Grade Point Averages (CrWGPi/Wi)
A21: Criterion 1: Curricular Aspects
A22: 1.1 | B22: Curriculum Planning and Implementation | C22: 20 | D22: =SUM('Ql (35m)'!M3) -> 0
A23: 1.3 | B23: Curriculum Enrichment | C23: 10 | D23: =SUM('Ql (35m)'!M4) -> 0
C24: =SUM(C22:C23) -> 30 | D24: =SUM(D22:D23) -> 0
D25: Grade | E25: =IF(AND($E$24<=4,$E$24>=3.51),"A++",IF(AND($E$24<=3.5,$E$24>=3.26),"A+",IF(AND($E$24<=3.25,$E$24>3.01),"A",IF(AND($E$24<=3,$E$24>=2.76),"B++",IF(AND($E$24<=2.75,$E$24>=2.51),"B+",IF(AND($E$24<=2.5,$E$24>=2.01),"B",IF(AND($E$24<=2,$E$24>=1.51),"C","D"))))))) -> D
A26: Criterion 2: Teaching-learning and Evaluation
A27: 2.3 | B27: Teaching- Learning Process | C27: 40 | D27: =SUM('Ql (35m)'!M5) -> 0
A28: 2.5 | B28: Evaluation Process and Reforms | C28: 40 | D28: =SUM('Ql (35m)'!M6) -> 0
A29: 2.6 | B29: Student Performance and Learning Outcomes | C29: 45 | D29: =SUM('Ql (35m)'!M7) -> 0
C30: =SUM(C27:C29) -> 125 | D30: =SUM(D27:D29) -> 0
D31: Grade | E31: =IF(AND($E$30<=4,$E$30>=3.51),"A++",IF(AND($E$30<=3.5,$E$30>=3.26),"A+",IF(AND($E$30<=3.25,$E$30>3.01),"A",IF(AND($E$30<=3,$E$30>=2.76),"B++",IF(AND($E$30<=2.75,$E$30>=2.51),"B+",IF(AND($E$30<=2.5,$E$30>=2.01),"B",IF(AND($E$30<=2,$E$30>=1.51),"C","D"))))))) -> D
A32: Criterion 3: Research, Innovations and Extension
A33: 3.2 | B33: Innovation Ecosystem | C33: 10 | D33: =SUM('Ql (35m)'!M8) -> 0
A34: 3.4 | B34: Extension Activities | C34: 20 | D34: =SUM('Ql (35m)'!M9:M10) -> 0
C35: =SUM(C33:C34) -> 30 | D35: =SUM(D33:D34) -> 0
D36: Grade | E36: =IF(AND($E$41<=4,$E$41>=3.51),"A++",IF(AND($E$41<=3.5,$E$41>=3.26),"A+",IF(AND($E$41<=3.25,$E$41>3.01),"A",IF(AND($E$41<=3,$E$41>=2.76),"B++",IF(AND($E$41<=2.75,$E$41>=2.51),"B+",IF(AND($E$41<=2.5,$E$41>=2.01),"B",IF(AND($E$41<=2,$E$41>=1.51),"C","D"))))))) -> D
A37: Criterion 4: Infrastructure and Learning Resources
A38: 4.1 | B38: Physical Facilities | C38: 20 | D38: =SUM('Ql (35m)'!M11) -> 0
A39: 4.2 | B39: Library as a Learning Resource | C39: 20 | D39: =SUM('Ql (35m)'!M12) -> 0
A40: 4.3 | B40: IT Infrastructure | C40: 20 | D40: =SUM('Ql (35m)'!M13) -> 0
C41: =SUM(C38:C40) -> 60 | D41: =SUM(D38:D40) -> 0
D42: Grade | E42: =IF(AND($E$41<=4,$E$41>=3.51),"A++",IF(AND($E$41<=3.5,$E$41>=3.26),"A+",IF(AND($E$41<=3.25,$E$41>3.01),"A",IF(AND($E$41<=3,$E$41>=2.76),"B++",IF(AND($E$41<=2.75,$E$41>=2.51),"B+",IF(AND($E$41<=2.5,$E$41>=2.01),"B",IF(AND($E$41<=2,$E$41>=1.51),"C","D"))))))) -> D
A43: Criterion 5: Student Support and Progression
A44: 5.4 | B44: Alumni Engagement | C44: 10 | D44: =SUM('Ql (35m)'!M14) -> 0
C45: =SUM(C44:C44) -> 10 | D45: =SUM(D44:D44) -> 0
D46: Grade | E46: =IF(AND($E$45<=4,$E$45>=3.51),"A++",IF(AND($E$45<=3.5,$E$45>=3.26),"A+",IF(AND($E$45<=3.25,$E$45>3.01),"A",IF(AND($E$45<=3,$E$45>=2.76),"B++",IF(AND($E$45<=2.75,$E$45>=2.51),"B+",IF(AND($E$45<=2.5,$E$45>=2.01),"B",IF(AND($E$45<=2,$E$45>=1.51),"C","D"))))))) -> D
A47: Criterion 6: Governance, Leadership and Management
A48: 6.1 | B48: Institutional Vision and Leadership | C48: 10 | D48: =SUM('Ql (35m)'!M15) -> 0
A49: 6.2 | B49: Strategy Development and Development | C49: 6 | D49: =SUM('Ql (35m)'!M16) -> 0
A50: 6.3 | B50: Faculty Empowerment Strategies | C50: 8 | D50: =SUM('Ql (35m)'!M17) -> 0
A51: 6.4 | B51: Financial Management and Resource Mobilization | C51: 15 | D51: =SUM('Ql (35m)'!M18) -> 0
A52: 6.5 | B52: Internal Quality Assurance System | C52: 15 | D52: =SUM('Ql (35m)'!M19) -> 0
C53: =SUM(C48:C52) -> 54 | D53: =SUM(D48:D52) -> 0
D54: Grade | E54: =IF(AND($E$53<=4,$E$53>=3.51),"A++",IF(AND($E$53<=3.5,$E$53>=3.26),"A+",IF(AND($E$53<=3.25,$E$53>3.01),"A",IF(AND($E$53<=3,$E$53>=2.76),"B++",IF(AND($E$53<=2.75,$E$53>=2.51),"B+",IF(AND($E$53<=2.5,$E$53>=2.01),"B",IF(AND($E$53<=2,$E$53>=1.51),"C","D"))))))) -> D
A55: Criterion 7: Institutional Values and Best Practices
A56: 7.1 | B56: Institutional Values and Social Responsibilities | C56: 20 | D56: =SUM('Ql (35m)'!M20:M21) -> 0
A57: 7.2 | B57: Best Practices | C57: 30 | D57: =SUM('Ql (35m)'!M22) -> 0
A58: 7.3 | B58: Institutional Distinctiveness | C58: 20 | D58: =SUM('Ql (35m)'!M23) -> 0
C59: =SUM(C56:C58) -> 70 | D59: =SUM(D56:D58) -> 0
D60: Grade | E60: =IF(AND($E$59<=4,$E$59>=3.51),"A++",IF(AND($E$59<=3.5,$E$59>=3.26),"A+",IF(AND($E$59<=3.25,$E$59>3.01),"A",IF(AND($E$59<=3,$E$59>=2.76),"B++",IF(AND($E$59<=2.75,$E$59>=2.51),"B+",IF(AND($E$59<=2.5,$E$59>=2.01),"B",IF(AND($E$59<=2,$E$59>=1.51),"C","D"))))))) -> D
